Workbook
Name Avance: {"MO(BASE)",#N/A,FALSE,"MO(BASE)";"MO(BASE)1",#N/A,FALSE,"MO(BASE)";"MO(BASE)2",#N/A,FALSE,"MO(BASE)"}
Name dh_mes: #REF!
Name dot_agua: #REF!
Name dot_ap: #REF!
Name dot_dist: #REF!
Name dot_mina: #REF!
Name dot_oca: #REF!
Name dot_per: #REF!
Name dotacion: #REF!
Name dotacion_CMDIC: #REF!
Name Dotación_Distribución: #REF!
Name Examenes: #REF!,#REF!,#REF!,#REF!,#REF!,#REF!,#REF!,#REF!,#REF!,#REF!,#REF!,#REF!,#REF!,#REF!,#REF!,#REF!,#REF!,#REF!,#REF!,#REF!,#REF!,#REF!,#REF!,#REF!,#REF!,#REF!,#REF!,#REF!,#REF!
Name hd: #REF!
Name IPC: #REF!
Name IPCB: #REF!
Name MACU: #N/A
Name mes: #REF!
Name NvsASD: "V2002-01-31"
Name NvsAutoDrillOk: "VN"
Name NvsEndTime: 37298.8705142361
Name NvsInstSpec: "%"
Name NvsLayoutType: "M3"
Name NvsNplSpec: "%,X,RZT.ACCOUNT.,CZF.."
Name NvsPanelEffdt: "V1901-01-01"
Name NvsPanelSetid: "VGRALS"
Name NvsReqBU: "VEL011"
Name NvsReqBUOnly: "VY"
Name NvsTransLed: "VN"
Name NvsTreeASD: "V2002-01-31"
Name NvsValTbl.BUSINESS_UNIT: "BUS_UNIT_TBL_GL"
Name pc_agua: #REF!
Name pc_ap: #REF!
Name pc_dist: #REF!
Name pc_mina: #REF!
Name Personal_STN: #REF!,#REF!,#REF!,#REF!,#REF!,#REF!,#REF!,#REF!,#REF!,#REF!,#REF!,#REF!,#REF!,#REF!
Name USD: #REF!
Name VBMEL: #REF!,#REF!,#REF!,#REF!,#REF!,#REF!,#REF!,#REF!,#REF!,#REF!,#REF!,#REF!,#REF!,#REF!,#REF!,#REF!,#REF!,#REF!,#REF!,#REF!,#REF!,#REF!,#REF!,#REF!,#REF!,#REF!,#REF!,#REF!

Sheet Dashboard_Ejecutivo
B2: DASHBOARD EJECUTIVO - CONTROL INTEGRAL DEL PROYECTO
B4: Proyecto: Aumento Capacidad BP1 SE O'Higgins
B5: Fecha de Corte: 26 de Mayo 2026
B8: 1. SALUD FINANCIERA (EVM & CURVA S)
B9: Presupuesto Total (BAC) | C9: =+Resumen_Control_Costos!C14 -> 2.5302808e+08
B10: Costo Real Incurrido (AC) | C10: =+Resumen_Control_Costos!D14 -> 200000
B11: Estimación al Cierre (EAC) | C11: =+Resumen_Control_Costos!F14 -> 2.5302808e+08
B12: Índice Desempeño Costo (CPI) | C12: =+Resumen_Control_Costos!C24 -> 2.4
B13: Índice Desempeño Crono (SPI) | C13: =+Resumen_Control_Costos!C23 -> Pendiente datos
B14: Variación al Término (VAC) | C14: =+Resumen_Control_Costos!C27 -> 199997.6
B16: 2. RECURSOS HUMANOS Y PRODUCTIVIDAD | M16: Recurso | N16: HH Plan | O16: HH Real
B17: Dotación Total (Organigrama) | C17: =COUNTA(RRHH_Control!A2:A19) -> 18 | M17: May | N17: 1500 | O17: 1250
B18: Personal con Examenes Aprobados | C18: =COUNTIFS(RRHH_Control!E:E, "Aprobado", RRHH_Control!F:F, "Aprobado") -> 16 | M18: Jun | N18: 2000 | O18: 0
B19: Personal con Carta Oferta / Anexo | C19: =COUNTIFS(RRHH_Control!S:S, "Aprobado") + COUNTIFS(RRHH_Control!U:U, "Aprobado") -> 15
B20: Personal 100% Acreditado | C20: =COUNTIF(RRHH_Control!AP2:AP99, 3) -> 0
B21: Promedio Avance HDR | C21: =AVERAGE(HDR_Matriz!BI2:BI100) -> 0
B22: Horas Hombre (HH) Consumidas | C22: =SUM(Curva_S_Avance!H22) -> 1250
B23: Riesgos Abiertos | C23: =COUNTIF('Matriz de Riesgos'!I3:I101, "Abierto") -> 0
B24: Avance Carpeta de Arranque STN (N°) | C24: =COUNTIF('Carpeta de Arranque_STN'!L14:L50, 1) -> 1
B25: Avance Carpeta de Arranque STN (%) | C25: =IFERROR(AVERAGE('Carpeta de Arranque_STN'!L14:L50), 0) -> 0.375
B27: 3. CALIDAD (QA/QC) Y COMPROMISOS
B28: Tareas Compromisos Totales | C28: 9
B29: Protocolos QA/QC Generados | C29: 0
B30: Protocolos QA/QC Aprobados MEL | C30: 0
B31: % Liberación QA/QC | C31: =IF(D22>0,D23/D22,0) -> 0
B32: Procedimientos a Generar | C32: Vincular
B33: % Procedimientos Generados | C33: Vincular
B35: 4. EQUIPOS RODANTES Y TOPOGRAFÍA
B36: Total Equipos y Vehículos | C36: =COUNTA(Equipos_y_Flota!A2:A99) -> 8
B37: Equipos 100% Acreditados | C37: =COUNTIF(Equipos_y_Flota!P2:P99, 3) -> 0
B38: Avance Promedio Flota | C38: Vincular
B39: N° de Camionetas | C39: Vincular
B40: % de Avance en Acreditación Camionetas | C40: Vincular
B41: N° Camión Pluma | C41: Vincular
B42: % de Avance en Acreditación Camion | C42: Vincular
B44: 5. DOCUMENTACION CONTRACTUAL
B45: Orden de Servicio STN | C45: OK
B46: Contrato KELTI / STN | C46: NA
B47: Contrato STN creado en PMF | C47: OK
B48: Orden de Servicio CTC Global | C48: OK
B49: Contrato CTC creado en PMF | C49: OK

Sheet Resumen_Control_Costos
B2: CONTROL DE COSTOS Y GESTIÓN DEL VALOR GANADO (EVM)
B5: PRESUPUESTO BASE (BAC) Y FORECAST POR CUENTA
B6: Cuenta / Item | C6: Presupuesto (BAC) | D6: Real a la Fecha (AC) | E6: Comprometido | F6: Estimación a Término (EAC) | G6: Desviación al Cierre (VAC)
B7: RRHH | C7: =+Control_Presupuesto!C2 -> 62700000 | D7: =+Control_Presupuesto!I2 -> 0 | E7: =+Control_Presupuesto!J2 -> 0 | F7: =IFERROR(C7, "Pendiente datos") -> 62700000 | G7: =IFERROR(C7-F7, "Pendiente datos") -> 0
B8: MATERIALES | C8: =+Control_Presupuesto!C12 -> 2956644.4 | D8: =+Control_Presupuesto!I12 -> 0 | E8: =+Control_Presupuesto!J12 -> 0 | F8: =IFERROR(C8, "Pendiente datos") -> 2956644.4 | G8: =IFERROR(C8-F8, "Pendiente datos") -> 0
B9: EQUIPOS MAQUINARIA | C9: =+Control_Presupuesto!C16 -> 57720797 | D9: =+Control_Presupuesto!I16 -> 0 | E9: =+Control_Presupuesto!J16 -> 0 | F9: =IFERROR(C9, "Pendiente datos") -> 57720797 | G9: =IFERROR(C9-F9, "Pendiente datos") -> 0
B10: SUBCONTRATOS | C10: =+Control_Presupuesto!C22 -> 4510650 | D10: =+Control_Presupuesto!I22 -> 0 | E10: =+Control_Presupuesto!J22 -> 0 | F10: =IFERROR(C10, "Pendiente datos") -> 4510650 | G10: =IFERROR(C10-F10, "Pendiente datos") -> 0
B11: CTC GLOBAL | C11: =+Control_Presupuesto!C26 -> 17980000 | D11: =+Control_Presupuesto!I26 -> 0 | E11: =+Control_Presupuesto!J26 -> 0 | F11: =IFERROR(C11, "Pendiente datos") -> 17980000 | G11: =IFERROR(C11-F11, "Pendiente datos") -> 0
B12: GASTOS GENERALES | C12: =+Control_Presupuesto!C30 -> 80209991 | D12: =+Control_Presupuesto!I30 -> 200000 | E12: =+Control_Presupuesto!J30 -> 0 | F12: =IFERROR(C12, "Pendiente datos") -> 80209991 | G12: =IFERROR(C12-F12, "Pendiente datos") -> 0
B13: IMPREVISTOS | C13: =+Control_Presupuesto!C37 -> 26950000 | D13: =+Control_Presupuesto!I37 -> 0 | E13: =+Control_Presupuesto!J37 -> 0 | F13: =IFERROR(C13, "Pendiente datos") -> 26950000 | G13: =IFERROR(C13-F13, "Pendiente datos") -> 0
B14: TOTAL COSTOS | C14: =IFERROR(SUM(C7:C13), "Pendiente datos") -> 2.5302808e+08 | D14: =IFERROR(SUM(D7:D13), "Pendiente datos") -> 200000 | E14: =IFERROR(SUM(E7:E13), "Pendiente datos") -> 0 | F14: =IFERROR(SUM(F7:F13), "Pendiente datos") -> 2.5302808e+08 | G14: =IFERROR(SUM(G7:G13), "Pendiente datos") -> 0
B17: INDICADORES CLAVE DE DESEMPEÑO (KPIs EVM - PMI) - MAYO 2026
B18: Indicador | C18: Valor | D18: Descripción
B19: Valor Planeado (PV) | C19: =IFERROR(253028082 * Curva_S_Avance!C7, "Pendiente datos") -> 30363370 | D19: Presupuesto autorizado asignado al trabajo programado.
B20: Valor Ganado (EV) | C20: =IFERROR(253028082 * Curva_S_Avance!C9, "Pendiente datos") -> 12651404 | D20: Medida del trabajo realizado en términos del presupuesto.
B21: Costo Real (AC) | C21: =IFERROR(D14, "Pendiente datos") -> 200000 | D21: Costo incurrido por el trabajo realizado a la fecha.
B22: Presupuesto (BAC) | C22: =IFERROR(C14, "Pendiente datos") -> 2.5302808e+08 | D22: Presupuesto total al finalizar.
B23: Índice Desempeño Cronograma (SPI) | C23: =IFERROR(C19/C18, "Pendiente datos") -> Pendiente datos | D23: EV / PV (>1 es adelantado, <1 atrasado)
B24: Índice Desempeño Costo (CPI) | C24: =IFERROR(C19/C20, "Pendiente datos") -> 2.4 | D24: EV / AC (>1 es ahorro, <1 sobrecosto)
B25: Estimación a Término (EAC) | C25: =IFERROR(C21/C23, "Pendiente datos") -> Pendiente datos | D25: Costo total estimado al finalizar el proyecto (BAC/CPI).
B26: Estimación para Terminar (ETC) | C26: =IFERROR(C24-C20, "Pendiente datos") -> -12651402 | D26: Costo esperado para terminar el trabajo restante (EAC - AC).
B27: Variación al Término (VAC) | C27: =IFERROR(C21-C24, "Pendiente datos") -> 199997.6 | D27: Déficit o superávit proyectado (BAC - EAC).

Sheet Control_Presupuesto
A1: WBS | B1: Descripción de la Partida | C1: Presupuesto Base (BAC) | D1: Gasto Real Mayo 2026 | E1: Gasto Real Junio 2026 | F1: Gasto Real Julio 2026 | G1: Gasto Real Agosto 2026 | H1: Gasto Real Sept 2026 | I1: Costo Real Acumulado (AC) | J1: Comprometido (OC) | K1: Costo Total Actual | L1: Presupuesto Disponible | M1: Avance Real (%) | N1: Valor Ganado (EV) | O1: Desviación a la fecha (CV) | P1: Estimación p/Terminar (ETC) | Q1: Forecast (EAC) | R1: Desviación Proyectada (VAC) | S1: Comentarios
A2: 1.0 | B2: RRHH DIRECTO E INDIRECTO | C2: =SUM(C3:C11) -> 62700000 | D2: =SUM(D3:D11) -> 0 | E2: =SUM(E3:E11) -> 0 | F2: =SUM(F3:F11) -> 0 | G2: =SUM(G3:G11) -> 0 | H2: =SUM(H3:H11) -> 0 | I2: =SUM(D2:G2) -> 0 | J2: 0 | K2: =I2+J2 -> 0 | L2: =C2-K2 -> 62700000 | M2: 0 | N2: =C2*M2 -> 0 | O2: =N2-I2 -> 0 | P2: 0 | Q2: =K2+P2 -> 0 | R2: =C2-Q2 -> 62700000
A3: 1.1 | B3: Supervisor de Terreno | C3: 6900000 | D3: =SUMIFS(Costos_Extracontables!$D:$D, Costos_Extracontables!$E:$E, $B3, Costos_Extracontables!$C:$C, ">=2026-05-01", Costos_Extracontables!$C:$C, "<=2026-05-31") -> 0 | E3: =SUMIFS(Costos_Extracontables!$D:$D, Costos_Extracontables!$E:$E, $B3, Costos_Extracontables!$C:$C, ">=2026-06-01", Costos_Extracontables!$C:$C, "<=2026-06-31") -> 0 | I3: =SUM(D3:G3) -> 0 | J3: 0 | K3: =I3+J3 -> 0 | L3: =C3-K3 -> 6900000 | M3: 0 | N3: =C3*M3 -> 0 | O3: =N3-I3 -> 0 | P3: 0 | Q3: =K3+P3 -> 0 | R3: =C3-Q3 -> 6900000
A4: 1.2 | B4: Administrativo de Obras y RRLL | C4: 4200000 | D4: =SUMIFS(Costos_Extracontables!$D:$D, Costos_Extracontables!$E:$E, $B4, Costos_Extracontables!$C:$C, ">=2026-05-01", Costos_Extracontables!$C:$C, "<=2026-05-31") -> 0 | E4: =SUMIFS(Costos_Extracontables!$D:$D, Costos_Extracontables!$E:$E, $B4, Costos_Extracontables!$C:$C, ">=2026-06-01", Costos_Extracontables!$C:$C, "<=2026-06-31") -> 0 | I4: =SUM(D4:G4) -> 0 | J4: 0 | K4: =I4+J4 -> 0 | L4: =C4-K4 -> 4200000 | M4: 0 | N4: =C4*M4 -> 0 | O4: =N4-I4 -> 0 | P4: 0 | Q4: =K4+P4 -> 0 | R4: =C4-Q4 -> 4200000
A5: 1.3 | B5: Topógrafo | C5: 5400000 | D5: =SUMIFS(Costos_Extracontables!$D:$D, Costos_Extracontables!$E:$E, $B5, Costos_Extracontables!$C:$C, ">=2026-05-01", Costos_Extracontables!$C:$C, "<=2026-05-31") -> 0 | E5: =SUMIFS(Costos_Extracontables!$D:$D, Costos_Extracontables!$E:$E, $B5, Costos_Extracontables!$C:$C, ">=2026-06-01", Costos_Extracontables!$C:$C, "<=2026-06-31") -> 0 | I5: =SUM(D5:G5) -> 0 | J5: 0 | K5: =I5+J5 -> 0 | L5: =C5-K5 -> 5400000 | M5: 0 | N5: =C5*M5 -> 0 | O5: =N5-I5 -> 0 | P5: 0 | Q5: =K5+P5 -> 0 | R5: =C5-Q5 -> 5400000
A6: 1.4 | B6: Alarife | C6: 3000000 | D6: =SUMIFS(Costos_Extracontables!$D:$D, Costos_Extracontables!$E:$E, $B6, Costos_Extracontables!$C:$C, ">=2026-05-01", Costos_Extracontables!$C:$C, "<=2026-05-31") -> 0 | E6: =SUMIFS(Costos_Extracontables!$D:$D, Costos_Extracontables!$E:$E, $B6, Costos_Extracontables!$C:$C, ">=2026-06-01", Costos_Extracontables!$C:$C, "<=2026-06-31") -> 0 | I6: =SUM(D6:G6) -> 0 | J6: 0 | K6: =I6+J6 -> 0 | L6: =C6-K6 -> 3000000 | M6: 0 | N6: =C6*M6 -> 0 | O6: =N6-I6 -> 0 | P6: 0 | Q6: =K6+P6 -> 0 | R6: =C6-Q6 -> 3000000
A7: 1.5 | B7: Maestro 1° Líneas Senior | C7: 4800000 | D7: =SUMIFS(Costos_Extracontables!$D:$D, Costos_Extracontables!$E:$E, $B7, Costos_Extracontables!$C:$C, ">=2026-05-01", Costos_Extracontables!$C:$C, "<=2026-05-31") -> 0 | E7: =SUMIFS(Costos_Extracontables!$D:$D, Costos_Extracontables!$E:$E, $B7, Costos_Extracontables!$C:$C, ">=2026-06-01", Costos_Extracontables!$C:$C, "<=2026-06-31") -> 0 | I7: =SUM(D7:G7) -> 0 | J7: 0 | K7: =I7+J7 -> 0 | L7: =C7-K7 -> 4800000 | M7: 0 | N7: =C7*M7 -> 0 | O7: =N7-I7 -> 0 | P7: 0 | Q7: =K7+P7 -> 0 | R7: =C7-Q7 -> 4800000
A8: 1.6 | B8: Maestro 1° Líneas | C8: 21000000 | D8: =SUMIFS(Costos_Extracontables!$D:$D, Costos_Extracontables!$E:$E, $B8, Costos_Extracontables!$C:$C, ">=2026-05-01", Costos_Extracontables!$C:$C, "<=2026-05-31") -> 0 | E8: =SUMIFS(Costos_Extracontables!$D:$D, Costos_Extracontables!$E:$E, $B8, Costos_Extracontables!$C:$C, ">=2026-06-01", Costos_Extracontables!$C:$C, "<=2026-06-31") -> 0 | I8: =SUM(D8:G8) -> 0 | J8: 0 | K8: =I8+J8 -> 0 | L8: =C8-K8 -> 21000000 | M8: 0 | N8: =C8*M8 -> 0 | O8: =N8-I8 -> 0 | P8: 0 | Q8: =K8+P8 -> 0 | R8: =C8-Q8 -> 21000000
A9: 1.7 | B9: Maestro 2° Líneas | C9: 7800000 | D9: =SUMIFS(Costos_Extracontables!$D:$D, Costos_Extracontables!$E:$E, $B9, Costos_Extracontables!$C:$C, ">=2026-05-01", Costos_Extracontables!$C:$C, "<=2026-05-31") -> 0 | E9: =SUMIFS(Costos_Extracontables!$D:$D, Costos_Extracontables!$E:$E, $B9, Costos_Extracontables!$C:$C, ">=2026-06-01", Costos_Extracontables!$C:$C, "<=2026-06-31") -> 0 | I9: =SUM(D9:G9) -> 0 | J9: 0 | K9: =I9+J9 -> 0 | L9: =C9-K9 -> 7800000 | M9: 0 | N9: =C9*M9 -> 0 | O9: =N9-I9 -> 0 | P9: 0 | Q9: =K9+P9 -> 0 | R9: =C9-Q9 -> 7800000
A10: 1.8 | B10: Operador Camión Pluma | C10: 5700000 | D10: =SUMIFS(Costos_Extracontables!$D:$D, Costos_Extracontables!$E:$E, $B10, Costos_Extracontables!$C:$C, ">=2026-05-01", Costos_Extracontables!$C:$C, "<=2026-05-31") -> 0 | E10: =SUMIFS(Costos_Extracontables!$D:$D, Costos_Extracontables!$E:$E, $B10, Costos_Extracontables!$C:$C, ">=2026-06-01", Costos_Extracontables!$C:$C, "<=2026-06-31") -> 0 | I10: =SUM(D10:G10) -> 0 | J10: 0 | K10: =I10+J10 -> 0 | L10: =C10-K10 -> 5700000 | M10: 0 | N10: =C10*M10 -> 0 | O10: =N10-I10 -> 0 | P10: 0 | Q10: =K10+P10 -> 0 | R10: =C10-Q10 -> 5700000
A11: 1.9 | B11: Rigger | C11: 3900000 | D11: =SUMIFS(Costos_Extracontables!$D:$D, Costos_Extracontables!$E:$E, $B11, Costos_Extracontables!$C:$C, ">=2026-05-01", Costos_Extracontables!$C:$C, "<=2026-05-31") -> 0 | E11: =SUMIFS(Costos_Extracontables!$D:$D, Costos_Extracontables!$E:$E, $B11, Costos_Extracontables!$C:$C, ">=2026-06-01", Costos_Extracontables!$C:$C, "<=2026-06-31") -> 0 | I11: =SUM(D11:G11) -> 0 | J11: 0 | K11: =I11+J11 -> 0 | L11: =C11-K11 -> 3900000 | M11: 0 | N11: =C11*M11 -> 0 | O11: =N11-I11 -> 0 | P11: 0 | Q11: =K11+P11 -> 0 | R11: =C11-Q11 -> 3900000
A12: 2.0 | B12: MATERIALES E INSUMOS | C12: =SUM(C13:C15) -> 2956644.4 | D12: =SUM(D13:D15) -> 0 | E12: =SUM(E13:E15) -> 0 | F12: =SUM(F13:F15) -> 0 | G12: =SUM(G13:G15) -> 0 | H12: =SUM(H13:H15) -> 0 | I12: =SUM(D12:G12) -> 0 | J12: 0 | K12: =I12+J12 -> 0 | L12: =C12-K12 -> 2956644.4 | M12: 0 | N12: =C12*M12 -> 0 | O12: =N12-I12 -> 0 | P12: 0 | Q12: =K12+P12 -> 0 | R12: =C12-Q12 -> 2956644.4
A13: 2.1 | B13: Instalación y Equipamiento Oficina Faena | C13: 1509542.9 | D13: =SUMIFS(Costos_Extracontables!$D:$D, Costos_Extracontables!$E:$E, $B13, Costos_Extracontables!$C:$C, ">=2026-05-01", Costos_Extracontables!$C:$C, "<=2026-05-31") -> 0 | E13: =SUMIFS(Costos_Extracontables!$D:$D, Costos_Extracontables!$E:$E, $B13, Costos_Extracontables!$C:$C, ">=2026-06-01", Costos_Extracontables!$C:$C, "<=2026-06-31") -> 0 | I13: =SUM(D13:G13) -> 0 | J13: 0 | K13: =I13+J13 -> 0 | L13: =C13-K13 -> 1509542.9 | M13: 0 | N13: =C13*M13 -> 0 | O13: =N13-I13 -> 0 | P13: 0 | Q13: =K13+P13 -> 0 | R13: =C13-Q13 -> 1509542.9
A14: 2.2 | B14: Suministros Menores (Agua, Café, etc.) | C14: 631832.8 | D14: =SUMIFS(Costos_Extracontables!$D:$D, Costos_Extracontables!$E:$E, $B14, Costos_Extracontables!$C:$C, ">=2026-05-01", Costos_Extracontables!$C:$C, "<=2026-05-31") -> 0 | E14: =SUMIFS(Costos_Extracontables!$D:$D, Costos_Extracontables!$E:$E, $B14, Costos_Extracontables!$C:$C, ">=2026-06-01", Costos_Extracontables!$C:$C, "<=2026-06-31") -> 0 | I14: =SUM(D14:G14) -> 0 | J14: 0 | K14: =I14+J14 -> 0 | L14: =C14-K14 -> 631832.8 | M14: 0 | N14: =C14*M14 -> 0 | O14: =N14-I14 -> 0 | P14: 0 | Q14: =K14+P14 -> 0 | R14: =C14-Q14 -> 631832.8
A15: 2.3 | B15: Implementos HSEC (Extintor, Camilla) | C15: 815268.67 | D15: =SUMIFS(Costos_Extracontables!$D:$D, Costos_Extracontables!$E:$E, $B15, Costos_Extracontables!$C:$C, ">=2026-05-01", Costos_Extracontables!$C:$C, "<=2026-05-31") -> 0 | E15: =SUMIFS(Costos_Extracontables!$D:$D, Costos_Extracontables!$E:$E, $B15, Costos_Extracontables!$C:$C, ">=2026-06-01", Costos_Extracontables!$C:$C, "<=2026-06-31") -> 0 | I15: =SUM(D15:G15) -> 0 | J15: 0 | K15: =I15+J15 -> 0 | L15: =C15-K15 -> 815268.67 | M15: 0 | N15: =C15*M15 -> 0 | O15: =N15-I15 -> 0 | P15: 0 | Q15: =K15+P15 -> 0 | R15: =C15-Q15 -> 815268.67
A16: 3.0 | B16: EQUIPOS Y MAQUINARIA | C16: =SUM(C17:C21) -> 57720797 | D16: =SUM(D17:D21) -> 0 | E16: =SUM(E17:E21) -> 0 | F16: =SUM(F17:F21) -> 0 | G16: =SUM(G17:G21) -> 0 | H16: =SUM(H17:H21) -> 0 | I16: =SUM(D16:G16) -> 0 | J16: 0 | K16: =I16+J16 -> 0 | L16: =C16-K16 -> 57720797 | M16: 0 | N16: =C16*M16 -> 0 | O16: =N16-I16 -> 0 | P16: 0 | Q16: =K16+P16 -> 0 | R16: =C16-Q16 -> 57720797
A17: 3.1 | B17: Arriendo Camionetas 4x4 | C17: 19000000 | D17: =SUMIFS(Costos_Extracontables!$D:$D, Costos_Extracontables!$E:$E, $B17, Costos_Extracontables!$C:$C, ">=2026-05-01", Costos_Extracontables!$C:$C, "<=2026-05-31") -> 0 | E17: =SUMIFS(Costos_Extracontables!$D:$D, Costos_Extracontables!$E:$E, $B17, Costos_Extracontables!$C:$C, ">=2026-06-01", Costos_Extracontables!$C:$C, "<=2026-06-31") -> 0 | I17: =SUM(D17:G17) -> 0 | J17: 0 | K17: =I17+J17 -> 0 | L17: =C17-K17 -> 19000000 | M17: 0 | N17: =C17*M17 -> 0 | O17: =N17-I17 -> 0 | P17: 0 | Q17: =K17+P17 -> 0 | R17: =C17-Q17 -> 19000000
A18: 3.2 | B18: Arriendo Camión Pluma 20 Ton | C18: 22500000 | D18: =SUMIFS(Costos_Extracontables!$D:$D, Costos_Extracontables!$E:$E, $B18, Costos_Extracontables!$C:$C, ">=2026-05-01", Costos_Extracontables!$C:$C, "<=2026-05-31") -> 0 | E18: =SUMIFS(Costos_Extracontables!$D:$D, Costos_Extracontables!$E:$E, $B18, Costos_Extracontables!$C:$C, ">=2026-06-01", Costos_Extracontables!$C:$C, "<=2026-06-31") -> 0 | I18: =SUM(D18:G18) -> 0 | J18: 0 | K18: =I18+J18 -> 0 | L18: =C18-K18 -> 22500000 | M18: 0 | N18: =C18*M18 -> 0 | O18: =N18-I18 -> 0 | P18: 0 | Q18: =K18+P18 -> 0 | R18: =C18-Q18 -> 22500000
A19: 3.3 | B19: Equipos HTLS (Prensa, Alzabobina, Cordina) | C19: 10507320 | D19: =SUMIFS(Costos_Extracontables!$D:$D, Costos_Extracontables!$E:$E, $B19, Costos_Extracontables!$C:$C, ">=2026-05-01", Costos_Extracontables!$C:$C, "<=2026-05-31") -> 0 | E19: =SUMIFS(Costos_Extracontables!$D:$D, Costos_Extracontables!$E:$E, $B19, Costos_Extracontables!$C:$C, ">=2026-06-01", Costos_Extracontables!$C:$C, "<=2026-06-31") -> 0 | I19: =SUM(D19:G19) -> 0 | J19: 0 | K19: =I19+J19 -> 0 | L19: =C19-K19 -> 10507320 | M19: 0 | N19: =C19*M19 -> 0 | O19: =N19-I19 -> 0 | P19: 0 | Q19: =K19+P19 -> 0 | R19: =C19-Q19 -> 10507320
A20: 3.4 | B20: Generador 30 kVA | C20: 2043010.8 | D20: =SUMIFS(Costos_Extracontables!$D:$D, Costos_Extracontables!$E:$E, $B20, Costos_Extracontables!$C:$C, ">=2026-05-01", Costos_Extracontables!$C:$C, "<=2026-05-31") -> 0 | E20: =SUMIFS(Costos_Extracontables!$D:$D, Costos_Extracontables!$E:$E, $B20, Costos_Extracontables!$C:$C, ">=2026-06-01", Costos_Extracontables!$C:$C, "<=2026-06-31") -> 0 | I20: =SUM(D20:G20) -> 0 | J20: 0 | K20: =I20+J20 -> 0 | L20: =C20-K20 -> 2043010.8 | M20: 0 | N20: =C20*M20 -> 0 | O20: =N20-I20 -> 0 | P20: 0 | Q20: =K20+P20 -> 0 | R20: =C20-Q20 -> 2043010.8
A21: 3.5 | B21: Herramientas e Implementos Menores (Escalas, Señalética) | C21: 3670465.9 | D21: =SUMIFS(Costos_Extracontables!$D:$D, Costos_Extracontables!$E:$E, $B21, Costos_Extracontables!$C:$C, ">=2026-05-01", Costos_Extracontables!$C:$C, "<=2026-05-31") -> 0 | E21: =SUMIFS(Costos_Extracontables!$D:$D, Costos_Extracontables!$E:$E, $B21, Costos_Extracontables!$C:$C, ">=2026-06-01", Costos_Extracontables!$C:$C, "<=2026-06-31") -> 0 | I21: =SUM(D21:G21) -> 0 | J21: 0 | K21: =I21+J21 -> 0 | L21: =C21-K21 -> 3670465.9 | M21: 0 | N21: =C21*M21 -> 0 | O21: =N21-I21 -> 0 | P21: 0 | Q21: =K21+P21 -> 0 | R21: =C21-Q21 -> 3670465.9
A22: 4.0 | B22: SUBCONTRATOS | C22: =SUM(C23:C25) -> 4510650 | D22: =SUM(D23:D25) -> 0 | E22: =SUM(E23:E25) -> 0 | F22: =SUM(F23:F25) -> 0 | G22: =SUM(G23:G25) -> 0 | H22: =SUM(H23:H25) -> 0 | I22: =SUM(D22:G22) -> 0 | J22: 0 | K22: =I22+J22 -> 0 | L22: =C22-K22 -> 4510650 | M22: 0 | N22: =C22*M22 -> 0 | O22: =N22-I22 -> 0 | P22: 0 | Q22: =K22+P22 -> 0 | R22: =C22-Q22 -> 4510650
A23: 4.1 | B23: Arriendo Container Oficina | C23: 710650 | D23: =SUMIFS(Costos_Extracontables!$D:$D, Costos_Extracontables!$E:$E, $B23, Costos_Extracontables!$C:$C, ">=2026-05-01", Costos_Extracontables!$C:$C, "<=2026-05-31") -> 0 | E23: =SUMIFS(Costos_Extracontables!$D:$D, Costos_Extracontables!$E:$E, $B23, Costos_Extracontables!$C:$C, ">=2026-06-01", Costos_Extracontables!$C:$C, "<=2026-06-31") -> 0 | I23: =SUM(D23:G23) -> 0 | J23: 0 | K23: =I23+J23 -> 0 | L23: =C23-K23 -> 710650 | M23: 0 | N23: =C23*M23 -> 0 | O23: =N23-I23 -> 0 | P23: 0 | Q23: =K23+P23 -> 0 | R23: =C23-Q23 -> 710650
A24: 4.2 | B24: Arriendo Baños Químicos | C24: 1800000 | D24: =SUMIFS(Costos_Extracontables!$D:$D, Costos_Extracontables!$E:$E, $B24, Costos_Extracontables!$C:$C, ">=2026-05-01", Costos_Extracontables!$C:$C, "<=2026-05-31") -> 0 | E24: =SUMIFS(Costos_Extracontables!$D:$D, Costos_Extracontables!$E:$E, $B24, Costos_Extracontables!$C:$C, ">=2026-06-01", Costos_Extracontables!$C:$C, "<=2026-06-31") -> 0 | I24: =SUM(D24:G24) -> 0 | J24: 0 | K24: =I24+J24 -> 0 | L24: =C24-K24 -> 1800000 | M24: 0 | N24: =C24*M24 -> 0 | O24: =N24-I24 -> 0 | P24: 0 | Q24: =K24+P24 -> 0 | R24: =C24-Q24 -> 1800000
A25: 4.3 | B25: Fletes y Transporte | C25: 2000000 | D25: =SUMIFS(Costos_Extracontables!$D:$D, Costos_Extracontables!$E:$E, $B25, Costos_Extracontables!$C:$C, ">=2026-05-01", Costos_Extracontables!$C:$C, "<=2026-05-31") -> 0 | E25: =SUMIFS(Costos_Extracontables!$D:$D, Costos_Extracontables!$E:$E, $B25, Costos_Extracontables!$C:$C, ">=2026-06-01", Costos_Extracontables!$C:$C, "<=2026-06-31") -> 0 | I25: =SUM(D25:G25) -> 0 | J25: 0 | K25: =I25+J25 -> 0 | L25: =C25-K25 -> 2000000 | M25: 0 | N25: =C25*M25 -> 0 | O25: =N25-I25 -> 0 | P25: 0 | Q25: =K25+P25 -> 0 | R25: =C25-Q25 -> 2000000
A26: 5.0 | B26: ASESORÍA TÉCNICA CTC GLOBAL | C26: =SUM(C27:C29) -> 17980000 | D26: =SUM(D27:D29) -> 0 | E26: =SUM(E27:E29) -> 0 | F26: =SUM(F27:F29) -> 0 | G26: =SUM(G27:G29) -> 0 | H26: =SUM(H27:H29) -> 0 | I26: =SUM(D26:G26) -> 0 | J26: 0 | K26: =I26+J26 -> 0 | L26: =C26-K26 -> 17980000 | M26: 0 | N26: =C26*M26 -> 0 | O26: =N26-I26 -> 0 | P26: 0 | Q26: =K26+P26 -> 0 | R26: =C26-Q26 -> 17980000
A27: 5.1 | B27: Servicios de Asesoría y Standby | C27: 14800000 | D27: =SUMIFS(Costos_Extracontables!$D:$D, Costos_Extracontables!$E:$E, $B27, Costos_Extracontables!$C:$C, ">=2026-05-01", Costos_Extracontables!$C:$C, "<=2026-05-31") -> 0 | E27: =SUMIFS(Costos_Extracontables!$D:$D, Costos_Extracontables!$E:$E, $B27, Costos_Extracontables!$C:$C, ">=2026-06-01", Costos_Extracontables!$C:$C, "<=2026-06-31") -> 0 | I27: =SUM(D27:G27) -> 0 | J27: 0 | K27: =I27+J27 -> 0 | L27: =C27-K27 -> 14800000 | M27: 0 | N27: =C27*M27 -> 0 | O27: =N27-I27 -> 0 | P27: 0 | Q27: =K27+P27 -> 0 | R27: =C27-Q27 -> 14800000
A28: 5.2 | B28: Logística y Viáticos Asesor | C28: 1680000 | D28: =SUMIFS(Costos_Extracontables!$D:$D, Costos_Extracontables!$E:$E, $B28, Costos_Extracontables!$C:$C, ">=2026-05-01", Costos_Extracontables!$C:$C, "<=2026-05-31") -> 0 | E28: =SUMIFS(Costos_Extracontables!$D:$D, Costos_Extracontables!$E:$E, $B28, Costos_Extracontables!$C:$C, ">=2026-06-01", Costos_Extracontables!$C:$C, "<=2026-06-31") -> 0 | I28: =SUM(D28:G28) -> 0 | J28: 0 | K28: =I28+J28 -> 0 | L28: =C28-K28 -> 1680000 | M28: 0 | N28: =C28*M28 -> 0 | O28: =N28-I28 -> 0 | P28: 0 | Q28: =K28+P28 -> 0 | R28: =C28-Q28 -> 1680000
A29: 5.3 | B29: EPP Asesor Especialista | C29: 1500000 | D29: =SUMIFS(Costos_Extracontables!$D:$D, Costos_Extracontables!$E:$E, $B29, Costos_Extracontables!$C:$C, ">=2026-05-01", Costos_Extracontables!$C:$C, "<=2026-05-31") -> 0 | E29: =SUMIFS(Costos_Extracontables!$D:$D, Costos_Extracontables!$E:$E, $B29, Costos_Extracontables!$C:$C, ">=2026-06-01", Costos_Extracontables!$C:$C, "<=2026-06-31") -> 0 | I29: =SUM(D29:G29) -> 0 | J29: 0 | K29: =I29+J29 -> 0 | L29: =C29-K29 -> 1500000 | M29: 0 | N29: =C29*M29 -> 0 | O29: =N29-I29 -> 0 | P29: 0 | Q29: =K29+P29 -> 0 | R29: =C29-Q29 -> 1500000
A30: 6.0 | B30: GASTOS GENERALES Y OPERACIONALES | C30: =SUM(C31:C36) -> 80209991 | D30: =SUM(D31:D36) -> 200000 | E30: =SUM(E31:E36) -> 0 | F30: =SUM(F31:F36) -> 0 | G30: =SUM(G31:G36) -> 0 | H30: =SUM(H31:H36) -> 0 | I30: =SUM(D30:G30) -> 200000 | J30: 0 | K30: =I30+J30 -> 200000 | L30: =C30-K30 -> 80009991 | M30: 0 | N30: =C30*M30 -> 0 | O30: =N30-I30 -> -200000 | P30: 0 | Q30: =K30+P30 -> 200000 | R30: =C30-Q30 -> 80009991
A31: 6.1 | B31: Logística: Alojamiento MOD/MOI/Staff | C31: 20800000 | D31: =SUMIFS(Costos_Extracontables!$D:$D, Costos_Extracontables!$E:$E, $B31, Costos_Extracontables!$C:$C, ">=2026-05-01", Costos_Extracontables!$C:$C, "<=2026-05-31") -> 200000 | E31: =SUMIFS(Costos_Extracontables!$D:$D, Costos_Extracontables!$E:$E, $B31, Costos_Extracontables!$C:$C, ">=2026-06-01", Costos_Extracontables!$C:$C, "<=2026-06-31") -> 0 | I31: =SUM(D31:G31) -> 200000 | J31: 0 | K31: =I31+J31 -> 200000 | L31: =C31-K31 -> 20600000 | M31: 0 | N31: =C31*M31 -> 0 | O31: =N31-I31 -> -200000 | P31: 0 | Q31: =K31+P31 -> 200000 | R31: =C31-Q31 -> 20600000
A32: 6.2 | B32: Logística: Alimentación MOD/MOI/Staff | C32: 11400000 | D32: =SUMIFS(Costos_Extracontables!$D:$D, Costos_Extracontables!$E:$E, $B32, Costos_Extracontables!$C:$C, ">=2026-05-01", Costos_Extracontables!$C:$C, "<=2026-05-31") -> 0 | E32: =SUMIFS(Costos_Extracontables!$D:$D, Costos_Extracontables!$E:$E, $B32, Costos_Extracontables!$C:$C, ">=2026-06-01", Costos_Extracontables!$C:$C, "<=2026-06-31") -> 0 | I32: =SUM(D32:G32) -> 0 | J32: 0 | K32: =I32+J32 -> 0 | L32: =C32-K32 -> 11400000 | M32: 0 | N32: =C32*M32 -> 0 | O32: =N32-I32 -> 0 | P32: 0 | Q32: =K32+P32 -> 0 | R32: =C32-Q32 -> 11400000
A33: 6.3 | B33: Logística: Pasajes y Traslados | C33: 12900000 | D33: =SUMIFS(Costos_Extracontables!$D:$D, Costos_Extracontables!$E:$E, $B33, Costos_Extracontables!$C:$C, ">=2026-05-01", Costos_Extracontables!$C:$C, "<=2026-05-31") -> 0 | E33: =SUMIFS(Costos_Extracontables!$D:$D, Costos_Extracontables!$E:$E, $B33, Costos_Extracontables!$C:$C, ">=2026-06-01", Costos_Extracontables!$C:$C, "<=2026-06-31") -> 0 | I33: =SUM(D33:G33) -> 0 | J33: 0 | K33: =I33+J33 -> 0 | L33: =C33-K33 -> 12900000 | M33: 0 | N33: =C33*M33 -> 0 | O33: =N33-I33 -> 0 | P33: 0 | Q33: =K33+P33 -> 0 | R33: =C33-Q33 -> 12900000
A34: 6.4 | B34: Costo Operativo Equipos (Combustible, etc.) | C34: 3989991 | D34: =SUMIFS(Costos_Extracontables!$D:$D, Costos_Extracontables!$E:$E, $B34, Costos_Extracontables!$C:$C, ">=2026-05-01", Costos_Extracontables!$C:$C, "<=2026-05-31") -> 0 | E34: =SUMIFS(Costos_Extracontables!$D:$D, Costos_Extracontables!$E:$E, $B34, Costos_Extracontables!$C:$C, ">=2026-06-01", Costos_Extracontables!$C:$C, "<=2026-06-31") -> 0 | I34: =SUM(D34:G34) -> 0 | J34: 0 | K34: =I34+J34 -> 0 | L34: =C34-K34 -> 3989991 | M34: 0 | N34: =C34*M34 -> 0 | O34: =N34-I34 -> 0 | P34: 0 | Q34: =K34+P34 -> 0 | R34: =C34-Q34 -> 3989991
A35: 6.5 | B35: EPP y Ropa de Trabajo Personal (Directo e Ind.) | C35: 25600000 | D35: =SUMIFS(Costos_Extracontables!$D:$D, Costos_Extracontables!$E:$E, $B35, Costos_Extracontables!$C:$C, ">=2026-05-01", Costos_Extracontables!$C:$C, "<=2026-05-31") -> 0 | E35: =SUMIFS(Costos_Extracontables!$D:$D, Costos_Extracontables!$E:$E, $B35, Costos_Extracontables!$C:$C, ">=2026-06-01", Costos_Extracontables!$C:$C, "<=2026-06-31") -> 0 | I35: =SUM(D35:G35) -> 0 | J35: 0 | K35: =I35+J35 -> 0 | L35: =C35-K35 -> 25600000 | M35: 0 | N35: =C35*M35 -> 0 | O35: =N35-I35 -> 0 | P35: 0 | Q35: =K35+P35 -> 0 | R35: =C35-Q35 -> 25600000
A36: 6.6 | B36: Certificaciones Externas | C36: 5520000 | D36: =SUMIFS(Costos_Extracontables!$D:$D, Costos_Extracontables!$E:$E, $B36, Costos_Extracontables!$C:$C, ">=2026-05-01", Costos_Extracontables!$C:$C, "<=2026-05-31") -> 0 | E36: =SUMIFS(Costos_Extracontables!$D:$D, Costos_Extracontables!$E:$E, $B36, Costos_Extracontables!$C:$C, ">=2026-06-01", Costos_Extracontables!$C:$C, "<=2026-06-31") -> 0 | I36: =SUM(D36:G36) -> 0 | J36: 0 | K36: =I36+J36 -> 0 | L36: =C36-K36 -> 5520000 | M36: 0 | N36: =C36*M36 -> 0 | O36: =N36-I36 -> 0 | P36: 0 | Q36: =K36+P36 -> 0 | R36: =C36-Q36 -> 5520000
A37: 7.0 | B37: IMPREVISTOS Y CONTINGENCIAS | C37: =SUM(C38) -> 26950000 | D37: =SUM(D38) -> 0 | E37: =SUM(E38) -> 0 | F37: =SUM(F38) -> 0 | G37: =SUM(G38) -> 0 | H37: =SUM(H38) -> 0 | I37: =SUM(D37:G37) -> 0 | J37: 0 | K37: =I37+J37 -> 0 | L37: =C37-K37 -> 26950000 | M37: 0 | N37: =C37*M37 -> 0 | O37: =N37-I37 -> 0 | P37: 0 | Q37: =K37+P37 -> 0 | R37: =C37-Q37 -> 26950000
A38: 7.1 | B38: Provisión Imprevistos (15 días) | C38: 26950000 | D38: =SUMIFS(Costos_Extracontables!$D:$D, Costos_Extracontables!$E:$E, $B38, Costos_Extracontables!$C:$C, ">=2026-05-01", Costos_Extracontables!$C:$C, "<=2026-05-31") -> 0 | E38: =SUMIFS(Costos_Extracontables!$D:$D, Costos_Extracontables!$E:$E, $B38, Costos_Extracontables!$C:$C, ">=2026-06-01", Costos_Extracontables!$C:$C, "<=2026-06-31") -> 0 | I38: =SUM(D38:G38) -> 0 | J38: 0 | K38: =I38+J38 -> 0 | L38: =C38-K38 -> 26950000 | M38: 0 | N38: =C38*M38 -> 0 | O38: =N38-I38 -> 0 | P38: 0 | Q38: =K38+P38 -> 0 | R38: =C38-Q38 -> 26950000
B39: TOTAL COSTOS | C39: =+C37+C30+C26+C22+C16+C12+C2 -> 2.5302808e+08 | D39: =+D37+D30+D26+D22+D16+D12+D2 -> 200000 | E39: =+E37+E30+E26+E22+E16+E12+E2 -> 0 | F39: =+F37+F30+F26+F22+F16+F12+F2 -> 0 | G39: =+G37+G30+G26+G22+G16+G12+G2 -> 0 | H39: =+H37+H30+H26+H22+H16+H12+H2 -> 0 | I39: =+I37+I30+I26+I22+I16+I12+I2 -> 200000 | J39: =+J37+J30+J26+J22+J16+J12+J2 -> 0 | ... L39: =+L37+L30+L26+L22+L16+L12+L2 -> 2.5282808e+08 | M39: =IF(C39>0,N39/C39,0) -> 0 | N39: =SUMIF(A2:A38, "*.0", N2:N38) -> 0 | O39: =SUMIF(A2:A38, "*.0", O2:O38) -> -200000 | P39: =SUMIF(A2:A38, "*.0", P2:P38) -> 0 | Q39: =SUMIF(A2:A38, "*.0", Q2:Q38) -> 200000 | R39: =SUMIF(A2:A38, "*.0", R2:R38) -> 2.5282808e+08
B40: TOTAL INGRESOS | C40: 3.84359e+08
B41: TOTAL MARGEN COMPROMETIDO | C41: =-C39+C40 -> 1.3133091e+08
O48: =3500000*5 -> 17500000
O49: =+O48*2 -> 35000000
O50: =+O49*1.2 -> 42000000
O51: 5000000
O52: =SUM(O50:O51) -> 47000000

Sheet Costos_Extracontables
A1: WBS | B1: Descripción del Costo | C1: Fecha (Mes) | D1: Monto Neto | E1: Clasificación (utilizar lista deplegable) | F1: Tipo de Costo | G1: Comentarios | H1: Registrado en Contabilidad
A2: 1 | B2: Estadia Capacitacion MOD + JC Santander - Iquique S25-29 Mayo | C2: 46143 | D2: =40000*5 -> 200000 | E2: Logística: Alojamiento MOD/MOI/Staff | F2: Factura Pago 30 días | H2: No
A3: 2 | B3: Examenes Iquique | H3: No
A4: 3 | B4: Coaching 3D CEIM | H4: No
A5: 4 | B5: Pasajes Iquique - Antofagasta Personal Directo | H5: No
A6: 5 | B6: Estadia Antofagasta Personal Directo | H6: No
A7: 6 | B7: Alimentacion Antofagasta Personal Directo | H7: No
A8: 7 | H8: No
A9: 8 | H9: No
A10: 9 | H10: No
A11: 10 | H11: No
A12: 11 | H12: No
A13: 12 | H13: No
A14: 13 | H14: No
A15: 14 | H15: No
A16: 15 | H16: No
A17: 16 | H17: No
A18: 17 | H18: No
A19: 18 | H19: No
... A137: 136 | H137: No
B138: TOTAL COSTOS | D138: =SUM(D2:D137) -> 200000

Sheet RRHH_Control
A1: ID | B1: Cargo | C1: Código | D1: Nombre | E1: Examen Méd. | F1: Test A&D | G1: Gran Altura Geografica | H1: Gran Altura Física | I1: Psicosenso. | J1: Aversión al Riesgo | K1: Indicadores Medidos en Aversion al Riesgo | L1: Adecuación a normas y procedimientos | M1: Capacidad de atención y concentración | N1: Capacidad para trabajar bajo presión | O1: Conducta precavida | P1: Control de impulsos | Q1: Disposición al aprendizaje y capacitación | R1: Estabilidad emocional | S1: Carta Oferta | T1: Documentos Solicitados STN | U1: Contrato / Anexo | V1: Ficha Trab. MEL | W1: Cert. Anteced. | X1: Cédula Ident. | Y1: Regl. Transp | Z1: Portal PMF | AA1: Coaching 3D | AB1: 3D-CEIM | AC1: Supervisor Izaje | AD1: Asistente Izaje | AE1: Lic. Rigger | AF1: Valid. Deloitte | AG1: Cursos Inatrans Lic. Interna Camionetas (3) | AH1: Lic. Operador | AI1: Avance HDR (%) | AJ1: % Cumpl. MEL | AK1: Estado Final | AL1: Semáforo | AM1: Cumplimiento Consolidado | AN1: Observaciones
A2: P01 | B2: Administrador Contrato | C2: ADM_01 | D2: Andrés Tebes | E2: Aprobado | F2: Aprobado | G2: Aprobado | H2: Aprobado | I2: Aprobado | J2: Aprobado | K2: =COUNTIF(L2:R2,"*OK*") & " de 7 ; " & ROUND(COUNTIF(L2:R2,"*OK*")/7*100,0) & "%" -> 7 de 7 ; 100% | L2: OK -Dentro de lo esperado | M2: OK -Dentro de lo esperado | N2: OK -Dentro de lo esperado | O2: OK -Dentro de lo esperado | P2: OK -Dentro de lo esperado | Q2: OK -Dentro de lo esperado | R2: OK -Dentro de lo esperado | S2: N/A | T2: N/A | U2: Aprobado | V2: N/A | W2: No Iniciado | X2: N/A | Y2: N/A | Z2: N/A | AA2: No Iniciado | AB2: No Iniciado | AC2: N/A | AD2: N/A | AE2: N/A | AF2: No Iniciado | AG2: 46177 | AH2: N/A | AI2: =IFERROR(HDR_Matriz!BI2, "Pendiente datos") -> 0 | AJ2: =IFERROR((COUNTIF(S2:AH2, "Aprobado")) / (12 - COUNTIF(S2:AH2, "N/A")), "Pendiente datos") -> 0.5 | AK2: En proceso | AL2: =IFERROR(IF(AK2="Acreditado", "Verde", IF(AK2="En Proceso", "Amarillo", "Rojo")), "Pendiente datos") -> Amarillo | AM2: =IFERROR(AVERAGE(AJ2, AI2), "Pendiente datos") -> 0.25 | AN2: Sincronizado
A3: P02 | B3: Asesor de Seguridad | C3: HSEC_01 | D3: Juan Carlos Santander | E3: Aprobado | F3: Aprobado | G3: Aprobado | H3: Aprobado | I3: Aprobado | J3: Aprobado | K3: =COUNTIF(L3:R3,"*OK*") & " de 7 ; " & ROUND(COUNTIF(L3:R3,"*OK*")/7*100,0) & "%" -> 7 de 7 ; 100% | L3: OK -Dentro de lo esperado | M3: OK -Dentro de lo esperado | N3: OK -Dentro de lo esperado | O3: OK -Dentro de lo esperado | P3: OK -Dentro de lo esperado | Q3: OK -Dentro de lo esperado | R3: OK -Dentro de lo esperado | S3: N/A | T3: N/A | U3: Aprobado | V3: N/A | W3: No Iniciado | X3: N/A | Y3: N/A | Z3: N/A | AA3: No Iniciado | AB3: No Iniciado | AC3: N/A | AD3: N/A | AE3: N/A | AF3: No Iniciado | AG3: 46184 | AH3: N/A | AI3: =IFERROR(HDR_Matriz!BI3, "Pendiente datos") -> 0 | AJ3: =IFERROR((COUNTIF(S3:AH3, "Aprobado")) / (12 - COUNTIF(S3:AH3, "N/A")), "Pendiente datos") -> 0.5 | AK3: En proceso | AL3: =IFERROR(IF(AK3="Acreditado", "Verde", IF(AK3="En Proceso", "Amarillo", "Rojo")), "Pendiente datos") -> Amarillo | AM3: =IFERROR(AVERAGE(AJ3, AI3), "Pendiente datos") -> 0.25 | AN3: Sincronizado
A4: P03 | B4: Jefe de Terreno | C4: JT_01 | D4: Leonel Sanchez | E4: Aprobado | F4: Aprobado | G4: Aprobado | H4: Aprobado | I4: Aprobado | J4: Aprobado | K4: =COUNTIF(L4:R4,"*OK*") & " de 7 ; " & ROUND(COUNTIF(L4:R4,"*OK*")/7*100,0) & "%" -> 7 de 7 ; 100% | L4: OK -Dentro de lo esperado | M4: OK -Dentro de lo esperado | N4: OK -Dentro de lo esperado | O4: OK -Dentro de lo esperado | P4: OK -Dentro de lo esperado | Q4: OK -Dentro de lo esperado | R4: OK -Dentro de lo esperado | S4: N/A | T4: N/A | U4: Aprobado | V4: N/A | W4: N/A | X4: N/A | Y4: N/A | Z4: N/A | AA4: No Iniciado | AB4: 46181 | AC4: N/A | AD4: N/A | AE4: N/A | AF4: No Iniciado | AG4: N/A | AH4: N/A | AI4: =IFERROR(HDR_Matriz!BI4, "Pendiente datos") -> 0 | AJ4: =IFERROR((COUNTIF(S4:AH4, "Aprobado")) / (12 - COUNTIF(S4:AH4, "N/A")), "Pendiente datos") -> Pendiente datos | AK4: En proceso | AL4: =IFERROR(IF(AK4="Acreditado", "Verde", IF(AK4="En Proceso", "Amarillo", "Rojo")), "Pendiente datos") -> Amarillo | AM4: =IFERROR(AVERAGE(AJ4, AI4), "Pendiente datos") -> 0 | AN4: Sincronizado
A5: P04 | B5: Supervisor de Terreno | C5: SUP_01 | D5: Ulises Psijas | E5: Aprobado | F5: Aprobado | G5: Aprobado | H5: Aprobado | I5: Aprobado | J5: Aprobado | K5: =COUNTIF(L5:R5,"*OK*") & " de 7 ; " & ROUND(COUNTIF(L5:R5,"*OK*")/7*100,0) & "%" -> 7 de 7 ; 100% | L5: OK -Dentro de lo esperado | M5: OK -Dentro de lo esperado | N5: OK -Dentro de lo esperado | O5: OK -Dentro de lo esperado | P5: OK -Dentro de lo esperado | Q5: OK -Dentro de lo esperado | R5: OK -Dentro de lo esperado | S5: Aprobado | T5: En proceso | U5: No Iniciado | V5: No Iniciado | W5: No Iniciado | X5: No Iniciado | Y5: No Iniciado | Z5: No Iniciado | AA5: No Iniciado | AB5: 46181 | AC5: 46178 | AD5: N/A | AE5: No Iniciado | AF5: No Iniciado | AG5: 46182 | AH5: N/A | AI5: =IFERROR(HDR_Matriz!BI5, "Pendiente datos") -> 0 | AJ5: =IFERROR((COUNTIF(S5:AH5, "Aprobado")) / (12 - COUNTIF(S5:AH5, "N/A")), "Pendiente datos") -> 0.1 | AK5: En proceso | AL5: =IFERROR(IF(AK5="Acreditado", "Verde", IF(AK5="En Proceso", "Amarillo", "Rojo")), "Pendiente datos") -> Amarillo | AM5: =IFERROR(AVERAGE(AJ5, AI5), "Pendiente datos") -> 0.05 | AN5: Sincronizado
A6: P05 | B6: Encargado Administrativo | C6: ADM_02 | D6: Jesenia Tapia | E6: Aprobado | F6: Aprobado | G6: Aprobado | H6: Aprobado | I6: Aprobado | J6: Aprobado | K6: =COUNTIF(L6:R6,"*OK*") & " de 7 ; " & ROUND(COUNTIF(L6:R6,"*OK*")/7*100,0) & "%" -> 7 de 7 ; 100% | L6: OK -Dentro de lo esperado | M6: OK -Dentro de lo esperado | N6: OK -Dentro de lo esperado | O6: OK -Dentro de lo esperado | P6: OK -Dentro de lo esperado | Q6: OK -Dentro de lo esperado | R6: OK -Dentro de lo esperado | S6: Aprobado | T6: No Iniciado | U6: Aprobado | V6: No Iniciado | W6: No Iniciado | X6: No Iniciado | Y6: No Iniciado | Z6: No Iniciado | AA6: No Iniciado | AB6: N/A | AC6: N/A | AD6: N/A | AE6: N/A | AF6: No Iniciado | AG6: N/A | AH6: N/A | AI6: =IFERROR(HDR_Matriz!BI6, "Pendiente datos") -> 0 | AJ6: =IFERROR((COUNTIF(S6:AH6, "Aprobado")) / (12 - COUNTIF(S6:AH6, "N/A")), "Pendiente datos") -> 0.33333333 | AK6: En proceso | AL6: =IFERROR(IF(AK6="Acreditado", "Verde", IF(AK6="En Proceso", "Amarillo", "Rojo")), "Pendiente datos") -> Amarillo | AM6: =IFERROR(AVERAGE(AJ6, AI6), "Pendiente datos") -> 0.16666667 | AN6: Sincronizado
A7: P06 | B7: Topógrafo | C7: TOPO_01 | D7: Manuel Tapia | E7: Aprobado | F7: Aprobado | G7: Aprobado | H7: Aprobado | I7: N/A | J7: Aprobado | K7: N/A | L7: OK -Dentro de lo esperado | M7: OK -Dentro de lo esperado | N7: OK -Dentro de lo esperado | O7: OK -Dentro de lo esperado | P7: OK -Dentro de lo esperado | Q7: OK -Dentro de lo esperado | R7: OK -Dentro de lo esperado | S7: Aprobado | T7: Aprobado | U7: Aprobado | V7: Aprobado | W7: Aprobado | X7: Aprobado | Y7: No Iniciado | Z7: No Iniciado | AA7: Aprobado | AB7: N/A | AC7: N/A | AD7: N/A | AE7: N/A | AF7: No Iniciado | AG7: N/A | AH7: N/A | AI7: =IFERROR(HDR_Matriz!BI7, "Pendiente datos") -> 0 | AJ7: =IFERROR((COUNTIF(S7:AH7, "Aprobado")) / (12 - COUNTIF(S7:AH7, "N/A")), "Pendiente datos") -> 1.1666667 | AK7: En proceso | AL7: =IFERROR(IF(AK7="Acreditado", "Verde", IF(AK7="En Proceso", "Amarillo", "Rojo")), "Pendiente datos") -> Amarillo | AM7: =IFERROR(AVERAGE(AJ7, AI7), "Pendiente datos") -> 0.58333333 | AN7: Sincronizado
A8: P07 | B8: Maestro 1° Líneas (Interno Alarife) | C8: M1_01 | D8: Orlando Maita | E8: Aprobado | F8: Aprobado | G8: Aprobado | H8: Aprobado | I8: N/A | J8: Aprobado | K8: =COUNTIF(L8:R8,"*OK*") & " de 7 ; " & ROUND(COUNTIF(L8:R8,"*OK*")/7*100,0) & "%" -> 7 de 7 ; 100% | L8: OK -Dentro de lo esperado | M8: OK -Dentro de lo esperado | N8: OK -Dentro de lo esperado | O8: OK -Dentro de lo esperado | P8: OK -Dentro de lo esperado | Q8: OK -Dentro de lo esperado | R8: OK -Dentro de lo esperado | S8: No Iniciado | T8: No Iniciado | U8: No Iniciado | V8: No Iniciado | W8: Aprobado | X8: No Iniciado | Y8: No Iniciado | Z8: No Iniciado | AA8: Aprobado | AB8: 46178 | AC8: N/A | AD8: N/A | AE8: N/A | AF8: No Iniciado | AG8: N/A | AH8: N/A | AI8: =IFERROR(HDR_Matriz!BI8, "Pendiente datos") -> 0 | AJ8: =IFERROR((COUNTIF(S8:AH8, "Aprobado")) / (12 - COUNTIF(S8:AH8, "N/A")), "Pendiente datos") -> 0.28571429 | AK8: En proceso | AL8: =IFERROR(IF(AK8="Acreditado", "Verde", IF(AK8="En Proceso", "Amarillo", "Rojo")), "Pendiente datos") -> Amarillo | AM8: =IFERROR(AVERAGE(AJ8, AI8), "Pendiente datos") -> 0.14285714 | AN8: Sincronizado
A9: P08 | B9: Maestro 1° Líneas | C9: M1_01 | D9: Wilmer Chambi | E9: Aprobado | F9: Aprobado | G9: Aprobado | H9: Aprobado | I9: N/A | J9: Aprobado | K9: =COUNTIF(L9:R9,"*OK*") & " de 7 ; " & ROUND(COUNTIF(L9:R9,"*OK*")/7*100,0) & "%" -> 7 de 7 ; 100% | L9: OK -Dentro de lo esperado | M9: OK -Dentro de lo esperado | N9: OK -Dentro de lo esperado | O9: OK -Dentro de lo esperado | P9: OK -Dentro de lo esperado | Q9: OK -Dentro de lo esperado | R9: OK -Dentro de lo esperado | S9: Aprobado | T9: No Iniciado | U9: Aprobado | V9: Aprobado | W9: Aprobado | X9: No Iniciado | Y9: No Iniciado | Z9: No Iniciado | AA9: Aprobado | AB9: 46177 | AC9: 46184 | AD9: N/A | AE9: No Iniciado | AF9: No Iniciado | AG9: N/A | AH9: N/A | AI9: =IFERROR(HDR_Matriz!BI9, "Pendiente datos") -> 0 | AJ9: =IFERROR((COUNTIF(S9:AH9, "Aprobado")) / (12 - COUNTIF(S9:AH9, "N/A")), "Pendiente datos") -> 0.55555556 | AK9: En proceso | AL9: =IFERROR(IF(AK9="Acreditado", "Verde", IF(AK9="En Proceso", "Amarillo", "Rojo")), "Pendiente datos") -> Amarillo | AM9: =IFERROR(AVERAGE(AJ9, AI9), "Pendiente datos") -> 0.27777778 | AN9: Sincronizado
A10: P19 | B10: Maestro 1° Líneas | C10: M1_02 | D10: David Flores | E10: Aprobado | F10: Aprobado | G10: Aprobado | H10: Aprobado | I10: Aprobado | J10: Aprobado | K10: 7 de 7 ; 100% | L10: OK -Dentro de lo esperado | M10: OK -Dentro de lo esperado | N10: OK -Dentro de lo esperado | O10: OK -Dentro de lo esperado | P10: OK -Dentro de lo esperado | Q10: OK -Dentro de lo esperado | R10: OK -Dentro de lo esperado | S10: En proceso | T10: No Iniciado | U10: No Iniciado | V10: No Iniciado | W10: Aprobado | X10: No Iniciado | Y10: No Iniciado | Z10: No Iniciado | AA10: Aprobado | AB10: 46177 | AC10: N/A | AD10: N/A | AE10: No Iniciado | AF10: No Iniciado | AG10: N/A | AH10: N/A | AI10: 0 | AJ10: 0 | AK10: En proceso | AL10: Amarillo | AM10: 0 | AN10: Sincronizado
A11: P10 | B11: Maestro 1° Líneas | C11: M1_03 | D11: Wilber Corrales | E11: Aprobado | F11: Aprobado | G11: Aprobado | H11: Aprobado | I11: N/A | J11: Aprobado | K11: =COUNTIF(L11:R11,"*OK*") & " de 7 ; " & ROUND(COUNTIF(L11:R11,"*OK*")/7*100,0) & "%" -> 7 de 7 ; 100% | L11: OK -Dentro de lo esperado | M11: OK -Dentro de lo esperado | N11: OK -Dentro de lo esperado | O11: OK -Dentro de lo esperado | P11: OK -Dentro de lo esperado | Q11: OK -Dentro de lo esperado | R11: OK -Dentro de lo esperado | S11: En proceso | T11: No Iniciado | U11: No Iniciado | V11: No Iniciado | W11: Aprobado | X11: No Iniciado | Y11: No Iniciado | Z11: No Iniciado | AA11: Aprobado | AB11: 46178 | AC11: N/A | AD11: N/A | AE11: N/A | AF11: No Iniciado | AG11: N/A | AH11: N/A | AI11: =IFERROR(HDR_Matriz!BI11, "Pendiente datos") -> 0 | AJ11: =IFERROR((COUNTIF(S11:AH11, "Aprobado")) / (12 - COUNTIF(S11:AH11, "N/A")), "Pendiente datos") -> 0.28571429 | AK11: En proceso | AL11: =IFERROR(IF(AK11="Acreditado", "Verde", IF(AK11="En Proceso", "Amarillo", "Rojo")), "Pendiente datos") -> Amarillo | AM11: =IFERROR(AVERAGE(AJ11, AI11), "Pendiente datos") -> 0.14285714 | AN11: Sincronizado
A12: P11 | B12: Maestro 1° Líneas | C12: M1_04 | D12: Ronald Orellana | E12: Aprobado | F12: Aprobado | G12: Aprobado | H12: Aprobado | I12: N/A | J12: Aprobado | K12: =COUNTIF(L12:R12,"*OK*") & " de 7 ; " & ROUND(COUNTIF(L12:R12,"*OK*")/7*100,0) & "%" -> 7 de 7 ; 100% | L12: OK -Dentro de lo esperado | M12: OK -Dentro de lo esperado | N12: OK -Dentro de lo esperado | O12: OK -Dentro de lo esperado | P12: OK -Dentro de lo esperado | Q12: OK -Dentro de lo esperado | R12: OK -Dentro de lo esperado | S12: En proceso | T12: No Iniciado | U12: No Iniciado | V12: No Iniciado | W12: Aprobado | X12: No Iniciado | Y12: No Iniciado | Z12: No Iniciado | AA12: Aprobado | AB12: 46178 | AC12: N/A | AD12: N/A | AE12: N/A | AF12: No Iniciado | AG12: N/A | AH12: N/A | AI12: =IFERROR(HDR_Matriz!BI12, "Pendiente datos") -> 0 | AJ12: =IFERROR((COUNTIF(S12:AH12, "Aprobado")) / (12 - COUNTIF(S12:AH12, "N/A")), "Pendiente datos") -> 0.28571429 | AK12: En proceso | AL12: =IFERROR(IF(AK12="Acreditado", "Verde", IF(AK12="En Proceso", "Amarillo", "Rojo")), "Pendiente datos") -> Amarillo | AM12: =IFERROR(AVERAGE(AJ12, AI12), "Pendiente datos") -> 0.14285714 | AN12: Sincronizado
A13: P12 | B13: Maestro 1° Líneas | C13: M1_05 | D13: Maica Villca | E13: Aprobado | F13: Aprobado | G13: Aprobado | H13: Aprobado | I13: N/A | J13: Aprobado | K13: =COUNTIF(L13:R13,"*OK*") & " de 7 ; " & ROUND(COUNTIF(L13:R13,"*OK*")/7*100,0) & "%" -> 7 de 7 ; 100% | L13: OK -Dentro de lo esperado | M13: OK -Dentro de lo esperado | N13: OK -Dentro de lo esperado | O13: OK -Dentro de lo esperado | P13: OK -Dentro de lo esperado | Q13: OK -Dentro de lo esperado | R13: OK -Dentro de lo esperado | S13: Aprobado | T13: No Iniciado | U13: Aprobado | V13: No Iniciado | W13: Aprobado | X13: No Iniciado | Y13: No Iniciado | Z13: No Iniciado | AA13: Aprobado | AB13: 46177 | AC13: N/A | AD13: 46181 | AE13: N/A | AF13: No Iniciado | AG13: N/A | AH13: N/A | AI13: =IFERROR(HDR_Matriz!BI13, "Pendiente datos") -> 0 | AJ13: =IFERROR((COUNTIF(S13:AH13, "Aprobado")) / (12 - COUNTIF(S13:AH13, "N/A")), "Pendiente datos") -> 0.5 | AK13: En proceso | AL13: =IFERROR(IF(AK13="Acreditado", "Verde", IF(AK13="En Proceso", "Amarillo", "Rojo")), "Pendiente datos") -> Amarillo | AM13: =IFERROR(AVERAGE(AJ13, AI13), "Pendiente datos") -> 0.25 | AN13: Sincronizado
A14: P13 | B14: Maestro 1° Líneas | C14: M1_06 | D14: Fredy Arena | E14: Aprobado | F14: Aprobado | G14: Aprobado | H14: Aprobado | I14: N/A | J14: Aprobado | K14: =COUNTIF(L14:R14,"*OK*") & " de 7 ; " & ROUND(COUNTIF(L14:R14,"*OK*")/7*100,0) & "%" -> 7 de 7 ; 100% | L14: OK -Dentro de lo esperado | M14: OK -Dentro de lo esperado | N14: OK -Dentro de lo esperado | O14: OK -Dentro de lo esperado | P14: OK -Dentro de lo esperado | Q14: OK -Dentro de lo esperado | R14: OK -Dentro de lo esperado | S14: Aprobado | T14: No Iniciado | U14: Aprobado | V14: No Iniciado | W14: Aprobado | X14: No Iniciado | Y14: No Iniciado | Z14: No Iniciado | AA14: Aprobado | AB14: 46177 | AC14: N/A | AD14: 46181 | AE14: No Iniciado | AF14: No Iniciado | AG14: N/A | AH14: N/A | AI14: =IFERROR(HDR_Matriz!BI14, "Pendiente datos") -> 0 | AJ14: =IFERROR((COUNTIF(S14:AH14, "Aprobado")) / (12 - COUNTIF(S14:AH14, "N/A")), "Pendiente datos") -> 0.44444444 | AK14: En proceso | AL14: =IFERROR(IF(AK14="Acreditado", "Verde", IF(AK14="En Proceso", "Amarillo", "Rojo")), "Pendiente datos") -> Amarillo | AM14: =IFERROR(AVERAGE(AJ14, AI14), "Pendiente datos") -> 0.22222222 | AN14: Sincronizado
A15: P14 | B15: Maestro 2° Líneas | C15: M2_01 | D15: Roly Ipurani | E15: Aprobado | F15: Aprobado | G15: Aprobado | H15: Aprobado | I15: N/A | J15: Aprobado | K15: =COUNTIF(L15:R15,"*OK*") & " de 7 ; " & ROUND(COUNTIF(L15:R15,"*OK*")/7*100,0) & "%" -> 7 de 7 ; 100% | L15: OK -Dentro de lo esperado | M15: OK -Dentro de lo esperado | N15: OK -Dentro de lo esperado | O15: OK -Dentro de lo esperado | P15: OK -Dentro de lo esperado | Q15: OK -Dentro de lo esperado | R15: OK -Dentro de lo esperado | S15: En proceso | T15: No Iniciado | U15: No Iniciado | V15: No Iniciado | W15: Aprobado | X15: No Iniciado | Y15: No Iniciado | Z15: No Iniciado | AA15: Aprobado | AB15: 46178 | AC15: N/A | AD15: N/A | AE15: N/A | AF15: No Iniciado | AG15: N/A | AH15: N/A | AI15: =IFERROR(HDR_Matriz!BI15, "Pendiente datos") -> 0 | AJ15: =IFERROR((COUNTIF(S15:AH15, "Aprobado")) / (12 - COUNTIF(S15:AH15, "N/A")), "Pendiente datos") -> 0.28571429 | AK15: En proceso | AL15: =IFERROR(IF(AK15="Acreditado", "Verde", IF(AK15="En Proceso", "Amarillo", "Rojo")), "Pendiente datos") -> Amarillo | AM15: =IFERROR(AVERAGE(AJ15, AI15), "Pendiente datos") -> 0.14285714 | AN15: Sincronizado
A16: P15 | B16: Maestro 2° Líneas | C16: M2_02 | D16: Erasmo Castellon | E16: Aprobado | F16: Aprobado | G16: Aprobado | H16: Aprobado | I16: N/A | J16: Alterado | K16: =COUNTIF(L16:R16,"*OK*") & " de 7 ; " & ROUND(COUNTIF(L16:R16,"*OK*")/7*100,0) & "%" -> 4 de 7 ; 57% | L16: OK -Dentro de lo esperado | M16: OK -Dentro de lo esperado | N16: Obs. Bajo lo esperado | O16: OK -Dentro de lo esperado | P16: Obs. Bajo lo esperado | Q16: OK -Dentro de lo esperado | R16: Obs. Bajo lo esperado | S16: En proceso | T16: No Iniciado | U16: No Iniciado | V16: No Iniciado | W16: Aprobado | X16: No Iniciado | Y16: No Iniciado | Z16: No Iniciado | AA16: Aprobado | AB16: 46178 | AC16: N/A | AD16: N/A | AE16: N/A | AF16: No Iniciado | AG16: N/A | AH16: N/A | AI16: =IFERROR(HDR_Matriz!BI9, "Pendiente datos") -> 0 | AJ16: =IFERROR((COUNTIF(S16:AH16, "Aprobado")) / (12 - COUNTIF(S16:AH16, "N/A")), "Pendiente datos") -> 0.28571429 | AK16: En proceso | AL16: =IFERROR(IF(AK16="Acreditado", "Verde", IF(AK16="En Proceso", "Amarillo", "Rojo")), "Pendiente datos") -> Amarillo | AM16: =IFERROR(AVERAGE(AJ16, AI16), "Pendiente datos") -> 0.14285714 | AN16: Sincronizado
A17: P16 | B17: Operador | C17: OP_01 | D17: Matias Quiñenao | E17: Aprobado | F17: Aprobado | G17: Aprobado | H17: Aprobado | I17: Aprobado | J17: Aprobado | K17: =COUNTIF(L17:R17,"*OK*") & " de 7 ; " & ROUND(COUNTIF(L17:R17,"*OK*")/7*100,0) & "%" -> 7 de 7 ; 100% | L17: OK -Dentro de lo esperado | M17: OK -Dentro de lo esperado | N17: OK -Dentro de lo esperado | O17: OK -Dentro de lo esperado | P17: OK -Dentro de lo esperado | Q17: OK -Dentro de lo esperado | R17: OK -Dentro de lo esperado | S17: N/A | T17: Aprobado | U17: Aprobado | V17: No Iniciado | W17: Aprobado | X17: No Iniciado | Y17: No Iniciado | Z17: No Iniciado | AA17: No Iniciado | AB17: 46181 | AC17: N/A | AD17: Aprobado | AE17: N/A | AF17: No Iniciado | AG17: Aprobado | AH17: No Iniciado | AI17: =IFERROR(HDR_Matriz!BI17, "Pendiente datos") -> 0 | AJ17: =IFERROR((COUNTIF(S17:AH17, "Aprobado")) / (12 - COUNTIF(S17:AH17, "N/A")), "Pendiente datos") -> 0.55555556 | AK17: En proceso | AL17: =IFERROR(IF(AK17="Acreditado", "Verde", IF(AK17="En Proceso", "Amarillo", "Rojo")), "Pendiente datos") -> Amarillo | AM17: =IFERROR(AVERAGE(AJ17, AI17), "Pendiente datos") -> 0.27777778 | AN17: Sincronizado
A18: P17 | B18: Rigger | C18: RIG_01 | D18: Mauro Vega (OP1) Sebastian Morales (OP2) | E18: 46183 | F18: 46183 | G18: 46183 | H18: 46183 | I18: N/A | J18: 46183 | K18: =COUNTIF(L18:R18,"*OK*") & " de 7 ; " & ROUND(COUNTIF(L18:R18,"*OK*")/7*100,0) & "%" -> 0 de 7 ; 0% | S18: No Iniciado | T18: No Iniciado | U18: No Iniciado | V18: No Iniciado | W18: No Iniciado | X18: No Iniciado | Y18: No Iniciado | Z18: No Iniciado | AA18: No Iniciado | AB18: No Iniciado | AC18: N/A | AD18: N/A | AE18: No Iniciado | AF18: No Iniciado | AG18: N/A | AH18: N/A | AI18: =IFERROR(HDR_Matriz!BI18, "Pendiente datos") -> 0 | AJ18: =IFERROR((COUNTIF(S18:AH18, "Aprobado")) / (12 - COUNTIF(S18:AH18, "N/A")), "Pendiente datos") -> 0 | AK18: En proceso | AL18: =IFERROR(IF(AK18="Acreditado", "Verde", IF(AK18="En Proceso", "Amarillo", "Rojo")), "Pendiente datos") -> Amarillo | AM18: =IFERROR(AVERAGE(AJ18, AI18), "Pendiente datos") -> 0 | AN18: Sincronizado
A19: SUBC. | B19: Jefe Especialista Tendido | C19: CTC_01 | D19: Ismael Dones | E19: No Iniciado | F19: No Iniciado | G19: No Iniciado | H19: No Iniciado | I19: N/A | J19: No Iniciado | K19: =COUNTIF(L19:R19,"*OK*") & " de 7 ; " & ROUND(COUNTIF(L19:R19,"*OK*")/7*100,0) & "%" -> 0 de 7 ; 0% | S19: No Iniciado | T19: No Iniciado | U19: No Iniciado | V19: No Iniciado | W19: No Iniciado | X19: No Iniciado | Y19: No Iniciado | Z19: No Iniciado | AA19: No Iniciado | AB19: No Iniciado | AC19: N/A | AD19: N/A | AE19: N/A | AF19: No Iniciado | AG19: N/A | AH19: N/A | AI19: =IFERROR(HDR_Matriz!BI19, "Pendiente datos") -> 0 | AJ19: =IFERROR((COUNTIF(S19:AH19, "Aprobado")) / (12 - COUNTIF(S19:AH19, "N/A")), "Pendiente datos") -> 0 | AK19: En proceso | AL19: =IFERROR(IF(AK19="Acreditado", "Verde", IF(AK19="En Proceso", "Amarillo", "Rojo")), "Pendiente datos") -> Amarillo | AM19: =IFERROR(AVERAGE(AJ19, AI19), "Pendiente datos") -> 0 | AN19: Sincronizado
A21: P18 | B21: Maestro 2° Líneas | C21: M2_03 | D21: Teodoro Paca | E21: Alterado | F21: Aprobado | G21: Aprobado | H21: Aprobado | I21: N/A | J21: Alterado | K21: =COUNTIF(L21:R21,"*OK*") & " de 7 ; " & ROUND(COUNTIF(L21:R21,"*OK*")/7*100,0) & "%" -> 2 de 7 ; 29% | L21: Obs. Bajo lo esperado | M21: OK -Dentro de lo esperado | N21: Obs. Bajo lo esperado | O21: Obs. Bajo lo esperado | P21: Obs. Bajo lo esperado | Q21: OK -Dentro de lo esperado | R21: Obs. Bajo lo esperado | S21: Alterado | T21: No Iniciado | U21: No Iniciado | V21: No Iniciado | W21: No Iniciado | X21: No Iniciado | Y21: No Iniciado | Z21: No Iniciado | AA21: No Iniciado | AB21: No Iniciado | AE21: N/A | AF21: No Iniciado | AH21: N/A | AI21: =IFERROR(HDR_Matriz!BI16, "Pendiente datos") -> 0 | AJ21: =IFERROR((COUNTIF(S21:AH21, "Aprobado")) / (12 - COUNTIF(S21:AH21, "N/A")), "Pendiente datos") -> 0 | AK21: En proceso | AL21: =IFERROR(IF(AK21="Acreditado", "Verde", IF(AK21="En Proceso", "Amarillo", "Rojo")), "Pendiente datos") -> Amarillo | AM21: =IFERROR(AVERAGE(AJ21, AI21), "Pendiente datos") -> 0 | AN21: Sincronizado
A22: P19 | B22: Rigger | C22: RIG_02 | D22: Christian Romero - Desiste | E22: No Iniciado | F22: No Iniciado | G22: No Iniciado | H22: No Iniciado | I22: N/A | J22: No Iniciado | K22: =COUNTIF(L22:R22,"*OK*") & " de 7 ; " & ROUND(COUNTIF(L22:R22,"*OK*")/7*100,0) & "%" -> 0 de 7 ; 0% | S22: No Iniciado | T22: No Iniciado | U22: No Iniciado | V22: No Iniciado | W22: No Iniciado | X22: No Iniciado | Y22: No Iniciado | Z22: No Iniciado | AA22: No Iniciado | AB22: No Iniciado | AE22: No Iniciado | AF22: No Iniciado | AH22: N/A | AI22: =IFERROR(HDR_Matriz!BI24, "Pendiente datos") -> 0 | AJ22: =IFERROR((COUNTIF(S22:AH22, "Aprobado")) / (12 - COUNTIF(S22:AH22, "N/A")), "Pendiente datos") -> 0 | AK22: En proceso | AL22: =IFERROR(IF(AK22="Acreditado", "Verde", IF(AK22="En Proceso", "Amarillo", "Rojo")), "Pendiente datos") -> Amarillo | AM22: =IFERROR(AVERAGE(AJ22, AI22), "Pendiente datos") -> 0 | AN22: Sincronizado
A23: P20 | B23: Alarife | C23: ALA_01 | D23: Javier Lucas | E23: Alterado | F23: Aprobado | G23: Alterado | H23: Alterado | I23: N/A | J23: Aprobado | K23: =COUNTIF(L23:R23,"*OK*") & " de 7 ; " & ROUND(COUNTIF(L23:R23,"*OK*")/7*100,0) & "%" -> 7 de 7 ; 100% | L23: OK -Dentro de lo esperado | M23: OK -Dentro de lo esperado | N23: OK -Dentro de lo esperado | O23: OK -Dentro de lo esperado | P23: OK -Dentro de lo esperado | Q23: OK -Dentro de lo esperado | R23: OK -Dentro de lo esperado | S23: No Iniciado | T23: No Iniciado | U23: No Iniciado | V23: No Iniciado | W23: No Iniciado | X23: No Iniciado | Y23: No Iniciado | Z23: No Iniciado | AA23: No Iniciado | AB23: No Iniciado | AE23: N/A | AF23: No Iniciado | AH23: N/A | AI23: =IFERROR(HDR_Matriz!BI24, "Pendiente datos") -> 0 | AJ23: =IFERROR((COUNTIF(S23:AH23, "Aprobado")) / (12 - COUNTIF(S23:AH23, "N/A")), "Pendiente datos") -> 0 | AK23: En proceso | AL23: =IFERROR(IF(AK23="Acreditado", "Verde", IF(AK23="En Proceso", "Amarillo", "Rojo")), "Pendiente datos") -> Amarillo | AM23: =IFERROR(AVERAGE(AJ23, AI23), "Pendiente datos") -> 0 | AN23: Sincronizado
A24: P21 | B24: Alarife | C24: ALA_02 | D24: Giovany Prandi | E24: Solicitado el 05-06-26 | F24: Solicitado el 05-06-27 | G24: Solicitado el 05-06-28 | H24: Solicitado el 05-06-29 | I24: N/A | J24: Solicitado el 05-06-29 | K24: =COUNTIF(L24:R24,"*OK*") & " de 7 ; " & ROUND(COUNTIF(L24:R24,"*OK*")/7*100,0) & "%" -> 7 de 7 ; 100% | L24: OK -Dentro de lo esperado | M24: OK -Dentro de lo esperado | N24: OK -Dentro de lo esperado | O24: OK -Dentro de lo esperado | P24: OK -Dentro de lo esperado | Q24: OK -Dentro de lo esperado | R24: OK -Dentro de lo esperado | S24: No Iniciado | T24: No Iniciado | U24: No Iniciado | V24: No Iniciado | W24: No Iniciado | X24: No Iniciado | Y24: No Iniciado | Z24: No Iniciado | AA24: No Iniciado | AB24: No Iniciado | AE24: N/A | AF24: No Iniciado | AH24: N/A | AI24: =IFERROR(HDR_Matriz!BI25, "Pendiente datos") -> 0 | AJ24: =IFERROR((COUNTIF(S24:AH24, "Aprobado")) / (12 - COUNTIF(S24:AH24, "N/A")), "Pendiente datos") -> 0 | AK24: En proceso | AL24: =IFERROR(IF(AK24="Acreditado", "Verde", IF(AK24="En Proceso", "Amarillo", "Rojo")), "Pendiente datos") -> Amarillo | AM24: =IFERROR(AVERAGE(AJ24, AI24), "Pendiente datos") -> 0 | AN24: Sincronizado

Sheet HDR_Matriz
A1: ID | B1: Cargo | C1: Nombre | D1: 1. IRL (DS.44) | E1: 2. Derecho detener trabajo | F1: 3. Inducción a riesgos | G1: 4. DDHH | H1: 5. Inducción Escondida | I1: 6. Intro a Gral IISS | J1: 7. Intro Zona Especifica | K1: 8. Cartilla Identificación | L1: 9. Obs. Preventivas | M1: 10. Liderazgo Terreno | N1: 11. Control critico | O1: 12. Auditoria Coaching | P1: 13. Inspecciones | Q1: 14. Aislamiento Bloqueo | R1: 15. Riesgo materiales | S1: 16. Procedimiento Emergencia | T1: 17. Reglas Cardinales | U1: 18. No en nuestro lugar | V1: 19. Preocupación Crónica | W1: 20. Politica Alcohol | X1: 21. Sustancias Peligrosas | Y1: 22. Nuestro Código | Z1: 23. Entrega RIOHS | AA1: 24. Entrega EPP | AB1: 25. Entrega Procedimiento | AC1: 26. Evaluación 3D | AD1: 27. Exámen Gran Altura | AE1: 28. Exámen Altura Fisica | AF1: 29. Contrato de trabajo | AG1: 30. Permiso Trabajo | AH1: 31. Protec. Respiratoria | AI1: 32. Espacio Confinado | AJ1: 33. Trabajo en caliente | AK1: 34. Alta tensión | AL1: 35. Control riesgos electricos | AM1: 36. Trabajo en altura | AN1: 37. Rescate en altura | AO1: 38. Armado andamios | AP1: 39. Riesgo Psicosocial | AQ1: 40. Hipobaria | AR1: 41. Protec. Auditiva | AS1: 42. Radiaciones UV | AT1: 43. Conciencia carcinógenos | AU1: 44. Primeros Auxilios | AV1: 45. Uso extintores | AW1: 46. Liderazgo en Terreno | AX1: 47. Manejo defensiva | AY1: 48. Examen Psicosensométrico | AZ1: 49. Hoja Vida conductor | BA1: 50. Licencia Municipal | BB1: 51. Operador Grúa | BC1: 52. Operador Equipos | BD1: 53. Operador andamios | BE1: 54. Eventos security | BF1: 55. Condiciones climáticas | BG1: 56. Riesgo caída rocas | BH1: Total Aplica | BI1: % Avance HDR
A2: P01 | B2: =+RRHH_Control!B2 -> Administrador Contrato | C2: =+RRHH_Control!D2 -> Andrés Tebes | D2: No Iniciado | E2: No Iniciado | F2: No Iniciado | G2: No Iniciado | H2: No Iniciado | I2: No Iniciado | J2: No Iniciado | K2: No Iniciado | L2: No Iniciado | M2: No Iniciado | N2: No Iniciado | O2: No Iniciado | P2: No Iniciado | Q2: No Iniciado | R2: No Iniciado | S2: No Iniciado | T2: No Iniciado | U2: No Iniciado | V2: No Iniciado | W2: No Iniciado | X2: No Iniciado | Y2: No Iniciado | Z2: No Iniciado | AA2: No Iniciado | AB2: No Iniciado | AC2: No Iniciado | AD2: No Iniciado | AE2: No Iniciado | AF2: No Iniciado | AG2: No Iniciado | AH2: No Iniciado | AI2: No Iniciado | AJ2: No Iniciado | AK2: No Iniciado | AL2: No Iniciado | AM2: No Iniciado | AN2: No Iniciado | AO2: No Iniciado | AP2: No Iniciado | AQ2: No Iniciado | AR2: No Iniciado | AS2: No Iniciado | AT2: No Iniciado | AU2: No Iniciado | AV2: No Iniciado | AW2: No Iniciado | AX2: No Iniciado | AY2: No Iniciado | AZ2: No Iniciado | BA2: No Iniciado | BB2: No Iniciado | BC2: No Iniciado | BD2: No Iniciado | BE2: No Iniciado | BF2: No Iniciado | BG2: No Iniciado | BH2: =IFERROR(56 - COUNTIF(D2:BG2, "N/A"), "Pendiente datos") -> 56 | BI2: =IFERROR(COUNTIF(D2:BG2, "Aprobado") / BH2, "Pendiente datos") -> 0
A3: P02 | B3: =+RRHH_Control!B3 -> Asesor de Seguridad | C3: =+RRHH_Control!D3 -> Juan Carlos Santander | D3: No Iniciado | E3: No Iniciado | F3: No Iniciado | G3: No Iniciado | H3: No Iniciado | I3: No Iniciado | J3: No Iniciado | K3: No Iniciado | L3: No Iniciado | M3: No Iniciado | N3: No Iniciado | O3: No Iniciado | P3: No Iniciado | Q3: No Iniciado | R3: No Iniciado | S3: No Iniciado | T3: No Iniciado | U3: No Iniciado | V3: No Iniciado | W3: No Iniciado | X3: No Iniciado | Y3: No Iniciado | Z3: No Iniciado | AA3: No Iniciado | AB3: No Iniciado | AC3: No Iniciado | AD3: No Iniciado | AE3: No Iniciado | AF3: No Iniciado | AG3: No Iniciado | AH3: No Iniciado | AI3: No Iniciado | AJ3: No Iniciado | AK3: No Iniciado | AL3: No Iniciado | AM3: No Iniciado | AN3: No Iniciado | AO3: No Iniciado | AP3: No Iniciado | AQ3: No Iniciado | AR3: No Iniciado | AS3: No Iniciado | AT3: No Iniciado | AU3: No Iniciado | AV3: No Iniciado | AW3: No Iniciado | AX3: No Iniciado | AY3: No Iniciado | AZ3: No Iniciado | BA3: No Iniciado | BB3: No Iniciado | BC3: No Iniciado | BD3: No Iniciado | BE3: No Iniciado | BF3: No Iniciado | BG3: No Iniciado | BH3: =IFERROR(56 - COUNTIF(D3:BG3, "N/A"), "Pendiente datos") -> 56 | BI3: =IFERROR(COUNTIF(D3:BG3, "Aprobado") / BH3, "Pendiente datos") -> 0
A4: P03 | B4: =+RRHH_Control!B4 -> Jefe de Terreno | C4: =+RRHH_Control!D4 -> Leonel Sanchez | D4: No Iniciado | E4: No Iniciado | F4: No Iniciado | G4: No Iniciado | H4: No Iniciado | I4: No Iniciado | J4: No Iniciado | K4: No Iniciado | L4: No Iniciado | M4: No Iniciado | N4: No Iniciado | O4: No Iniciado | P4: No Iniciado | Q4: No Iniciado | R4: No Iniciado | S4: No Iniciado | T4: No Iniciado | U4: No Iniciado | V4: No Iniciado | W4: No Iniciado | X4: No Iniciado | Y4: No Iniciado | Z4: No Iniciado | AA4: No Iniciado | AB4: No Iniciado | AC4: No Iniciado | AD4: No Iniciado | AE4: No Iniciado | AF4: No Iniciado | AG4: No Iniciado | AH4: No Iniciado | AI4: No Iniciado | AJ4: No Iniciado | AK4: No Iniciado | AL4: No Iniciado | AM4: No Iniciado | AN4: No Iniciado | AO4: No Iniciado | AP4: No Iniciado | AQ4: No Iniciado | AR4: No Iniciado | AS4: No Iniciado | AT4: No Iniciado | AU4: No Iniciado | AV4: No Iniciado | AW4: No Iniciado | AX4: No Iniciado | AY4: No Iniciado | AZ4: No Iniciado | BA4: No Iniciado | BB4: No Iniciado | BC4: No Iniciado | BD4: No Iniciado | BE4: No Iniciado | BF4: No Iniciado | BG4: No Iniciado | BH4: =IFERROR(56 - COUNTIF(D4:BG4, "N/A"), "Pendiente datos") -> 56 | BI4: =IFERROR(COUNTIF(D4:BG4, "Aprobado") / BH4, "Pendiente datos") -> 0
A5: P04 | B5: =+RRHH_Control!B5 -> Supervisor de Terreno | C5: =+RRHH_Control!D5 -> Ulises Psijas | D5: No Iniciado | E5: No Iniciado | F5: No Iniciado | G5: No Iniciado | H5: No Iniciado | I5: No Iniciado | J5: No Iniciado | K5: No Iniciado | L5: No Iniciado | M5: No Iniciado | N5: No Iniciado | O5: No Iniciado | P5: No Iniciado | Q5: No Iniciado | R5: No Iniciado | S5: No Iniciado | T5: No Iniciado | U5: No Iniciado | V5: No Iniciado | W5: No Iniciado | X5: No Iniciado | Y5: No Iniciado | Z5: No Iniciado | AA5: No Iniciado | AB5: No Iniciado | AC5: No Iniciado | AD5: No Iniciado | AE5: No Iniciado | AF5: No Iniciado | AG5: No Iniciado | AH5: No Iniciado | AI5: No Iniciado | AJ5: No Iniciado | AK5: No Iniciado | AL5: No Iniciado | AM5: No Iniciado | AN5: No Iniciado | AO5: No Iniciado | AP5: No Iniciado | AQ5: No Iniciado | AR5: No Iniciado | AS5: No Iniciado | AT5: No Iniciado | AU5: No Iniciado | AV5: No Iniciado | AW5: No Iniciado | AX5: No Iniciado | AY5: No Iniciado | AZ5: No Iniciado | BA5: No Iniciado | BB5: No Iniciado | BC5: No Iniciado | BD5: No Iniciado | BE5: No Iniciado | BF5: No Iniciado | BG5: No Iniciado | BH5: =IFERROR(56 - COUNTIF(D5:BG5, "N/A"), "Pendiente datos") -> 56 | BI5: =IFERROR(COUNTIF(D5:BG5, "Aprobado") / BH5, "Pendiente datos") -> 0
A6: P05 | B6: =+RRHH_Control!B6 -> Encargado Administrativo | C6: =+RRHH_Control!D6 -> Jesenia Tapia | D6: No Iniciado | E6: No Iniciado | F6: No Iniciado | G6: No Iniciado | H6: No Iniciado | I6: No Iniciado | J6: No Iniciado | K6: No Iniciado | L6: No Iniciado | M6: No Iniciado | N6: No Iniciado | O6: No Iniciado | P6: No Iniciado | Q6: No Iniciado | R6: No Iniciado | S6: No Iniciado | T6: No Iniciado | U6: No Iniciado | V6: No Iniciado | W6: No Iniciado | X6: No Iniciado | Y6: No Iniciado | Z6: No Iniciado | AA6: No Iniciado | AB6: No Iniciado | AC6: No Iniciado | AD6: No Iniciado | AE6: No Iniciado | AF6: No Iniciado | AG6: No Iniciado | AH6: No Iniciado | AI6: No Iniciado | AJ6: No Iniciado | AK6: No Iniciado | AL6: No Iniciado | AM6: No Iniciado | AN6: No Iniciado | AO6: No Iniciado | AP6: No Iniciado | AQ6: No Iniciado | AR6: No Iniciado | AS6: No Iniciado | AT6: No Iniciado | AU6: No Iniciado | AV6: No Iniciado | AW6: No Iniciado | AX6: No Iniciado | AY6: No Iniciado | AZ6: No Iniciado | BA6: No Iniciado | BB6: No Iniciado | BC6: No Iniciado | BD6: No Iniciado | BE6: No Iniciado | BF6: No Iniciado | BG6: No Iniciado | BH6: =IFERROR(56 - COUNTIF(D6:BG6, "N/A"), "Pendiente datos") -> 56 | BI6: =IFERROR(COUNTIF(D6:BG6, "Aprobado") / BH6, "Pendiente datos") -> 0
A7: P06 | B7: =+RRHH_Control!B7 -> Topógrafo | C7: =+RRHH_Control!D7 -> Manuel Tapia | D7: No Iniciado | E7: No Iniciado | F7: No Iniciado | G7: No Iniciado | H7: No Iniciado | I7: No Iniciado | J7: No Iniciado | K7: No Iniciado | L7: No Iniciado | M7: No Iniciado | N7: No Iniciado | O7: No Iniciado | P7: No Iniciado | Q7: No Iniciado | R7: No Iniciado | S7: No Iniciado | T7: No Iniciado | U7: No Iniciado | V7: No Iniciado | W7: No Iniciado | X7: No Iniciado | Y7: No Iniciado | Z7: No Iniciado | AA7: No Iniciado | AB7: No Iniciado | AC7: No Iniciado | AD7: No Iniciado | AE7: No Iniciado | AF7: No Iniciado | AG7: No Iniciado | AH7: No Iniciado | AI7: No Iniciado | AJ7: No Iniciado | AK7: No Iniciado | AL7: No Iniciado | AM7: No Iniciado | AN7: No Iniciado | AO7: No Iniciado | AP7: No Iniciado | AQ7: No Iniciado | AR7: No Iniciado | AS7: No Iniciado | AT7: No Iniciado | AU7: No Iniciado | AV7: No Iniciado | AW7: No Iniciado | AX7: No Iniciado | AY7: No Iniciado | AZ7: No Iniciado | BA7: No Iniciado | BB7: No Iniciado | BC7: No Iniciado | BD7: No Iniciado | BE7: No Iniciado | BF7: No Iniciado | BG7: No Iniciado | BH7: =IFERROR(56 - COUNTIF(D7:BG7, "N/A"), "Pendiente datos") -> 56 | BI7: =IFERROR(COUNTIF(D7:BG7, "Aprobado") / BH7, "Pendiente datos") -> 0
A8: P07 | B8: =+RRHH_Control!B8 -> Maestro 1° Líneas (Interno Alarife) | C8: =+RRHH_Control!D8 -> Orlando Maita | D8: No Iniciado | E8: No Iniciado | F8: No Iniciado | G8: No Iniciado | H8: No Iniciado | I8: No Iniciado | J8: No Iniciado | K8: No Iniciado | L8: No Iniciado | M8: No Iniciado | N8: No Iniciado | O8: No Iniciado | P8: No Iniciado | Q8: No Iniciado | R8: No Iniciado | S8: No Iniciado | T8: No Iniciado | U8: No Iniciado | V8: No Iniciado | W8: No Iniciado | X8: No Iniciado | Y8: No Iniciado | Z8: No Iniciado | AA8: No Iniciado | AB8: No Iniciado | AC8: No Iniciado | AD8: No Iniciado | AE8: No Iniciado | AF8: No Iniciado | AG8: No Iniciado | AH8: No Iniciado | AI8: No Iniciado | AJ8: No Iniciado | AK8: No Iniciado | AL8: No Iniciado | AM8: No Iniciado | AN8: No Iniciado | AO8: No Iniciado | AP8: No Iniciado | AQ8: No Iniciado | AR8: No Iniciado | AS8: No Iniciado | AT8: No Iniciado | AU8: No Iniciado | AV8: No Iniciado | AW8: No Iniciado | AX8: No Iniciado | AY8: No Iniciado | AZ8: No Iniciado | BA8: No Iniciado | BB8: No Iniciado | BC8: No Iniciado | BD8: No Iniciado | BE8: No Iniciado | BF8: No Iniciado | BG8: No Iniciado | BH8: =IFERROR(56 - COUNTIF(D8:BG8, "N/A"), "Pendiente datos") -> 56 | BI8: =IFERROR(COUNTIF(D8:BG8, "Aprobado") / BH8, "Pendiente datos") -> 0
A9: P08 | B9: =+RRHH_Control!B9 -> Maestro 1° Líneas | C9: =+RRHH_Control!D9 -> Wilmer Chambi | D9: No Iniciado | E9: No Iniciado | F9: No Iniciado | G9: No Iniciado | H9: No Iniciado | I9: No Iniciado | J9: No Iniciado | K9: No Iniciado | L9: No Iniciado | M9: No Iniciado | N9: No Iniciado | O9: No Iniciado | P9: No Iniciado | Q9: No Iniciado | R9: No Iniciado | S9: No Iniciado | T9: No Iniciado | U9: No Iniciado | V9: No Iniciado | W9: No Iniciado | X9: No Iniciado | Y9: No Iniciado | Z9: No Iniciado | AA9: No Iniciado | AB9: No Iniciado | AC9: No Iniciado | AD9: No Iniciado | AE9: No Iniciado | AF9: No Iniciado | AG9: No Iniciado | AH9: No Iniciado | AI9: No Iniciado | AJ9: No Iniciado | AK9: No Iniciado | AL9: No Iniciado | AM9: No Iniciado | AN9: No Iniciado | AO9: No Iniciado | AP9: No Iniciado | AQ9: No Iniciado | AR9: No Iniciado | AS9: No Iniciado | AT9: No Iniciado | AU9: No Iniciado | AV9: No Iniciado | AW9: No Iniciado | AX9: No Iniciado | AY9: No Iniciado | AZ9: No Iniciado | BA9: No Iniciado | BB9: No Iniciado | BC9: No Iniciado | BD9: No Iniciado | BE9: No Iniciado | BF9: No Iniciado | BG9: No Iniciado | BH9: =IFERROR(56 - COUNTIF(D9:BG9, "N/A"), "Pendiente datos") -> 56 | BI9: =IFERROR(COUNTIF(D9:BG9, "Aprobado") / BH9, "Pendiente datos") -> 0
A10: P09 | B10: =+RRHH_Control!B10 -> Maestro 1° Líneas | C10: =+RRHH_Control!D10 -> David Flores | D10: No Iniciado | E10: No Iniciado | F10: No Iniciado | G10: No Iniciado | H10: No Iniciado | I10: No Iniciado | J10: No Iniciado | K10: No Iniciado | L10: No Iniciado | M10: No Iniciado | N10: No Iniciado | O10: No Iniciado | P10: No Iniciado | Q10: No Iniciado | R10: No Iniciado | S10: No Iniciado | T10: No Iniciado | U10: No Iniciado | V10: No Iniciado | W10: No Iniciado | X10: No Iniciado | Y10: No Iniciado | Z10: No Iniciado | AA10: No Iniciado | AB10: No Iniciado | AC10: No Iniciado | AD10: No Iniciado | AE10: No Iniciado | AF10: No Iniciado | AG10: No Iniciado | AH10: No Iniciado | AI10: No Iniciado | AJ10: No Iniciado | AK10: No Iniciado | AL10: No Iniciado | AM10: No Iniciado | AN10: No Iniciado | AO10: No Iniciado | AP10: No Iniciado | AQ10: No Iniciado | AR10: No Iniciado | AS10: No Iniciado | AT10: No Iniciado | AU10: No Iniciado | AV10: No Iniciado | AW10: No Iniciado | AX10: No Iniciado | AY10: No Iniciado | AZ10: No Iniciado | BA10: No Iniciado | BB10: No Iniciado | BC10: No Iniciado | BD10: No Iniciado | BE10: No Iniciado | BF10: No Iniciado | BG10: No Iniciado | BH10: =IFERROR(56 - COUNTIF(D10:BG10, "N/A"), "Pendiente datos") -> 56 | BI10: =IFERROR(COUNTIF(D10:BG10, "Aprobado") / BH10, "Pendiente datos") -> 0
A11: P10 | B11: =+RRHH_Control!B11 -> Maestro 1° Líneas | C11: =+RRHH_Control!D11 -> Wilber Corrales | D11: No Iniciado | E11: No Iniciado | F11: No Iniciado | G11: No Iniciado | H11: No Iniciado | I11: No Iniciado | J11: No Iniciado | K11: No Iniciado | L11: No Iniciado | M11: No Iniciado | N11: No Iniciado | O11: No Iniciado | P11: No Iniciado | Q11: No Iniciado | R11: No Iniciado | S11: No Iniciado | T11: No Iniciado | U11: No Iniciado | V11: No Iniciado | W11: No Iniciado | X11: No Iniciado | Y11: No Iniciado | Z11: No Iniciado | AA11: No Iniciado | AB11: No Iniciado | AC11: No Iniciado | AD11: No Iniciado | AE11: No Iniciado | AF11: No Iniciado | AG11: No Iniciado | AH11: No Iniciado | AI11: No Iniciado | AJ11: No Iniciado | AK11: No Iniciado | AL11: No Iniciado | AM11: No Iniciado | AN11: No Iniciado | AO11: No Iniciado | AP11: No Iniciado | AQ11: No Iniciado | AR11: No Iniciado | AS11: No Iniciado | AT11: No Iniciado | AU11: No Iniciado | AV11: No Iniciado | AW11: No Iniciado | AX11: No Iniciado | AY11: No Iniciado | AZ11: No Iniciado | BA11: No Iniciado | BB11: No Iniciado | BC11: No Iniciado | BD11: No Iniciado | BE11: No Iniciado | BF11: No Iniciado | BG11: No Iniciado | BH11: =IFERROR(56 - COUNTIF(D11:BG11, "N/A"), "Pendiente datos") -> 56 | BI11: =IFERROR(COUNTIF(D11:BG11, "Aprobado") / BH11, "Pendiente datos") -> 0
A12: P11 | B12: =+RRHH_Control!B12 -> Maestro 1° Líneas | C12: =+RRHH_Control!D12 -> Ronald Orellana | D12: No Iniciado | E12: No Iniciado | F12: No Iniciado | G12: No Iniciado | H12: No Iniciado | I12: No Iniciado | J12: No Iniciado | K12: No Iniciado | L12: No Iniciado | M12: No Iniciado | N12: No Iniciado | O12: No Iniciado | P12: No Iniciado | Q12: No Iniciado | R12: No Iniciado | S12: No Iniciado | T12: No Iniciado | U12: No Iniciado | V12: No Iniciado | W12: No Iniciado | X12: No Iniciado | Y12: No Iniciado | Z12: No Iniciado | AA12: No Iniciado | AB12: No Iniciado | AC12: No Iniciado | AD12: No Iniciado | AE12: No Iniciado | AF12: No Iniciado | AG12: No Iniciado | AH12: No Iniciado | AI12: No Iniciado | AJ12: No Iniciado | AK12: No Iniciado | AL12: No Iniciado | AM12: No Iniciado | AN12: No Iniciado | AO12: No Iniciado | AP12: No Iniciado | AQ12: No Iniciado | AR12: No Iniciado | AS12: No Iniciado | AT12: No Iniciado | AU12: No Iniciado | AV12: No Iniciado | AW12: No Iniciado | AX12: No Iniciado | AY12: No Iniciado | AZ12: No Iniciado | BA12: No Iniciado | BB12: No Iniciado | BC12: No Iniciado | BD12: No Iniciado | BE12: No Iniciado | BF12: No Iniciado | BG12: No Iniciado | BH12: =IFERROR(56 - COUNTIF(D12:BG12, "N/A"), "Pendiente datos") -> 56 | BI12: =IFERROR(COUNTIF(D12:BG12, "Aprobado") / BH12, "Pendiente datos") -> 0
A13: P12 | B13: =+RRHH_Control!B13 -> Maestro 1° Líneas | C13: =+RRHH_Control!D13 -> Maica Villca | D13: No Iniciado | E13: No Iniciado | F13: No Iniciado | G13: No Iniciado | H13: No Iniciado | I13: No Iniciado | J13: No Iniciado | K13: No Iniciado | L13: No Iniciado | M13: No Iniciado | N13: No Iniciado | O13: No Iniciado | P13: No Iniciado | Q13: No Iniciado | R13: No Iniciado | S13: No Iniciado | T13: No Iniciado | U13: No Iniciado | V13: No Iniciado | W13: No Iniciado | X13: No Iniciado | Y13: No Iniciado | Z13: No Iniciado | AA13: No Iniciado | AB13: No Iniciado | AC13: No Iniciado | AD13: No Iniciado | AE13: No Iniciado | AF13: No Iniciado | AG13: No Iniciado | AH13: No Iniciado | AI13: No Iniciado | AJ13: No Iniciado | AK13: No Iniciado | AL13: No Iniciado | AM13: No Iniciado | AN13: No Iniciado | AO13: No Iniciado | AP13: No Iniciado | AQ13: No Iniciado | AR13: No Iniciado | AS13: No Iniciado | AT13: No Iniciado | AU13: No Iniciado | AV13: No Iniciado | AW13: No Iniciado | AX13: No Iniciado | AY13: No Iniciado | AZ13: No Iniciado | BA13: No Iniciado | BB13: No Iniciado | BC13: No Iniciado | BD13: No Iniciado | BE13: No Iniciado | BF13: No Iniciado | BG13: No Iniciado | BH13: =IFERROR(56 - COUNTIF(D13:BG13, "N/A"), "Pendiente datos") -> 56 | BI13: =IFERROR(COUNTIF(D13:BG13, "Aprobado") / BH13, "Pendiente datos") -> 0
... A15: P14 | B15: =+RRHH_Control!B15 -> Maestro 2° Líneas | C15: =+RRHH_Control!D15 -> Roly Ipurani | D15: No Iniciado | E15: No Iniciado | F15: No Iniciado | G15: No Iniciado | H15: No Iniciado | I15: No Iniciado | J15: No Iniciado | K15: No Iniciado | L15: No Iniciado | M15: No Iniciado | N15: No Iniciado | O15: No Iniciado | P15: No Iniciado | Q15: No Iniciado | R15: No Iniciado | S15: No Iniciado | T15: No Iniciado | U15: No Iniciado | V15: No Iniciado | W15: No Iniciado | X15: No Iniciado | Y15: No Iniciado | Z15: No Iniciado | AA15: No Iniciado | AB15: No Iniciado | AC15: No Iniciado | AD15: No Iniciado | AE15: No Iniciado | AF15: No Iniciado | AG15: No Iniciado | AH15: No Iniciado | AI15: No Iniciado | AJ15: No Iniciado | AK15: No Iniciado | AL15: No Iniciado | AM15: No Iniciado | AN15: No Iniciado | AO15: No Iniciado | AP15: No Iniciado | AQ15: No Iniciado | AR15: No Iniciado | AS15: No Iniciado | AT15: No Iniciado | AU15: No Iniciado | AV15: No Iniciado | AW15: No Iniciado | AX15: No Iniciado | AY15: No Iniciado | AZ15: No Iniciado | BA15: No Iniciado | BB15: No Iniciado | BC15: No Iniciado | BD15: No Iniciado | BE15: No Iniciado | BF15: No Iniciado | BG15: No Iniciado | BH15: =IFERROR(56 - COUNTIF(D15:BG15, "N/A"), "Pendiente datos") -> 56 | BI15: =IFERROR(COUNTIF(D15:BG15, "Aprobado") / BH15, "Pendiente datos") -> 0
A16: P15 | B16: =+RRHH_Control!B21 -> Maestro 2° Líneas | C16: =+RRHH_Control!D21 -> Teodoro Paca | D16: No Iniciado | E16: No Iniciado | F16: No Iniciado | G16: No Iniciado | H16: No Iniciado | I16: No Iniciado | J16: No Iniciado | K16: No Iniciado | L16: No Iniciado | M16: No Iniciado | N16: No Iniciado | O16: No Iniciado | P16: No Iniciado | Q16: No Iniciado | R16: No Iniciado | S16: No Iniciado | T16: No Iniciado | U16: No Iniciado | V16: No Iniciado | W16: No Iniciado | X16: No Iniciado | Y16: No Iniciado | Z16: No Iniciado | AA16: No Iniciado | AB16: No Iniciado | AC16: No Iniciado | AD16: No Iniciado | AE16: No Iniciado | AF16: No Iniciado | AG16: No Iniciado | AH16: No Iniciado | AI16: No Iniciado | AJ16: No Iniciado | AK16: No Iniciado | AL16: No Iniciado | AM16: No Iniciado | AN16: No Iniciado | AO16: No Iniciado | AP16: No Iniciado | AQ16: No Iniciado | AR16: No Iniciado | AS16: No Iniciado | AT16: No Iniciado | AU16: No Iniciado | AV16: No Iniciado | AW16: No Iniciado | AX16: No Iniciado | AY16: No Iniciado | AZ16: No Iniciado | BA16: No Iniciado | BB16: No Iniciado | BC16: No Iniciado | BD16: No Iniciado | BE16: No Iniciado | BF16: No Iniciado | BG16: No Iniciado | BH16: =IFERROR(56 - COUNTIF(D16:BG16, "N/A"), "Pendiente datos") -> 56 | BI16: =IFERROR(COUNTIF(D16:BG16, "Aprobado") / BH16, "Pendiente datos") -> 0
A17: P16 | B17: =+RRHH_Control!B17 -> Operador | C17: =+RRHH_Control!D17 -> Matias Quiñenao | D17: No Iniciado | E17: No Iniciado | F17: No Iniciado | G17: No Iniciado | H17: No Iniciado | I17: No Iniciado | J17: No Iniciado | K17: No Iniciado | L17: No Iniciado | M17: No Iniciado | N17: No Iniciado | O17: No Iniciado | P17: No Iniciado | Q17: No Iniciado | R17: No Iniciado | S17: No Iniciado | T17: No Iniciado | U17: No Iniciado | V17: No Iniciado | W17: No Iniciado | X17: No Iniciado | Y17: No Iniciado | Z17: No Iniciado | AA17: No Iniciado | AB17: No Iniciado | AC17: No Iniciado | AD17: No Iniciado | AE17: No Iniciado | AF17: No Iniciado | AG17: No Iniciado | AH17: No Iniciado | AI17: No Iniciado | AJ17: No Iniciado | AK17: No Iniciado | AL17: No Iniciado | AM17: No Iniciado | AN17: No Iniciado | AO17: No Iniciado | AP17: No Iniciado | AQ17: No Iniciado | AR17: No Iniciado | AS17: No Iniciado | AT17: No Iniciado | AU17: No Iniciado | AV17: No Iniciado | AW17: No Iniciado | AX17: No Iniciado | AY17: No Iniciado | AZ17: No Iniciado | BA17: No Iniciado | BB17: No Iniciado | BC17: No Iniciado | BD17: No Iniciado | BE17: No Iniciado | BF17: No Iniciado | BG17: No Iniciado | BH17: =IFERROR(56 - COUNTIF(D17:BG17, "N/A"), "Pendiente datos") -> 56 | BI17: =IFERROR(COUNTIF(D17:BG17, "Aprobado") / BH17, "Pendiente datos") -> 0
A18: P17 | B18: =+RRHH_Control!B18 -> Rigger | C18: =+RRHH_Control!D18 -> Mauro Vega (OP1) Sebastian Morales (OP2) | D18: No Iniciado | E18: No Iniciado | F18: No Iniciado | G18: No Iniciado | H18: No Iniciado | I18: No Iniciado | J18: No Iniciado | K18: No Iniciado | L18: No Iniciado | M18: No Iniciado | N18: No Iniciado | O18: No Iniciado | P18: No Iniciado | Q18: No Iniciado | R18: No Iniciado | S18: No Iniciado | T18: No Iniciado | U18: No Iniciado | V18: No Iniciado | W18: No Iniciado | X18: No Iniciado | Y18: No Iniciado | Z18: No Iniciado | AA18: No Iniciado | AB18: No Iniciado | AC18: No Iniciado | AD18: No Iniciado | AE18: No Iniciado | AF18: No Iniciado | AG18: No Iniciado | AH18: No Iniciado | AI18: No Iniciado | AJ18: No Iniciado | AK18: No Iniciado | AL18: No Iniciado | AM18: No Iniciado | AN18: No Iniciado | AO18: No Iniciado | AP18: No Iniciado | AQ18: No Iniciado | AR18: No Iniciado | AS18: No Iniciado | AT18: No Iniciado | AU18: No Iniciado | AV18: No Iniciado | AW18: No Iniciado | AX18: No Iniciado | AY18: No Iniciado | AZ18: No Iniciado | BA18: No Iniciado | BB18: No Iniciado | BC18: No Iniciado | BD18: No Iniciado | BE18: No Iniciado | BF18: No Iniciado | BG18: No Iniciado | BH18: =IFERROR(56 - COUNTIF(D18:BG18, "N/A"), "Pendiente datos") -> 56 | BI18: =IFERROR(COUNTIF(D18:BG18, "Aprobado") / BH18, "Pendiente datos") -> 0
A19: P18 | B19: =+RRHH_Control!B19 -> Jefe Especialista Tendido | C19: =+RRHH_Control!D19 -> Ismael Dones | D19: No Iniciado | E19: No Iniciado | F19: No Iniciado | G19: No Iniciado | H19: No Iniciado | I19: No Iniciado | J19: No Iniciado | K19: No Iniciado | L19: No Iniciado | M19: No Iniciado | N19: No Iniciado | O19: No Iniciado | P19: No Iniciado | Q19: No Iniciado | R19: No Iniciado | S19: No Iniciado | T19: No Iniciado | U19: No Iniciado | V19: No Iniciado | W19: No Iniciado | X19: No Iniciado | Y19: No Iniciado | Z19: No Iniciado | AA19: No Iniciado | AB19: No Iniciado | AC19: No Iniciado | AD19: No Iniciado | AE19: No Iniciado | AF19: No Iniciado | AG19: No Iniciado | AH19: No Iniciado | AI19: No Iniciado | AJ19: No Iniciado | AK19: No Iniciado | AL19: No Iniciado | AM19: No Iniciado | AN19: No Iniciado | AO19: No Iniciado | AP19: No Iniciado | AQ19: No Iniciado | AR19: No Iniciado | AS19: No Iniciado | AT19: No Iniciado | AU19: No Iniciado | AV19: No Iniciado | AW19: No Iniciado | AX19: No Iniciado | AY19: No Iniciado | AZ19: No Iniciado | BA19: No Iniciado | BB19: No Iniciado | BC19: No Iniciado | BD19: No Iniciado | BE19: No Iniciado | BF19: No Iniciado | BG19: No Iniciado | BH19: =IFERROR(56 - COUNTIF(D19:BG19, "N/A"), "Pendiente datos") -> 56 | BI19: =IFERROR(COUNTIF(D19:BG19, "Aprobado") / BH19, "Pendiente datos") -> 0
A21: P19 | B21: Maestro 1° | C21: David Flores | D21: No Iniciado | E21: No Iniciado | F21: No Iniciado | G21: No Iniciado | H21: No Iniciado | I21: No Iniciado | J21: No Iniciado | K21: No Iniciado | L21: No Iniciado | M21: No Iniciado | N21: No Iniciado | O21: No Iniciado | P21: No Iniciado | Q21: No Iniciado | R21: No Iniciado | S21: No Iniciado | T21: No Iniciado | U21: No Iniciado | V21: No Iniciado | W21: No Iniciado | X21: No Iniciado | Y21: No Iniciado | Z21: No Iniciado | AA21: No Iniciado | AB21: No Iniciado | AC21: No Iniciado | AD21: No Iniciado | AE21: No Iniciado | AF21: No Iniciado | AG21: No Iniciado | AH21: No Iniciado | AI21: No Iniciado | AJ21: No Iniciado | AK21: No Iniciado | AL21: No Iniciado | AM21: No Iniciado | AN21: No Iniciado | AO21: No Iniciado | AP21: No Iniciado | AQ21: No Iniciado | AR21: No Iniciado | AS21: No Iniciado | AT21: No Iniciado | AU21: No Iniciado | AV21: No Iniciado | AW21: No Iniciado | AX21: No Iniciado | AY21: No Iniciado | AZ21: No Iniciado | BA21: No Iniciado | BB21: No Iniciado | BC21: No Iniciado | BD21: No Iniciado | BE21: No Iniciado | BF21: No Iniciado | BG21: No Iniciado | BH21: =IFERROR(56 - COUNTIF(D21:BG21, "N/A"), "Pendiente datos") -> 56 | BI21: =IFERROR(COUNTIF(D21:BG21, "Aprobado") / BH21, "Pendiente datos") -> 0
A22: P20 | B22: Maestro 1° | C22: Orlando Maita | D22: No Iniciado | E22: No Iniciado | F22: No Iniciado | G22: No Iniciado | H22: No Iniciado | I22: No Iniciado | J22: No Iniciado | K22: No Iniciado | L22: No Iniciado | M22: No Iniciado | N22: No Iniciado | O22: No Iniciado | P22: No Iniciado | Q22: No Iniciado | R22: No Iniciado | S22: No Iniciado | T22: No Iniciado | U22: No Iniciado | V22: No Iniciado | W22: No Iniciado | X22: No Iniciado | Y22: No Iniciado | Z22: No Iniciado | AA22: No Iniciado | AB22: No Iniciado | AC22: No Iniciado | AD22: No Iniciado | AE22: No Iniciado | AF22: No Iniciado | AG22: No Iniciado | AH22: No Iniciado | AI22: No Iniciado | AJ22: No Iniciado | AK22: No Iniciado | AL22: No Iniciado | AM22: No Iniciado | AN22: No Iniciado | AO22: No Iniciado | AP22: No Iniciado | AQ22: No Iniciado | AR22: No Iniciado | AS22: No Iniciado | AT22: No Iniciado | AU22: No Iniciado | AV22: No Iniciado | AW22: No Iniciado | AX22: No Iniciado | AY22: No Iniciado | AZ22: No Iniciado | BA22: No Iniciado | BB22: No Iniciado | BC22: No Iniciado | BD22: No Iniciado | BE22: No Iniciado | BF22: No Iniciado | BG22: No Iniciado | BH22: =IFERROR(56 - COUNTIF(D22:BG22, "N/A"), "Pendiente datos") -> 56 | BI22: =IFERROR(COUNTIF(D22:BG22, "Aprobado") / BH22, "Pendiente datos") -> 0

Sheet Organigrama 
P3: 1 | V3: 5X2 | AQ3: Total Organigrama | AR3: =+P3+E11+E15+P11+AB11+AJ11+P17+K22+U22+K31+U26 -> 17
P4: Administrador
P6: Andres Tebes | W6: Anexo
E11: 1 | I11: 5X2 | P11: 1 | W11: 5X2 | AB11: 1 | AG11: 5X2 | AJ11: 1 | AN11: 5X2
E12: Topógrafo | P12: Supervisor de Montaje y Tendido | AB12: Administrativo & RRLL | AJ12: HSEC
E13: Manuel Tapia
P14: Leonel Sanchez | W14: Anexo | AB14: Jesenia Tapia | AG14: Ctto | AJ14: Juan Carlos Santander | AN14: Anexo
E15: 1 | I15: 5X2
E16: Alarife
E17: =+RRHH_Control!D8 -> Orlando Maita | P17: 1 | W17: 5X2
P18: Sup. Terreno
P19: Ulises Psijas
K22: 6 | R22: 5X2 | U22: 1 | AA22: 5X2
K23: M1 Montaje y Tendido | U23: Operador Camión Pluma
K24: 1 | L24: Wilmer Chambi | O24: / | P24: Maestro 1° Senior | U24: 1 | V24: =+RRHH_Control!D17 -> Matias Quiñenao | AA24: Anexo
K25: 2 | L25: Ronald Orellana | O25: / | P25: Maestro 1°
K26: 3 | L26: Wilber Corrales | O26: / | P26: Maestro 1° | U26: 1 | AA26: 5X2
K27: 4 | L27: Erasmo Castellon | O27: / | P27: Maestro 1° | U27: Rigger
K28: 5 | L28: Maica Villca | O28: / | P28: Maestro 1° | U28: 1 | V28: =+RRHH_Control!D18 -> Mauro Vega (OP1) Sebastian Morales (OP2)
K29: 6 | L29: Fredy Arena | O29: / | P29: Maestro 1°
K31: 2 | R31: 5X2
K32: M2 Montaje y Tendido
K33: 1 | L33: Roly Ipurani | O33: / | P33: Maestro 2°
K34: 2 | O34: / | P34: Maestro 2°

Sheet Listas
A1: Estado | B1: Acreditado | D1: Estado KANBAN | F1: Responsables | H1: Prioridad | J1: Descripción del Costo | L1: Tipo de Costo | N1: Aversion al Riesgo | P1: Descripción de la Partida
A2: No Iniciado | B2: En proceso | D2: Backlog / Por Iniciar | F2: Andres Tebes | H2: Alta | J2: Supervisor de Terreno | L2: Factura Pago 30 días | N2: OK -Dentro de lo esperado | P2: Supervisor de Terreno
A3: Programado | B3: Retrasado | D3: En Proceso | F3: Alex Vergara | H3: Media | J3: Administrativo de Obras y RRLL | L3: Factura Pago Contado | N3: Obs. Bajo lo esperado | P3: Administrativo de Obras y RRLL
A4: En proceso | D4: En Revisión / MEL | F4: Banesa Garrido | H4: Baja | J4: Topógrafo | L4: Caja Chica / Fondo Fijo | P4: Topógrafo
A5: Pendiente doc. | D5: Aprobado / Terminado | F5: Bárbara Tureo | J5: Alarife | P5: Alarife
A6: Aprobado | D6: Bloqueado / Riesgo | F6: Claudio Cajas | J6: Maestro 1° Líneas Senior | P6: Maestro 1° Líneas Senior
A7: Alterado | F7: Claudio Cajas | J7: Maestro 1° Líneas | P7: Maestro 1° Líneas
A8: Eliminado | F8: Franklin Godoy | J8: Maestro 2° Líneas | P8: Maestro 2° Líneas
A9: N/A | F9: Javier Gomez | J9: Operador Camión Pluma | P9: Operador Camión Pluma
F10: Jesenia Ramirez | J10: Rigger | P10: Rigger
F11: Jessica Ortiz | J11: Instalación y Equipamiento Oficina Faena | P11: Instalación y Equipamiento Oficina Faena
F12: Jose Contuliano | J12: Suministros Menores (Agua, Café, etc.) | P12: Suministros Menores (Agua, Café, etc.)
F13: Juan Carlos Gonzalez | J13: Implementos HSEC (Extintor, Camilla) | P13: Implementos HSEC (Extintor, Camilla)
F14: Juan Carlos Santander | J14: Arriendo Camionetas 4x4 | P14: Arriendo Camionetas 4x4
F15: Kathia San Martin | J15: Arriendo Camión Pluma 20 Ton | P15: Arriendo Camión Pluma 20 Ton
F16: Leonel Sanchez | J16: Equipos HTLS (Prensa, Alzabobina, Cordina) | P16: Equipos HTLS (Prensa, Alzabobina, Cordina)
F17: Rodrigo Palma | J17: Generador 30 kVA | P17: Generador 30 kVA
F18: Ulises Psijas | J18: Herramientas e Implementos Menores (Escalas, Señalética) | P18: Herramientas e Implementos Menores (Escalas, Señalética)
J19: Arriendo Container Oficina | P19: Arriendo Container Oficina
J20: Arriendo Baños Químicos | P20: Arriendo Baños Químicos
J21: Fletes y Transporte | P21: Fletes y Transporte
J22: Servicios de Asesoría y Standby | P22: Servicios de Asesoría y Standby
J23: Logística y Viáticos Asesor | P23: Logística y Viáticos Asesor
J24: EPP Asesor Especialista | P24: EPP Asesor Especialista
J25: Logística: Alojamiento MOD/MOI/Staff | P25: Logística: Alojamiento MOD/MOI/Staff
J26: Logística: Alimentación MOD/MOI/Staff | P26: Logística: Alimentación MOD/MOI/Staff
J27: Logística: Pasajes y Traslados | P27: Logística: Pasajes y Traslados
J28: Costo Operativo Equipos (Combustible, etc.) | P28: Costo Operativo Equipos (Combustible, etc.)
J29: EPP y Ropa de Trabajo Personal (Directo e Ind.) | P29: EPP y Ropa de Trabajo Personal (Directo e Ind.)
J30: Certificaciones Externas | P30: Certificaciones Externas
P31: Provisión Imprevistos (15 días)

Sheet Carpeta de Arranque_STN
B2: Empresa: Sistema de Transmisión del Norte S.A. (STN) | F2: RUT: 76.41.374-2 | G2: Dotación: 68 personas | T2: FECHA ULTIMA ACTUALIZACIÓN | U2: 45957
B3: Descripción del Servicio: Servicios de Mantenimiento Eléctrica para Equipos Primarios, Líneas de Transmisión, Distribución, Salas Eléctricas, SSEE Móviles y Maniobras Sistema Eléctrico de Potencia. | F3: N° Contrato: 9100077508
B4: Empresa colaboradora | D4: Nombre | E4: Cargo | F4: Fecha | G4: Firma
D5: Juan Carlos Gonzalez | E5: Administrador Contrato | F5: 15 de Septiembre 2025
D6: Alejandro Morgado | E6: Asesor Prevención de Riesgos | F6: 15 de Septiembre 2025
B7: II. Revisión de Antecedentes:
B8: Minera Escondida | D8: Nombre | E8: Cargo | F8: Fecha | G8: Firma
D9: Camilo Garay | E9: Contract Owner | F9: 15 de Septiembre 2025
D10: Felindo Concha | E10: Operador de Contrato | F10: 16 de Septiembre 2025
B11: III. Lista de documentos a presentar antes del inicio del contrato | G11: Control de Documentos | K11: =TODAY() -> 46195 | N11: Fecha Limite para el 100%
B12: En Antofagasta (Control Acceso) - ANTES de ingreso a faena | G12: SI | H12: NO | I12: N/A | J12: Observación. | K12: Planificado | L12: Real | M12: Variación | O12: Comentarios(Fecha) | P12: Comentarios(Fecha) | Q12: Justificación | R12: Fecha Compromiso
B13: 1 | C13: Autorización jornada especial Inspección del Trabajo (adherencia a "Jornadas Marco" de Escondida-BHP). | H13: X | J13: RRLL | K13: =IF(N13="","",MIN(1,MAX(0,(TODAY()-DATE(2026,5,1))/(N13-DATE(2026,5,1))))) -> 1 | L13: 1 | M13: =+L13-K13 -> 0 | N13: 46188
B14: 2 | C14: Carta aprobación del personal que está autorizado por Escondida-BHP para firma de "Permiso de trabajo". | G14: X | J14: RRLL | K14: =IF(N14="","",MIN(1,MAX(0,(TODAY()-DATE(2026,5,1))/(N14-DATE(2026,5,1))))) -> 1 | L14: 0 | M14: =+L14-K14 -> -1 | N14: 46188
B15: 3 | C15: Carta de constitución el comité paritario (> 25 Personas) y copia del acta de reuniones del comité (tres últimos meses). | G15: X | J15: PREV. RIESGOS | K15: =IF(N15="","",MIN(1,MAX(0,(TODAY()-DATE(2026,5,1))/(N15-DATE(2026,5,1))))) -> 1 | L15: 1 | M15: =+L15-K15 -> 0 | N15: 46188
B16: 4 | C16: Acta de constitución del "Comité bipartito" de capacitación (>14 personas). | G16: X | J16: RRLL | K16: =IF(N16="","",MIN(1,MAX(0,(TODAY()-DATE(2026,5,1))/(N16-DATE(2026,5,1))))) -> 1 | L16: 0 | M16: =+L16-K16 -> -1 | N16: 46188
B17: 5 | C17: Carta "Inicio de actividades Sernageomin". | G17: X | J17: PREV. RIESGOS - RRLL | K17: =IF(N17="","",MIN(1,MAX(0,(TODAY()-DATE(2026,5,1))/(N17-DATE(2026,5,1))))) -> 1 | M17: =+L17-K17 -> -1 | N17: 46188
B18: 6 | C18: Certificación de los "Equipos de protección personal" de acuerdo al ISP y adjuntar listado. | G18: X | J18: PREV. RIESGOS | K18: =IF(N18="","",MIN(1,MAX(0,(TODAY()-DATE(2026,5,1))/(N18-DATE(2026,5,1))))) -> 1 | M18: =+L18-K18 -> -1 | N18: 46188
B19: 7 | C19: Certificación de los equipos móviles de levante y accesorios de levante que utilizaran, adjuntar listado de equipos. | G19: X | J19: RRLL - OPERATIVO | K19: =IF(N19="","",MIN(1,MAX(0,(TODAY()-DATE(2026,5,1))/(N19-DATE(2026,5,1))))) -> 1 | M19: =+L19-K19 -> -1 | N19: 46188
B20: 8 | C20: Certificación de vehículos equipos móviles, adjuntar listado. | G20: X | J20: OPERATIVO | K20: =IF(N20="","",MIN(1,MAX(0,(TODAY()-DATE(2026,5,1))/(N20-DATE(2026,5,1))))) -> 1 | M20: =+L20-K20 -> -1 | N20: 46188
B21: 9 | C21: Certificado de afiliación a un organismo administrador de la Ley 16744. | G21: X | J21: PREV. RIESGOS | K21: =IF(N21="","",MIN(1,MAX(0,(TODAY()-DATE(2026,5,1))/(N21-DATE(2026,5,1))))) -> 1 | M21: =+L21-K21 -> -1 | N21: 46188
B22: 10 | C22: Contrato con "Gerencia Escondida-BHP" (contrato comercial). | G22: X | J22: GERENCIAL | K22: =IF(N22="","",MIN(1,MAX(0,(TODAY()-DATE(2026,5,1))/(N22-DATE(2026,5,1))))) -> 1 | M22: =+L22-K22 -> -1 | N22: 46188
B23: 11 | C23: Copia de "Reglamento interno de orden, higiene y seguridad" de la empresa contratista. | G23: X | J23: PREV. RIESGOS | K23: =IF(N23="","",MIN(1,MAX(0,(TODAY()-DATE(2026,5,1))/(N23-DATE(2026,5,1))))) -> 1 | M23: =+L23-K23 -> -1 | N23: 46188
B24: 12 | C24: Registro de recepción de "Reglamento interno" por parte de los trabajadores. | G24: X | J24: RRLL | K24: =IF(N24="","",MIN(1,MAX(0,(TODAY()-DATE(2026,5,1))/(N24-DATE(2026,5,1))))) -> 1 | M24: =+L24-K24 -> -1 | N24: 46188
B25: 13 | C25: Croquis de instalación de faena identificando áreas, PEE, puntos de almacenamiento temporal de residuos y puntos de almacenamiento de sustancias peligrosas. | G25: X | J25: PREV. RIESGOS | K25: =IF(N25="","",MIN(1,MAX(0,(TODAY()-DATE(2026,5,1))/(N25-DATE(2026,5,1))))) -> 1 | M25: =+L25-K25 -> -1 | N25: 46188
B26: 14 | C26: Curricular y acreditación de o los profesional(es) en "Prevención de Riesgos" DS-95. Ley 16.744- Decreto 132 Seguridad Minera. (Según categoría de acuerdo al reglamento de empresas colaboradoras)/ Estos deben ser aprobados por el Dpto. de Seguridad de Minera Escondida-BHP. | G26: X | J26: PREV. RIESGOS | K26: =IF(N26="","",MIN(1,MAX(0,(TODAY()-DATE(2026,5,1))/(N26-DATE(2026,5,1))))) -> 1 | M26: =+L26-K26 -> -1 | N26: 46188
B27: 15 | C27: Designación de monitores de seguridad (empresas <25 trabajadores). | I27: X | J27: PREV. RIESGOS | K27: =IF(N27="","",MIN(1,MAX(0,(TODAY()-DATE(2026,5,1))/(N27-DATE(2026,5,1))))) -> 1 | M27: =+L27-K27 -> -1 | N27: 46188
B28: 16 | C28: Hoja Ruta de cada trabajador (Ver Hoja de Ruta para Trabajadores), adjuntar respaldos. | G28: X | J28: RRLL - PREV RIESGOS | K28: =IF(N28="","",MIN(1,MAX(0,(TODAY()-DATE(2026,5,1))/(N28-DATE(2026,5,1))))) -> 1 | M28: =+L28-K28 -> -1 | N28: 46188
B29: 17 | C29: "Inventario de Riesgos Salud, Seguridad y Medio Ambiente" de acuerdo a formato Escondida-BHP. | G29: X | J29: PREV. RIESGOS | K29: =IF(N29="","",MIN(1,MAX(0,(TODAY()-DATE(2026,5,1))/(N29-DATE(2026,5,1))))) -> 1 | M29: =+L29-K29 -> -1 | N29: 46188
B30: 18 | C30: Listado conductor, recepción reglamento transportes. | G30: X | J30: RRLL | K30: =IF(N30="","",MIN(1,MAX(0,(TODAY()-DATE(2026,5,1))/(N30-DATE(2026,5,1))))) -> 1 | M30: =+L30-K30 -> -1 | N30: 46188
B31: 19 | C31: Listado de vehículo, con sus marcas, capacidad de carga, modelo, año y placa patente. | G31: X | J31: OPERATIVO | K31: =IF(N31="","",MIN(1,MAX(0,(TODAY()-DATE(2026,5,1))/(N31-DATE(2026,5,1))))) -> 1 | M31: =+L31-K31 -> -1 | N31: 46188
B32: 20 | C32: Matriz de Evaluación Cualitativa de exposición (Salud). | G32: X | J32: PREV. RIESGOS | K32: =IF(N32="","",MIN(1,MAX(0,(TODAY()-DATE(2026,5,1))/(N32-DATE(2026,5,1))))) -> 1 | M32: =+L32-K32 -> -1 | N32: 46188
B33: 21 | C33: Medio de Transporte del personal (Antofagasta - campamento y campamento - Mina). | G33: X | J33: PREV. RIESGOS | K33: =IF(N33="","",MIN(1,MAX(0,(TODAY()-DATE(2026,5,1))/(N33-DATE(2026,5,1))))) -> 1 | M33: =+L33-K33 -> -1 | N33: 46188
B34: 22 | C34: Organigrama de la Empresa y listado de la dotación de la empresa. | G34: X | J34: RRLL - OPERATIVO | K34: =IF(N34="", "", IF($K$11>=N34, 1, 0)) -> 1 | M34: =+L34-K34 -> -1 | N34: 46188
B35: 23 | C35: Organigrama del Departamento de Prevención de Riesgos. (si la empresa es de >100 trabajadores)/ Los cuales deben depender de la Gerencia General de acuerdo al DS 132. | I35: X | J35: PREV RIESGOS | K35: =IF(N35="", "", IF($K$11>=N35, 1, 0)) -> 1 | M35: =+L35-K35 -> -1 | N35: 46188
B36: 24 | C36: Permisos ambientales y de salud requeridos para ejercer los servicios contratados (según aplicación). | I36: X | J36: PREV. RIESGOS | K36: =IF(N36="", "", IF($K$11>=N36, 1, 0)) -> 1 | M36: =+L36-K36 -> -1 | N36: 46188
B37: 25 | C37: Plan de cierre de faena (abandono de instalación faena). | G37: X | J37: PREV. RIESGOS | K37: =IF(N37="", "", IF($K$11>=N37, 1, 0)) -> 1 | M37: =+L37-K37 -> -1 | N37: 46188
B38: 26 | C38: Plan de regularización de puntos de almacenamiento temporal de residuos y de puntos de almacenamiento de sustancias peligrosas. | G38: X | J38: PREV. RIESGOS | K38: =IF(N38="", "", IF($K$11>=N38, 1, 0)) -> 1 | M38: =+L38-K38 -> -1 | N38: 46188
B39: 27 | C39: Política HSEC y Política de Alcohol y Drogas, adjuntar Programa de envío del personal a Policlínico. | G39: X | J39: PREV. RIESGOS | K39: =IF(N39="", "", IF($K$11>=N39, 1, 0)) -> 1 | M39: =+L39-K39 -> -1 | N39: 46188
B40: 28 | C40: Procedimiento de preparación y respuesta ante situaciones de emergencia (con nombre y teléfonos claves de la empresa). | G40: X | J40: PREV. RIESGOS | K40: =IF(N40="", "", IF($K$11>=N40, 1, 0)) -> 1 | M40: =+L40-K40 -> -1 | N40: 46188
B41: 29 | C41: Procedimientos de "Trabajo Seguro" con firmas correspondiente (elaboración, revisión y aprobación), adjuntar listado de los procedimientos. | G41: X | J41: OPERATIVO - PREV. RIESGOS | K41: =IF(N41="", "", IF($K$11>=N41, 1, 0)) -> 1 | M41: =+L41-K41 -> -1 | N41: 46188
B42: 30 | C42: Programa de capacitación (HSE) de acuerdo a niveles de riesgo evaluado en los inventarios. | G42: X | J42: PREV. RIESGOS | K42: =IF(N42="", "", IF($K$11>=N42, 1, 0)) -> 1 | M42: =+L42-K42 -> -1 | N42: 46188
B43: 31 | C43: "Programa de Gestión en Salud, Seguridad y Medio Ambiente" alineado con el programa de Escondida-BHP (basado en el Check list que indica el "Reglamento de Empresas colaboradoras y Subcontratistas") revisado y timbrado por HSE Escondida-BHP. | G43: X | J43: PREV. RIESGOS | K43: =IF(N43="", "", IF($K$11>=N43, 1, 0)) -> 1 | M43: =+L43-K43 -> -1 | N43: 46188
B44: 32 | C44: Programa mantención; vehículos, equipos de apoyo, levante, eléctricos portátiles. | G44: X | J44: OPERATIVO | K44: =IF(N44="", "", IF($K$11>=N44, 1, 0)) -> 1 | M44: =+L44-K44 -> -1 | N44: 46188
B45: 33 | C45: Certificación soldador, Rigger, Mufas, operadores, etc | G45: X | J45: RRLL | K45: =IF(N45="", "", IF($K$11>=N45, 1, 0)) -> 1 | M45: =+L45-K45 -> -1 | N45: 46188
B46: 34 | C46: Boleta de garantía (sólo si está estipulado en el contrato). | G46: X | J46: GERENCIAL | K46: =IF(N46="", "", IF($K$11>=N46, 1, 0)) -> 1 | M46: =+L46-K46 -> -1 | N46: 46188
B47: 35 | C47: Historial de los accidentes del trabajo y enfermedades profesionales "Certificado Organismo Administrador" últimos 3 Periodos (ley 16.744). | G47: X | J47: PREV. RIESGOS | K47: =IF(N47="", "", IF($K$11>=N47, 1, 0)) -> 1 | M47: =+L47-K47 -> -1 | N47: 46188
J48: AVANCE | K48: =AVERAGE(K13:K47) -> 1 | L48: =AVERAGE(L13:L47) -> 0.5 | M48: =AVERAGE(M13:M47) -> -0.94285714

Sheet Detalle Compromisos
A1: Activity ID | B1: Código EDT/WBS | C1: Actividad | D1: Responsable | E1: Prioridad | F1: Estado | G1: Fecha de Compromiso | H1: % Avance Real | I1: Fecha de Inicio de Actividad | J1: Fecha Limite Cierre Actividad | K1: Duración de actividad en días | L1: % Avance Esperado | M1: % Desviación | N1: Mitigación / Acción ante Riesgo
A2: ACT-001 | B2: 1.2 Obras Civiles y Montaje | C2: Traslado de conductor eléctrico desde SSEE Buín a Antofagasta | D2: Jose Contuliano | E2: =IF(J2="", "", IF(J2<=TODAY()+7, "Alta", IF(J2<=TODAY()+14, "Media", "Baja"))) -> Alta | F2: Backlog / Por Iniciar | G2: 46188 | H2: =IF(F2="Aprobado / Terminado", 1, IF(F2="En Revisión / MEL", 0.9, IF(F2="En Proceso", 0.5, 0))) -> 0 | I2: 46183 | J2: 46193 | K2: =IF(OR(I2="", J2=""), 0, NETWORKDAYS(I2, J2)) -> 8 | L2: =IF(OR(I2="", J2=""), 0, IF(TODAY()>=J2, 1, IF(TODAY()<=I2, 0, NETWORKDAYS(I2, TODAY()) / NETWORKDAYS(I2, J2)))) -> 1 | M2: =IF(OR(H2="", L2=""), "", H2 - L2) -> -1 | N2: Gestionar como gasto reembolsable con cliente
A3: ACT-002 | B3: 2.1 HSEC & Acreditación | C3: Cursos Mutual | D3: Juan Carlos Santander | E3: =IF(J3="", "", IF(J3<=TODAY()+7, "Alta", IF(J3<=TODAY()+14, "Media", "Baja"))) -> Alta | F3: En Proceso | G3: 46178 | H3: =IF(F3="Aprobado / Terminado", 1, IF(F3="En Revisión / MEL", 0.9, IF(F3="En Proceso", 0.5, 0))) -> 0.5 | I3: 46167 | J3: 46178 | K3: =IF(OR(I3="", J3=""), 0, NETWORKDAYS(I3, J3)) -> 10 | L3: =IF(OR(I3="", J3=""), 0, IF(TODAY()>=J3, 1, IF(TODAY()<=I3, 0, NETWORKDAYS(I3, TODAY()) / NETWORKDAYS(I3, J3)))) -> 1 | M3: =IF(OR(H3="", L3=""), "", H3 - L3) -> -0.5 | N3: Monitoreo en bloque desde hotel (10:00 a 20:00 hrs)
C4: Cursos MEL (5h) | D4: Juan Carlos Santander | E4: =IF(J4="", "", IF(J4<=TODAY()+7, "Alta", IF(J4<=TODAY()+14, "Media", "Baja"))) | F4: En Proceso | H4: =IF(F4="Aprobado / Terminado", 1, IF(F4="En Revisión / MEL", 0.9, IF(F4="En Proceso", 0.5, 0))) -> 0.5 | K4: =IF(OR(I4="", J4=""), 0, NETWORKDAYS(I4, J4)) -> 0 | L4: =IF(OR(I4="", J4=""), 0, IF(TODAY()>=J4, 1, IF(TODAY()<=I4, 0, NETWORKDAYS(I4, TODAY()) / NETWORKDAYS(I4, J4)))) -> 0 | M4: =IF(OR(H4="", L4=""), "", H4 - L4) -> 0.5
C5: Cursos LMS | D5: Juan Carlos Santander | E5: =IF(J5="", "", IF(J5<=TODAY()+7, "Alta", IF(J5<=TODAY()+14, "Media", "Baja"))) | F5: En Proceso | H5: =IF(F5="Aprobado / Terminado", 1, IF(F5="En Revisión / MEL", 0.9, IF(F5="En Proceso", 0.5, 0))) -> 0.5 | K5: =IF(OR(I5="", J5=""), 0, NETWORKDAYS(I5, J5)) -> 0 | L5: =IF(OR(I5="", J5=""), 0, IF(TODAY()>=J5, 1, IF(TODAY()<=I5, 0, NETWORKDAYS(I5, TODAY()) / NETWORKDAYS(I5, J5)))) -> 0 | M5: =IF(OR(H5="", L5=""), "", H5 - L5) -> 0.5
C6: Inscripción Cursos PMF | D6: Jesenia Ramirez | E6: =IF(J6="", "", IF(J6<=TODAY()+7, "Alta", IF(J6<=TODAY()+14, "Media", "Baja"))) | F6: En Proceso | H6: =IF(F6="Aprobado / Terminado", 1, IF(F6="En Revisión / MEL", 0.9, IF(F6="En Proceso", 0.5, 0))) -> 0.5 | K6: =IF(OR(I6="", J6=""), 0, NETWORKDAYS(I6, J6)) -> 0 | L6: =IF(OR(I6="", J6=""), 0, IF(TODAY()>=J6, 1, IF(TODAY()<=I6, 0, NETWORKDAYS(I6, TODAY()) / NETWORKDAYS(I6, J6)))) -> 0 | M6: =IF(OR(H6="", L6=""), "", H6 - L6) -> 0.5
A7: ACT-003 | B7: 2.1 HSEC & Acreditación | C7: Cotizacion Coaching psicológico 3D (10-12 personas) | D7: Jesenia Ramirez | E7: =IF(J7="", "", IF(J7<=TODAY()+7, "Alta", IF(J7<=TODAY()+14, "Media", "Baja"))) | F7: Backlog / Por Iniciar | G7: 29/05/2026 | H7: =IF(F7="Aprobado / Terminado", 1, IF(F7="En Revisión / MEL", 0.9, IF(F7="En Proceso", 0.5, 0))) -> 0 | K7: =IF(OR(I7="", J7=""), 0, NETWORKDAYS(I7, J7)) -> 0 | L7: =IF(OR(I7="", J7=""), 0, IF(TODAY()>=J7, 1, IF(TODAY()<=I7, 0, NETWORKDAYS(I7, TODAY()) / NETWORKDAYS(I7, J7)))) -> 0 | M7: =IF(OR(H7="", L7=""), "", H7 - L7) -> 0 | N7: Cotizar opción presencial en Antofagasta (2,5 UF/pax)
A8: ACT-004 | B8: 2.2 HSEC & Acreditación | C8: Obtener validación de MEL (Osman/Marco) para CV Supervisor | D8: Jose Contuliano | E8: =IF(J8="", "", IF(J8<=TODAY()+7, "Alta", IF(J8<=TODAY()+14, "Media", "Baja"))) | F8: Aprobado / Terminado | G8: 27/05/2026 | H8: =IF(F8="Aprobado / Terminado", 1, IF(F8="En Revisión / MEL", 0.9, IF(F8="En Proceso", 0.5, 0))) -> 1 | K8: =IF(OR(I8="", J8=""), 0, NETWORKDAYS(I8, J8)) -> 0 | L8: =IF(OR(I8="", J8=""), 0, IF(TODAY()>=J8, 1, IF(TODAY()<=I8, 0, NETWORKDAYS(I8, TODAY()) / NETWORKDAYS(I8, J8)))) -> 0 | M8: =IF(OR(H8="", L8=""), "", H8 - L8) -> 1 | N8: Posicionar a Leonel Sánchez como respaldo técnico en terreno
A9: ACT-005 | B9: 3.1 Gestión de Flota | C9: Retirar 3 camionetas estándar MEL desde Tattersal Antofagasta | D9: Franklin Godoy | E9: =IF(J9="", "", IF(J9<=TODAY()+7, "Alta", IF(J9<=TODAY()+14, "Media", "Baja"))) | F9: Backlog / Por Iniciar | G9: 28/05/2026 | H9: =IF(F9="Aprobado / Terminado", 1, IF(F9="En Revisión / MEL", 0.9, IF(F9="En Proceso", 0.5, 0))) -> 0 | K9: =IF(OR(I9="", J9=""), 0, NETWORKDAYS(I9, J9)) -> 0 | L9: =IF(OR(I9="", J9=""), 0, IF(TODAY()>=J9, 1, IF(TODAY()<=I9, 0, NETWORKDAYS(I9, TODAY()) / NETWORKDAYS(I9, J9)))) -> 0 | M9: =IF(OR(H9="", L9=""), "", H9 - L9) -> 0 | N9: Validar emisión de certificados de torque
A10: ACT-006 | B10: 3.1 Gestión de Flota | C10: Emitir OC vía CAPEX para 4 radios APX 1.500 | D10: Claudio Cajas | E10: =IF(J10="", "", IF(J10<=TODAY()+7, "Alta", IF(J10<=TODAY()+14, "Media", "Baja"))) | F10: Backlog / Por Iniciar | G10: 05/06/2026 | H10: =IF(F10="Aprobado / Terminado", 1, IF(F10="En Revisión / MEL", 0.9, IF(F10="En Proceso", 0.5, 0))) -> 0 | K10: =IF(OR(I10="", J10=""), 0, NETWORKDAYS(I10, J10)) -> 0 | L10: =IF(OR(I10="", J10=""), 0, IF(TODAY()>=J10, 1, IF(TODAY()<=I10, 0, NETWORKDAYS(I10, TODAY()) / NETWORKDAYS(I10, J10)))) -> 0 | M10: =IF(OR(H10="", L10=""), "", H10 - L10) -> 0 | N10: Escalar firma a Javier para acelerar entrega
A11: ACT-007 | B11: 3.2 Equipamiento Mayor | C11: Regularizar certificado Hombre Muerto PESCO para Camión Grúa | D11: Franklin Godoy | E11: =IF(J11="", "", IF(J11<=TODAY()+7, "Alta", IF(J11<=TODAY()+14, "Media", "Baja"))) | F11: Backlog / Por Iniciar | G11: 28/05/2026 | H11: =IF(F11="Aprobado / Terminado", 1, IF(F11="En Revisión / MEL", 0.9, IF(F11="En Proceso", 0.5, 0))) -> 0 | K11: =IF(OR(I11="", J11=""), 0, NETWORKDAYS(I11, J11)) -> 0 | L11: =IF(OR(I11="", J11=""), 0, IF(TODAY()>=J11, 1, IF(TODAY()<=I11, 0, NETWORKDAYS(I11, TODAY()) / NETWORKDAYS(I11, J11)))) -> 0 | M11: =IF(OR(H11="", L11=""), "", H11 - L11) -> 0 | N11: Gestión urgente para obtención de sello QR SEIM
A12: ACT-008 | B12: 4.1 Logística de Instalaciones | C12: Confirmar condición de entrega en sitio de Container arrendado | D12: Franklin Godoy | E12: =IF(J12="", "", IF(J12<=TODAY()+7, "Alta", IF(J12<=TODAY()+14, "Media", "Baja"))) | F12: Backlog / Por Iniciar | G12: 28/05/2026 | H12: =IF(F12="Aprobado / Terminado", 1, IF(F12="En Revisión / MEL", 0.9, IF(F12="En Proceso", 0.5, 0))) -> 0 | K12: =IF(OR(I12="", J12=""), 0, NETWORKDAYS(I12, J12)) -> 0 | L12: =IF(OR(I12="", J12=""), 0, IF(TODAY()>=J12, 1, IF(TODAY()<=I12, 0, NETWORKDAYS(I12, TODAY()) / NETWORKDAYS(I12, J12)))) -> 0 | M12: =IF(OR(H12="", L12=""), "", H12 - L12) -> 0 | N12: Arrendar cama baja en Antofagasta si no incluye flete a terreno
A13: ACT-009 | B13: 4.2 Procura Menor | C13: Comprar ropa de invierno requerida para test 3D | D13: Juan Carlos Santander | E13: =IF(J13="", "", IF(J13<=TODAY()+7, "Alta", IF(J13<=TODAY()+14, "Media", "Baja"))) | F13: Backlog / Por Iniciar | G13: 29/05/2026 | H13: =IF(F13="Aprobado / Terminado", 1, IF(F13="En Revisión / MEL", 0.9, IF(F13="En Proceso", 0.5, 0))) -> 0 | K13: =IF(OR(I13="", J13=""), 0, NETWORKDAYS(I13, J13)) -> 0 | L13: =IF(OR(I13="", J13=""), 0, IF(TODAY()>=J13, 1, IF(TODAY()<=I13, 0, NETWORKDAYS(I13, TODAY()) / NETWORKDAYS(I13, J13)))) -> 0 | M13: =IF(OR(H13="", L13=""), "", H13 - L13) -> 0 | N13: Activar proveedor spot local ante quiebre de stock
C14: Guía de Maniobras. | D14: Alex Vergara | F14: En Proceso | G14: 46533 | H14: =IF(F14="Aprobado / Terminado", 1, IF(F14="En Revisión / MEL", 0.9, IF(F14="En Proceso", 0.5, 0))) -> 0.5 | I14: 46160 | J14: 46177 | K14: =IF(OR(I14="", J14=""), 0, NETWORKDAYS(I14, J14)) -> 14 | L14: =IF(OR(I14="", J14=""), 0, IF(TODAY()>=J14, 1, IF(TODAY()<=I14, 0, NETWORKDAYS(I14, TODAY()) / NETWORKDAYS(I14, J14)))) -> 1 | M14: =IF(OR(H14="", L14=""), "", H14 - L14) -> -0.5
C15: Formulario de Aislación y Bloqueo. | D15: Alex Vergara | F15: En Proceso | G15: 46533 | H15: =IF(F15="Aprobado / Terminado", 1, IF(F15="En Revisión / MEL", 0.9, IF(F15="En Proceso", 0.5, 0))) -> 0.5 | I15: 46160 | J15: 46177 | K15: =IF(OR(I15="", J15=""), 0, NETWORKDAYS(I15, J15)) -> 14 | L15: =IF(OR(I15="", J15=""), 0, IF(TODAY()>=J15, 1, IF(TODAY()<=I15, 0, NETWORKDAYS(I15, TODAY()) / NETWORKDAYS(I15, J15)))) -> 1 | M15: =IF(OR(H15="", L15=""), "", H15 - L15) -> -0.5
C16: SODI, apoyado con el DU que te adjunté previamente. | D16: Alex Vergara | F16: En Proceso | G16: 46533 | H16: =IF(F16="Aprobado / Terminado", 1, IF(F16="En Revisión / MEL", 0.9, IF(F16="En Proceso", 0.5, 0))) -> 0.5 | I16: 46160 | J16: 46177 | K16: =IF(OR(I16="", J16=""), 0, NETWORKDAYS(I16, J16)) -> 14 | L16: =IF(OR(I16="", J16=""), 0, IF(TODAY()>=J16, 1, IF(TODAY()<=I16, 0, NETWORKDAYS(I16, TODAY()) / NETWORKDAYS(I16, J16)))) -> 1 | M16: =IF(OR(H16="", L16=""), "", H16 - L16) -> -0.5
C17: Plan de Trabajo. | D17: Alex Vergara | F17: En Proceso | G17: 46533 | H17: =IF(F17="Aprobado / Terminado", 1, IF(F17="En Revisión / MEL", 0.9, IF(F17="En Proceso", 0.5, 0))) -> 0.5 | I17: 46160 | J17: 46177 | K17: =IF(OR(I17="", J17=""), 0, NETWORKDAYS(I17, J17)) -> 14 | L17: =IF(OR(I17="", J17=""), 0, IF(TODAY()>=J17, 1, IF(TODAY()<=I17, 0, NETWORKDAYS(I17, TODAY()) / NETWORKDAYS(I17, J17)))) -> 1 | M17: =IF(OR(H17="", L17=""), "", H17 - L17) -> -0.5
A18: A1140 | B18: 1.1.5.1 | C18: Hito: Disponibilidad de Conductor y Herrajes en Faena | D18: Ulises Psijas | E18: =IF(J18="", "", IF(J18<=TODAY()+7, "Alta", IF(J18<=TODAY()+14, "Media", "Baja"))) | F18: Backlog / Por Iniciar | H18: =IF(F18="Aprobado / Terminado", 1, IF(F18="En Revisión / MEL", 0.9, IF(F18="En Proceso", 0.5, 0))) -> 0 | K18: =IF(OR(I18="", J18=""), 0, NETWORKDAYS(I18, J18)) -> 0 | L18: =IF(OR(I18="", J18=""), 0, IF(TODAY()>=J18, 1, IF(TODAY()<=I18, 0, NETWORKDAYS(I18, TODAY()) / NETWORKDAYS(I18, J18)))) -> 0 | M18: =IF(OR(H18="", L18=""), "", H18 - L18) -> 0
A19: A1500 | B19: 1.1.5.2 | C19: Examenes - Cartas Oferta - Contratación | D19: Jesenia Ramirez | E19: =IF(J19="", "", IF(J19<=TODAY()+7, "Alta", IF(J19<=TODAY()+14, "Media", "Baja"))) | F19: Backlog / Por Iniciar | H19: =IF(F19="Aprobado / Terminado", 1, IF(F19="En Revisión / MEL", 0.9, IF(F19="En Proceso", 0.5, 0))) -> 0 | K19: =IF(OR(I19="", J19=""), 0, NETWORKDAYS(I19, J19)) -> 0 | L19: =IF(OR(I19="", J19=""), 0, IF(TODAY()>=J19, 1, IF(TODAY()<=I19, 0, NETWORKDAYS(I19, TODAY()) / NETWORKDAYS(I19, J19)))) -> 0 | M19: =IF(OR(H19="", L19=""), "", H19 - L19) -> 0
A20: A1510 | B20: 1.1.5.2 | C20: Tramitación y Carga de Carpetas Acreditación Personal Delloitte | E20: =IF(J20="", "", IF(J20<=TODAY()+7, "Alta", IF(J20<=TODAY()+14, "Media", "Baja"))) | F20: Backlog / Por Iniciar | H20: =IF(F20="Aprobado / Terminado", 1, IF(F20="En Revisión / MEL", 0.9, IF(F20="En Proceso", 0.5, 0))) -> 0 | K20: =IF(OR(I20="", J20=""), 0, NETWORKDAYS(I20, J20)) -> 0 | L20: =IF(OR(I20="", J20=""), 0, IF(TODAY()>=J20, 1, IF(TODAY()<=I20, 0, NETWORKDAYS(I20, TODAY()) / NETWORKDAYS(I20, J20)))) -> 0 | M20: =IF(OR(H20="", L20=""), "", H20 - L20) -> 0
A21: A1520 | B21: 1.1.5.3 | C21: Pases de Vehículos y Maquinarias (MEL) | E21: =IF(J21="", "", IF(J21<=TODAY()+7, "Alta", IF(J21<=TODAY()+14, "Media", "Baja"))) | F21: Backlog / Por Iniciar | H21: =IF(F21="Aprobado / Terminado", 1, IF(F21="En Revisión / MEL", 0.9, IF(F21="En Proceso", 0.5, 0))) -> 0 | K21: =IF(OR(I21="", J21=""), 0, NETWORKDAYS(I21, J21)) -> 0 | L21: =IF(OR(I21="", J21=""), 0, IF(TODAY()>=J21, 1, IF(TODAY()<=I21, 0, NETWORKDAYS(I21, TODAY()) / NETWORKDAYS(I21, J21)))) -> 0 | M21: =IF(OR(H21="", L21=""), "", H21 - L21) -> 0
A22: A1530 | B22: 1.1.5.4 | C22: Certificación 3D CEIM | E22: =IF(J22="", "", IF(J22<=TODAY()+7, "Alta", IF(J22<=TODAY()+14, "Media", "Baja"))) | F22: Backlog / Por Iniciar | H22: =IF(F22="Aprobado / Terminado", 1, IF(F22="En Revisión / MEL", 0.9, IF(F22="En Proceso", 0.5, 0))) -> 0 | K22: =IF(OR(I22="", J22=""), 0, NETWORKDAYS(I22, J22)) -> 0 | L22: =IF(OR(I22="", J22=""), 0, IF(TODAY()>=J22, 1, IF(TODAY()<=I22, 0, NETWORKDAYS(I22, TODAY()) / NETWORKDAYS(I22, J22)))) -> 0 | M22: =IF(OR(H22="", L22=""), "", H22 - L22) -> 0
A23: A1540 | B23: 1.1.5.5 | C23: Aprobación Final de Planes de Izaje Estándar BHP (Pluma) | E23: =IF(J23="", "", IF(J23<=TODAY()+7, "Alta", IF(J23<=TODAY()+14, "Media", "Baja"))) | F23: Backlog / Por Iniciar | H23: =IF(F23="Aprobado / Terminado", 1, IF(F23="En Revisión / MEL", 0.9, IF(F23="En Proceso", 0.5, 0))) -> 0 | K23: =IF(OR(I23="", J23=""), 0, NETWORKDAYS(I23, J23)) -> 0 | L23: =IF(OR(I23="", J23=""), 0, IF(TODAY()>=J23, 1, IF(TODAY()<=I23, 0, NETWORKDAYS(I23, TODAY()) / NETWORKDAYS(I23, J23)))) -> 0 | M23: =IF(OR(H23="", L23=""), "", H23 - L23) -> 0
A24: A1600 | B24: 1.1.6 | C24: Capacitación CTC Global (Personal STN en Antofagasta) | E24: =IF(J24="", "", IF(J24<=TODAY()+7, "Alta", IF(J24<=TODAY()+14, "Media", "Baja"))) | F24: Backlog / Por Iniciar | H24: =IF(F24="Aprobado / Terminado", 1, IF(F24="En Revisión / MEL", 0.9, IF(F24="En Proceso", 0.5, 0))) -> 0 | K24: =IF(OR(I24="", J24=""), 0, NETWORKDAYS(I24, J24)) -> 0 | L24: =IF(OR(I24="", J24=""), 0, IF(TODAY()>=J24, 1, IF(TODAY()<=I24, 0, NETWORKDAYS(I24, TODAY()) / NETWORKDAYS(I24, J24)))) -> 0 | M24: =IF(OR(H24="", L24=""), "", H24 - L24) -> 0
A25: A1700 | B25: 1.1.7 | C25: Movilización de Equipos y Container a SSEE Ohiggins | E25: =IF(J25="", "", IF(J25<=TODAY()+7, "Alta", IF(J25<=TODAY()+14, "Media", "Baja"))) | F25: Backlog / Por Iniciar | H25: =IF(F25="Aprobado / Terminado", 1, IF(F25="En Revisión / MEL", 0.9, IF(F25="En Proceso", 0.5, 0))) -> 0 | K25: =IF(OR(I25="", J25=""), 0, NETWORKDAYS(I25, J25)) -> 0 | L25: =IF(OR(I25="", J25=""), 0, IF(TODAY()>=J25, 1, IF(TODAY()<=I25, 0, NETWORKDAYS(I25, TODAY()) / NETWORKDAYS(I25, J25)))) -> 0 | M25: =IF(OR(H25="", L25=""), "", H25 - L25) -> 0
A26: A2000 | B26: 1.2.1 | C26: Hito: Ventana Contractual - Inicio Obras Terreno | E26: =IF(J26="", "", IF(J26<=TODAY()+7, "Alta", IF(J26<=TODAY()+14, "Media", "Baja"))) | F26: Backlog / Por Iniciar | H26: =IF(F26="Aprobado / Terminado", 1, IF(F26="En Revisión / MEL", 0.9, IF(F26="En Proceso", 0.5, 0))) -> 0 | K26: =IF(OR(I26="", J26=""), 0, NETWORKDAYS(I26, J26)) -> 0 | L26: =IF(OR(I26="", J26=""), 0, IF(TODAY()>=J26, 1, IF(TODAY()<=I26, 0, NETWORKDAYS(I26, TODAY()) / NETWORKDAYS(I26, J26)))) -> 0 | M26: =IF(OR(H26="", L26=""), "", H26 - L26) -> 0
A27: A2010 | B27: 1.2.2 | C27: Recepción de Área de Trabajo y Bloqueos Eléctricos BP1 | E27: =IF(J27="", "", IF(J27<=TODAY()+7, "Alta", IF(J27<=TODAY()+14, "Media", "Baja"))) | F27: Backlog / Por Iniciar | H27: =IF(F27="Aprobado / Terminado", 1, IF(F27="En Revisión / MEL", 0.9, IF(F27="En Proceso", 0.5, 0))) -> 0 | K27: =IF(OR(I27="", J27=""), 0, NETWORKDAYS(I27, J27)) -> 0 | L27: =IF(OR(I27="", J27=""), 0, IF(TODAY()>=J27, 1, IF(TODAY()<=I27, 0, NETWORKDAYS(I27, TODAY()) / NETWORKDAYS(I27, J27)))) -> 0 | M27: =IF(OR(H27="", L27=""), "", H27 - L27) -> 0
A28: A2020 | B28: 1.2.3 | C28: Retiro de Conductor Flint Existente y Desarme de Herrajes | E28: =IF(J28="", "", IF(J28<=TODAY()+7, "Alta", IF(J28<=TODAY()+14, "Media", "Baja"))) | F28: Backlog / Por Iniciar | H28: =IF(F28="Aprobado / Terminado", 1, IF(F28="En Revisión / MEL", 0.9, IF(F28="En Proceso", 0.5, 0))) -> 0 | K28: =IF(OR(I28="", J28=""), 0, NETWORKDAYS(I28, J28)) -> 0 | L28: =IF(OR(I28="", J28=""), 0, IF(TODAY()>=J28, 1, IF(TODAY()<=I28, 0, NETWORKDAYS(I28, TODAY()) / NETWORKDAYS(I28, J28)))) -> 0 | M28: =IF(OR(H28="", L28=""), "", H28 - L28) -> 0
A29: A2030 | B29: 1.2.4 | C29: Mitigación: Limpieza y Medición de Espesores Marcos MB2/MB3 | E29: =IF(J29="", "", IF(J29<=TODAY()+7, "Alta", IF(J29<=TODAY()+14, "Media", "Baja"))) | F29: Backlog / Por Iniciar | H29: =IF(F29="Aprobado / Terminado", 1, IF(F29="En Revisión / MEL", 0.9, IF(F29="En Proceso", 0.5, 0))) -> 0 | K29: =IF(OR(I29="", J29=""), 0, NETWORKDAYS(I29, J29)) -> 0 | L29: =IF(OR(I29="", J29=""), 0, IF(TODAY()>=J29, 1, IF(TODAY()<=I29, 0, NETWORKDAYS(I29, TODAY()) / NETWORKDAYS(I29, J29)))) -> 0 | M29: =IF(OR(H29="", L29=""), "", H29 - L29) -> 0
A30: A2040 | B30: 1.2.5 | C30: Preparativos de Tendido y Montaje de Poleas en Pórticos | E30: =IF(J30="", "", IF(J30<=TODAY()+7, "Alta", IF(J30<=TODAY()+14, "Media", "Baja"))) | F30: Backlog / Por Iniciar | H30: =IF(F30="Aprobado / Terminado", 1, IF(F30="En Revisión / MEL", 0.9, IF(F30="En Proceso", 0.5, 0))) -> 0 | K30: =IF(OR(I30="", J30=""), 0, NETWORKDAYS(I30, J30)) -> 0 | L30: =IF(OR(I30="", J30=""), 0, IF(TODAY()>=J30, 1, IF(TODAY()<=I30, 0, NETWORKDAYS(I30, TODAY()) / NETWORKDAYS(I30, J30)))) -> 0 | M30: =IF(OR(H30="", L30=""), "", H30 - L30) -> 0
A31: A2050 | B31: 1.2.6 | C31: Tendido Mecánico y Regulado Conductor ACCC Lisbon (2xF) | E31: =IF(J31="", "", IF(J31<=TODAY()+7, "Alta", IF(J31<=TODAY()+14, "Media", "Baja"))) | F31: Backlog / Por Iniciar | H31: =IF(F31="Aprobado / Terminado", 1, IF(F31="En Revisión / MEL", 0.9, IF(F31="En Proceso", 0.5, 0))) -> 0 | K31: =IF(OR(I31="", J31=""), 0, NETWORKDAYS(I31, J31)) -> 0 | L31: =IF(OR(I31="", J31=""), 0, IF(TODAY()>=J31, 1, IF(TODAY()<=I31, 0, NETWORKDAYS(I31, TODAY()) / NETWORKDAYS(I31, J31)))) -> 0 | M31: =IF(OR(H31="", L31=""), "", H31 - L31) -> 0
... A41: A3020 | B41: 1.3.3 | C41: Cierre Comercial del Contrato y Devolución de Garantías | E41: =IF(J41="", "", IF(J41<=TODAY()+7, "Alta", IF(J41<=TODAY()+14, "Media", "Baja"))) | F41: Backlog / Por Iniciar | H41: =IF(F41="Aprobado / Terminado", 1, IF(F41="En Revisión / MEL", 0.9, IF(F41="En Proceso", 0.5, 0))) -> 0 | K41: =IF(OR(I41="", J41=""), 0, NETWORKDAYS(I41, J41)) -> 0 | L41: =IF(OR(I41="", J41=""), 0, IF(TODAY()>=J41, 1, IF(TODAY()<=I41, 0, NETWORKDAYS(I41, TODAY()) / NETWORKDAYS(I41, J41)))) -> 0 | M41: =IF(OR(H41="", L41=""), "", H41 - L41) -> 0
A42: OH-6020 | C42: Término del Proyecto | E42: =IF(J42="", "", IF(J42<=TODAY()+7, "Alta", IF(J42<=TODAY()+14, "Media", "Baja"))) | F42: Backlog / Por Iniciar | H42: =IF(F42="Aprobado / Terminado", 1, IF(F42="En Revisión / MEL", 0.9, IF(F42="En Proceso", 0.5, 0))) -> 0 | K42: =IF(OR(I42="", J42=""), 0, NETWORKDAYS(I42, J42)) -> 0 | L42: =IF(OR(I42="", J42=""), 0, IF(TODAY()>=J42, 1, IF(TODAY()<=I42, 0, NETWORKDAYS(I42, TODAY()) / NETWORKDAYS(I42, J42)))) -> 0 | M42: =IF(OR(H42="", L42=""), "", H42 - L42) -> 0
E43: =IF(J43="", "", IF(J43<=TODAY()+7, "Alta", IF(J43<=TODAY()+14, "Media", "Baja"))) | H43: =IF(F43="Aprobado / Terminado", 1, IF(F43="En Revisión / MEL", 0.9, IF(F43="En Proceso", 0.5, 0))) -> 0 | K43: =IF(OR(I43="", J43=""), 0, NETWORKDAYS(I43, J43)) -> 0 | L43: =IF(OR(I43="", J43=""), 0, IF(TODAY()>=J43, 1, IF(TODAY()<=I43, 0, NETWORKDAYS(I43, TODAY()) / NETWORKDAYS(I43, J43)))) -> 0 | M43: =IF(OR(H43="", L43=""), "", H43 - L43) -> 0
E44: =IF(J44="", "", IF(J44<=TODAY()+7, "Alta", IF(J44<=TODAY()+14, "Media", "Baja"))) | H44: =IF(F44="Aprobado / Terminado", 1, IF(F44="En Revisión / MEL", 0.9, IF(F44="En Proceso", 0.5, 0))) -> 0 | K44: =IF(OR(I44="", J44=""), 0, NETWORKDAYS(I44, J44)) -> 0 | L44: =IF(OR(I44="", J44=""), 0, IF(TODAY()>=J44, 1, IF(TODAY()<=I44, 0, NETWORKDAYS(I44, TODAY()) / NETWORKDAYS(I44, J44)))) -> 0 | M44: =IF(OR(H44="", L44=""), "", H44 - L44) -> 0
E45: =IF(J45="", "", IF(J45<=TODAY()+7, "Alta", IF(J45<=TODAY()+14, "Media", "Baja"))) | H45: =IF(F45="Aprobado / Terminado", 1, IF(F45="En Revisión / MEL", 0.9, IF(F45="En Proceso", 0.5, 0))) -> 0 | K45: =IF(OR(I45="", J45=""), 0, NETWORKDAYS(I45, J45)) -> 0 | L45: =IF(OR(I45="", J45=""), 0, IF(TODAY()>=J45, 1, IF(TODAY()<=I45, 0, NETWORKDAYS(I45, TODAY()) / NETWORKDAYS(I45, J45)))) -> 0 | M45: =IF(OR(H45="", L45=""), "", H45 - L45) -> 0
E46: =IF(J46="", "", IF(J46<=TODAY()+7, "Alta", IF(J46<=TODAY()+14, "Media", "Baja"))) | H46: =IF(F46="Aprobado / Terminado", 1, IF(F46="En Revisión / MEL", 0.9, IF(F46="En Proceso", 0.5, 0))) -> 0 | K46: =IF(OR(I46="", J46=""), 0, NETWORKDAYS(I46, J46)) -> 0 | L46: =IF(OR(I46="", J46=""), 0, IF(TODAY()>=J46, 1, IF(TODAY()<=I46, 0, NETWORKDAYS(I46, TODAY()) / NETWORKDAYS(I46, J46)))) -> 0 | M46: =IF(OR(H46="", L46=""), "", H46 - L46) -> 0
E47: =IF(J47="", "", IF(J47<=TODAY()+7, "Alta", IF(J47<=TODAY()+14, "Media", "Baja"))) | H47: =IF(F47="Aprobado / Terminado", 1, IF(F47="En Revisión / MEL", 0.9, IF(F47="En Proceso", 0.5, 0))) -> 0 | K47: =IF(OR(I47="", J47=""), 0, NETWORKDAYS(I47, J47)) -> 0 | L47: =IF(OR(I47="", J47=""), 0, IF(TODAY()>=J47, 1, IF(TODAY()<=I47, 0, NETWORKDAYS(I47, TODAY()) / NETWORKDAYS(I47, J47)))) -> 0 | M47: =IF(OR(H47="", L47=""), "", H47 - L47) -> 0
E48: =IF(J48="", "", IF(J48<=TODAY()+7, "Alta", IF(J48<=TODAY()+14, "Media", "Baja"))) | H48: =IF(F48="Aprobado / Terminado", 1, IF(F48="En Revisión / MEL", 0.9, IF(F48="En Proceso", 0.5, 0))) -> 0 | K48: =IF(OR(I48="", J48=""), 0, NETWORKDAYS(I48, J48)) -> 0 | L48: =IF(OR(I48="", J48=""), 0, IF(TODAY()>=J48, 1, IF(TODAY()<=I48, 0, NETWORKDAYS(I48, TODAY()) / NETWORKDAYS(I48, J48)))) -> 0 | M48: =IF(OR(H48="", L48=""), "", H48 - L48) -> 0
E49: =IF(J49="", "", IF(J49<=TODAY()+7, "Alta", IF(J49<=TODAY()+14, "Media", "Baja"))) | H49: =IF(F49="Aprobado / Terminado", 1, IF(F49="En Revisión / MEL", 0.9, IF(F49="En Proceso", 0.5, 0))) -> 0 | K49: =IF(OR(I49="", J49=""), 0, NETWORKDAYS(I49, J49)) -> 0 | L49: =IF(OR(I49="", J49=""), 0, IF(TODAY()>=J49, 1, IF(TODAY()<=I49, 0, NETWORKDAYS(I49, TODAY()) / NETWORKDAYS(I49, J49)))) -> 0 | M49: =IF(OR(H49="", L49=""), "", H49 - L49) -> 0
E50: =IF(J50="", "", IF(J50<=TODAY()+7, "Alta", IF(J50<=TODAY()+14, "Media", "Baja"))) | H50: =IF(F50="Aprobado / Terminado", 1, IF(F50="En Revisión / MEL", 0.9, IF(F50="En Proceso", 0.5, 0))) -> 0 | K50: =IF(OR(I50="", J50=""), 0, NETWORKDAYS(I50, J50)) -> 0 | L50: =IF(OR(I50="", J50=""), 0, IF(TODAY()>=J50, 1, IF(TODAY()<=I50, 0, NETWORKDAYS(I50, TODAY()) / NETWORKDAYS(I50, J50)))) -> 0 | M50: =IF(OR(H50="", L50=""), "", H50 - L50) -> 0
E51: =IF(J51="", "", IF(J51<=TODAY()+7, "Alta", IF(J51<=TODAY()+14, "Media", "Baja"))) | H51: =IF(F51="Aprobado / Terminado", 1, IF(F51="En Revisión / MEL", 0.9, IF(F51="En Proceso", 0.5, 0))) -> 0 | K51: =IF(OR(I51="", J51=""), 0, NETWORKDAYS(I51, J51)) -> 0 | L51: =IF(OR(I51="", J51=""), 0, IF(TODAY()>=J51, 1, IF(TODAY()<=I51, 0, NETWORKDAYS(I51, TODAY()) / NETWORKDAYS(I51, J51)))) -> 0 | M51: =IF(OR(H51="", L51=""), "", H51 - L51) -> 0
E52: =IF(J52="", "", IF(J52<=TODAY()+7, "Alta", IF(J52<=TODAY()+14, "Media", "Baja"))) | H52: =IF(F52="Aprobado / Terminado", 1, IF(F52="En Revisión / MEL", 0.9, IF(F52="En Proceso", 0.5, 0))) -> 0 | K52: =IF(OR(I52="", J52=""), 0, NETWORKDAYS(I52, J52)) -> 0 | L52: =IF(OR(I52="", J52=""), 0, IF(TODAY()>=J52, 1, IF(TODAY()<=I52, 0, NETWORKDAYS(I52, TODAY()) / NETWORKDAYS(I52, J52)))) -> 0 | M52: =IF(OR(H52="", L52=""), "", H52 - L52) -> 0
E53: =IF(J53="", "", IF(J53<=TODAY()+7, "Alta", IF(J53<=TODAY()+14, "Media", "Baja"))) | H53: =IF(F53="Aprobado / Terminado", 1, IF(F53="En Revisión / MEL", 0.9, IF(F53="En Proceso", 0.5, 0))) -> 0 | K53: =IF(OR(I53="", J53=""), 0, NETWORKDAYS(I53, J53)) -> 0 | L53: =IF(OR(I53="", J53=""), 0, IF(TODAY()>=J53, 1, IF(TODAY()<=I53, 0, NETWORKDAYS(I53, TODAY()) / NETWORKDAYS(I53, J53)))) -> 0 | M53: =IF(OR(H53="", L53=""), "", H53 - L53) -> 0
E54: =IF(J54="", "", IF(J54<=TODAY()+7, "Alta", IF(J54<=TODAY()+14, "Media", "Baja"))) | H54: =IF(F54="Aprobado / Terminado", 1, IF(F54="En Revisión / MEL", 0.9, IF(F54="En Proceso", 0.5, 0))) -> 0 | K54: =IF(OR(I54="", J54=""), 0, NETWORKDAYS(I54, J54)) -> 0 | L54: =IF(OR(I54="", J54=""), 0, IF(TODAY()>=J54, 1, IF(TODAY()<=I54, 0, NETWORKDAYS(I54, TODAY()) / NETWORKDAYS(I54, J54)))) -> 0 | M54: =IF(OR(H54="", L54=""), "", H54 - L54) -> 0
... E124: =IF(J124="", "", IF(J124<=TODAY()+7, "Alta", IF(J124<=TODAY()+14, "Media", "Baja"))) | H124: =IF(F124="Aprobado / Terminado", 1, IF(F124="En Revisión / MEL", 0.9, IF(F124="En Proceso", 0.5, 0))) -> 0 | K124: =IF(OR(I124="", J124=""), 0, NETWORKDAYS(I124, J124)) -> 0 | L124: =IF(OR(I124="", J124=""), 0, IF(TODAY()>=J124, 1, IF(TODAY()<=I124, 0, NETWORKDAYS(I124, TODAY()) / NETWORKDAYS(I124, J124)))) -> 0 | M124: =IF(OR(H124="", L124=""), "", H124 - L124) -> 0

Sheet PlanificaciónBase
A2: Proyecto 4518893428- Aumento Capacidad BP1 SE OHiggins-CMDIC
A3: TABLA DE ACTIVIDADES - FASE DE INICIO
A4: Fecha Revisión : 22 Mayo 2026
A6: Activity ID | B6: Código EDT/WBS | C6: Activity Name | D6: Original Duration | E6: Remaining Duration | F6: Start | G6: Finish | H6: Total Float | I6: Performance % Complete | J6: Predecessors | K6: Peso
A7: A1000 | B7: 1.1.1 | C7: Hito: Adjudicación de Servicio y Firma Contrato | D7: 0 | E7: 0 | F7: 45950 | G7: 45950 | H7: 0 | I7: 1 | J7: --
A8: A1010 | B8: 1.1.2 | C8: Hito: Kick-Off Meeting (KOM) Oficial con MEL | D8: 0 | E8: 0 | F8: 46030 | G8: 46030 | H8: 0 | I8: 1 | J8: A1000
A9: A1100 | B9: 1.1.3 | C9: Ingeniería de Detalle Aprobada para Construcción (AptC) | D9: 72 | E9: 0 | F9: 45951 | G9: 46053 | H9: 120 | I9: 1 | J9: A1010 | K9: 0.02
A10: A1120 | B10: 1.1.4 | C10: Validación Estructural y Mecánica de Marcos Existentes | D10: 15 | E10: 0 | F10: 46054 | G10: 46068 | H10: 120 | I10: 1 | J10: A1100 | K10: 0.02
A11: A1130 | B11: 1.1.5 | C11: Monitoreo Arribo Suministro Conductor HTLS (RTHO) | D11: 250 | E11: 37 | F11: 45950 | G11: 46170 | H11: 0 | I11: 1 | J11: A1000 | K11: 0.05
A12: A1140 | B12: 1.1.5.1 | C12: Hito: Disponibilidad de Conductor y Herrajes en Faena | D12: 0 | E12: 0 | F12: 46202 | G12: 46202 | H12: 0 | I12: 0 | J12: A1130
A13: A1500 | B13: 1.1.5.2 | C13: Examenes - Cartas Oferta - Contratación | D13: 45 | E13: 8 | F13: 46167 | G13: 46178 | H13: 10 | I13: 0.15 | J13: A1120 | K13: 0.04
A14: A1510 | B14: 1.1.5.2 | C14: Tramitación y Carga de Carpetas Acreditación Personal Deloitte | D14: 45 | E14: 8 | F14: 46181 | G14: 46197 | H14: 10 | I14: 0.1 | J14: A1120 | K14: 0.03
A15: A1520 | B15: 1.1.5.3 | C15: Pases de Vehículos y Maquinarias (MEL) | D15: 30 | E15: 9 | F15: 46174 | G15: 46188 | H15: 10 | I15: 0.65 | J15: A1500 | K15: 0.02
A16: A1530 | B16: 1.1.5.4 | C16: Certificación 3D CEIM | D16: 20 | E16: 20 | F16: 46174 | G16: 46196 | H16: 10 | I16: 0.1
A17: A1540 | B17: 1.1.5.5 | C17: Aprobación Final de Planes de Izaje Estándar BHP (Pluma) | D17: 15 | E17: 15 | F17: 46174 | G17: 46188 | H17: 10 | I17: 0 | J17: A1520 | K17: 0.03
A18: A1600 | B18: 1.1.6 | C18: Capacitación CTC Global (Personal STN en Antofagasta) | D18: 4 | E18: 4 | F18: 46203 | G18: 46206 | H18: 0 | I18: 0 | J18: A1140 | K18: 0.06
A19: A1700 | B19: 1.1.7 | C19: Movilización de Equipos y Container a SSEE Ohiggins | D19: 5 | E19: 5 | F19: 46181 | G19: 46197 | H19: 0 | I19: 0 | J19: A1140, A1540 | K19: 0.06
A20: A2000 | B20: 1.2.1 | C20: Hito: Ventana Contractual - Inicio Obras Terreno | D20: 0 | E20: 0 | F20: 46209 | G20: 46209 | H20: 0 | I20: 0 | J20: A1600
A21: A2010 | B21: 1.2.2 | C21: Recepción de Área de Trabajo y Bloqueos Eléctricos BP1 | D21: 1 | E21: 1 | F21: 46209 | G21: 46209 | H21: 0 | I21: 0 | J21: A2000, A1700 | K21: 0.03
A22: A2020 | B22: 1.2.3 | C22: Retiro de Conductor Flint Existente y Desarme de Herrajes | D22: 3 | E22: 3 | F22: 46210 | G22: 46212 | H22: 0 | I22: 0 | J22: A2010 | K22: 0.08
A23: A2030 | B23: 1.2.4 | C23: Mitigación: Limpieza y Medición de Espesores Marcos MB2/MB3 | D23: 1 | E23: 1 | F23: 46213 | G23: 46213 | H23: 0 | I23: 0 | J23: A2020 | K23: 0.06
A24: A2040 | B24: 1.2.5 | C24: Preparativos de Tendido y Montaje de Poleas en Pórticos | D24: 1 | E24: 1 | F24: 46214 | G24: 46214 | H24: 0 | I24: 0 | J24: A2030 | K24: 0.02
A25: A2050 | B25: 1.2.6 | C25: Tendido Mecánico y Regulado Conductor ACCC Lisbon (2xF) | D25: 4 | E25: 4 | F25: 46215 | G25: 46218 | H25: 0 | I25: 0 | J25: A2040 | K25: 0.09
A26: A2060 | B26: 1.2.6.1 | C26: Hito de Control: Asesoría Técnica Terreno Especialista CTC | D26: 5 | E26: 5 | F26: 46216 | G26: 46220 | H26: 0 | I26: 0 | J26: A2050 SS
A27: A2070 | B27: 1.2.7 | C27: Engrampado y Templado Final de Conductor HTLS | D27: 2 | E27: 2 | F27: 46219 | G27: 46220 | H27: 0 | I27: 0 | J27: A2050 | K27: 0.08
A28: A2080 | B28: 1.2.8 | C28: Instalación de Amortiguadores y Separadores Rígidos | D28: 2 | E28: 2 | F28: 46221 | G28: 46222 | H28: 0 | I28: 0 | J28: A2070 | K28: 0.06
A29: A2090 | B29: 1.2.9 | C29: Montaje de Conectores Tipo T y Acometidas a Equipos Patio | D29: 2 | E29: 2 | F29: 46223 | G29: 46224 | H29: 0 | I29: 0 | J29: A2080 | K29: 0.06
A30: A2100 | B30: 1.2.10 | C30: Conexión Recta de Conductor ACCC a Mufa de Acoplamiento GIS | D30: 2 | E30: 2 | F30: 46225 | G30: 46226 | H30: 0 | I30: 0 | J30: A2090 | K30: 0.05
A31: A2110 | B31: 1.2.11 | C31: Pruebas de Pre-Comisionamiento y Comisionamiento (Pre-COM/COM) | D31: 3 | E31: 3 | F31: 46227 | G31: 46229 | H31: 0 | I31: 0 | J31: A2100 | K31: 0.05
A32: A2120 | B32: 1.2.12 | C32: Hito: Barra Principal BP1 Energizada y Comercial Operativa | D32: 0 | E32: 0 | F32: 46229 | G32: 46229 | H32: 0 | I32: 0 | J32: A2110
A33: A3000 | B33: 1.3.1 | C33: Desmovilización de IIFF, Equipos y Limpieza Industrial | D33: 2 | E33: 2 | F33: 46230 | G33: 46231 | H33: 5 | I33: 0 | J33: A2120 | K33: 0.05
A34: A3010 | B34: 1.3.2 | C34: Elaboración, Validación y Entrega de Planos As-Built STN | D34: 5 | E34: 5 | F34: 46230 | G34: 46234 | H34: 0 | I34: 0 | J34: A2120 | K34: 0.02
A35: A3020 | B35: 1.3.3 | C35: Cierre Comercial del Contrato y Devolución de Garantías | D35: 1 | E35: 1 | F35: 46234 | G35: 46234 | H35: 0 | I35: 0 | J35: A3010 | K35: 0.02
A36: OH-6020 | C36: Término del Proyecto | D36: 1 | E36: 1 | F36: 46234 | G36: 46234 | H36: 0 | I36: 0 | J36: OH-6010
K37: =SUM(K7:K36) -> 1

Sheet PlanificaciónRev02.06
A2: Proyecto 4518893428- Aumento Capacidad BP1 SE OHiggins-CMDIC
A3: TABLA DE ACTIVIDADES - PROYECTO INTEGRAL
A4: Fecha Revisión : 02 de Junio 2026
A6: Activity ID | B6: Código EDT/WBS | C6: Activity Name | D6: Original Duration | E6: Remaining Duration | F6: Start | G6: Finish | H6: Total Float | I6: Performance % Complete | J6: Predecessors | K6: Peso | M6: % Complete
A7: A1000 | B7: 1.1.1 | C7: Hito: Adjudicación de Servicio y Firma Contrato | D7: 0 | E7: 0 | F7: 45950 | G7: 45950 | H7: 0 | I7: 1 | J7: --
A8: A1010 | B8: 1.1.2 | C8: Hito: Kick-Off Meeting (KOM) Oficial con MEL | D8: 0 | E8: 0 | F8: 46030 | G8: 46030 | H8: 0 | I8: 1 | J8: A1000
A9: A1100 | B9: 1.1.3 | C9: Ingeniería de Detalle Aprobada para Construcción (AptC) | D9: 72 | E9: 0 | F9: 45951 | G9: 46053 | H9: 120 | I9: 1 | J9: A1010 | K9: 0.02 | M9: =+I9*K9 -> 0.02
A10: A1120 | B10: 1.1.4 | C10: Validación Estructural y Mecánica de Marcos Existentes | D10: 15 | E10: 0 | F10: 46054 | G10: 46068 | H10: 120 | I10: 1 | J10: A1100 | K10: 0.02 | M10: =+I10*K10 -> 0.02
A11: A1130 | B11: 1.1.5 | C11: Monitoreo Arribo Suministro Conductor HTLS (RTHO) | D11: 250 | E11: 37 | F11: 45950 | G11: 46170 | H11: 0 | I11: 1 | J11: A1000 | K11: 0.05 | M11: =+I11*K11 -> 0.05
A12: A1140 | B12: 1.1.5.1 | C12: Hito: Disponibilidad de Conductor y Herrajes en Faena | D12: 0 | E12: 0 | F12: 46188 | G12: 46192 | H12: 0 | I12: 0 | J12: A1130
A13: A1500 | B13: 1.1.5.2 | C13: Examenes - Cartas Oferta - Contratación | D13: 45 | E13: 8 | F13: 46167 | G13: 46181 | H13: 10 | I13: 0.15 | J13: A1120 | K13: 0.04 | M13: =+I13*K13 -> 0.006
A14: A1510 | B14: 1.1.5.2 | C14: Tramitación y Carga de Carpetas Acreditación Personal Deloitte | D14: 45 | E14: 8 | F14: 46181 | G14: 46188 | H14: 10 | I14: 0.1 | J14: A1120 | K14: 0.03 | M14: =+I14*K14 -> 0.003
A15: A1520 | B15: 1.1.5.3 | C15: Pases de Vehículos y Maquinarias (MEL) | D15: 30 | E15: 9 | F15: 46174 | G15: 46188 | H15: 10 | I15: 0.65 | J15: A1500 | K15: 0.02 | M15: =+I15*K15 -> 0.013
A16: A1530 | B16: 1.1.5.4 | C16: Certificación 3D CEIM | D16: 20 | E16: 20 | F16: 46174 | G16: 46196 | H16: 10 | I16: 0.1 | M16: =+I16*K16 -> 0
A17: A1540 | B17: 1.1.5.5 | C17: Aprobación Final de Planes de Izaje Estándar BHP (Pluma) | D17: 15 | E17: 15 | F17: 46174 | G17: 46188 | H17: 10 | I17: 0 | J17: A1520 | K17: 0.03 | M17: =+I17*K17 -> 0
A18: A1600 | B18: 1.1.6 | C18: Capacitación CTC Global (Personal STN en Antofagasta) | D18: 4 | E18: 4 | F18: 46197 | G18: 46199 | H18: 0 | I18: 0 | J18: A1140 | K18: 0.06 | M18: =+I18*K18 -> 0
A19: A1700 | B19: 1.1.7 | C19: Movilización de Equipos y Container a SSEE Ohiggins | D19: 5 | E19: 5 | F19: 46181 | G19: 46192 | H19: 0 | I19: 0 | J19: A1140, A1540 | K19: 0.06 | M19: =+I19*K19 -> 0
A20: A2000 | B20: 1.2.1 | C20: Hito: Ventana Contractual - Inicio Obras Terreno | D20: 0 | E20: 0 | F20: 46202 | G20: 46209 | H20: 0 | I20: 0 | J20: A1600
A21: A2010 | B21: 1.2.2 | C21: Recepción de Área de Trabajo y Bloqueos Eléctricos BP1 | D21: 1 | E21: 1 | F21: 46202 | G21: 46202 | H21: 0 | I21: 0 | J21: A2000, A1700 | K21: 0.03 | M21: =+I21*K21 -> 0
A22: A2020 | B22: 1.2.3 | C22: Retiro de Conductor Flint Existente y Desarme de Herrajes | D22: 3 | E22: 2 | F22: 46203 | G22: 46203 | H22: 0 | I22: 0 | J22: A2010 | K22: 0.08 | M22: =+I22*K22 -> 0
A23: A2030 | B23: 1.2.4 | C23: Mitigación: Limpieza y Medición de Espesores Marcos MB2/MB3 | D23: 1 | E23: 1 | F23: 46203 | G23: 46203 | H23: 0 | I23: 0 | J23: A2020 | K23: 0.06 | M23: =+I23*K23 -> 0
A24: A2040 | B24: 1.2.5 | C24: Preparativos de Tendido y Montaje de Poleas en Pórticos | D24: 1 | E24: 1 | F24: 46203 | G24: 46203 | H24: 0 | I24: 0 | J24: A2030 | K24: 0.02 | M24: =+I24*K24 -> 0
A25: A2050 | B25: 1.2.6 | C25: Tendido Mecánico y Regulado Conductor ACCC Lisbon (2xF) | D25: 4 | E25: 4 | F25: 46204 | G25: 46204 | H25: 0 | I25: 0 | J25: A2040 | K25: 0.09 | M25: =+I25*K25 -> 0
A26: A2060 | B26: 1.2.7 | C26: Engrampado y Templado Final de Conductor HTLS | D26: 2 | E26: 2 | F26: 46205 | G26: 46205 | H26: 0 | I26: 0 | J26: A2050 | K26: 0.08 | M26: =+I26*K26 -> 0
A27: A2070 | B27: 1.2.8 | C27: Instalación de Amortiguadores y Separadores Rígidos | D27: 2 | E27: 2 | F27: 46205 | G27: 46205 | H27: 0 | I27: 0 | J27: A2070 | K27: 0.06 | M27: =+I27*K27 -> 0
A28: A2080 | B28: 1.2.9 | C28: Montaje de Conectores Tipo T y Acometidas a Equipos Patio | D28: 2 | E28: 2 | F28: 46205 | G28: 46205 | H28: 0 | I28: 0 | J28: A2080 | K28: 0.06 | M28: =+I28*K28 -> 0
A29: A2090 | B29: 1.2.10 | C29: Conexión Recta de Conductor ACCC a Mufa de Acoplamiento GIS | D29: 2 | E29: 2 | F29: 46206 | G29: 46206 | H29: 0 | I29: 0 | J29: A2090 | K29: 0.05 | M29: =+I29*K29 -> 0
A30: A2100 | B30: 1.2.11 | C30: Pruebas de Pre-Comisionamiento y Comisionamiento (Pre-COM/COM) | D30: 3 | E30: 3 | F30: 46209 | G30: 46209 | H30: 0 | I30: 0 | J30: A2100 | K30: 0.05 | M30: =+I30*K30 -> 0
A31: A2110 | B31: 1.2.12 | C31: Hito: Barra Principal BP1 Energizada y Comercial Operativa | D31: 0 | E31: 0 | F31: 46209 | G31: 46209 | H31: 0 | I31: 0 | J31: A2110
A32: A3000 | B32: 1.3.1 | C32: Desmovilización de IIFF, Equipos y Limpieza Industrial | D32: 2 | E32: 2 | F32: 46210 | G32: 46211 | H32: 5 | I32: 0 | J32: A2120 | K32: 0.05 | M32: =+I32*K32 -> 0
A33: A3010 | B33: 1.3.2 | C33: Elaboración, Validación y Entrega de Planos As-Built STN | D33: 5 | E33: 5 | F33: 46211 | G33: 46216 | H33: 5 | I33: 0 | J33: A2120 | K33: 0.02 | M33: =+I33*K33 -> 0
A34: A3020 | B34: 1.3.3 | C34: Cierre Comercial del Contrato | D34: 1 | E34: 1 | F34: 46216 | G34: 46230 | H34: 3 | I34: 0 | J34: A3010 | K34: 0.02 | M34: =+I34*K34 -> 0
A35: OH-6020 | C35: Término del Proyecto | D35: 1 | E35: 1 | F35: 46234 | G35: 46234 | H35: 0 | I35: 0 | J35: OH-6010 | M35: =+I35*K35 -> 0
K36: =SUM(K7:K35) -> 1 | M36: =SUM(M9:M35) -> 0.112

Sheet Kanban
B2: KANBAN | H2: Tablero Tareas
B3: Backlog / Por Iniciar | C3: En Proceso | D3: En Revisión / MEL | E3: Aprobado / Terminado | F3: Bloqueado / Riesgo
B4: Instalación de faena en S/E | C4: Cursos LMS | D4: Aprobación de CVs (Lote 2) | E4: Kick-off Meeting KOM | F4: Acreditación de CTC Global | H4: Total Tareas: | I4: =COUNTA('Detalle Compromisos'!C2:C106) -> 41
B5: Cursos OTEC | C5: Finalizar cursos Mutual, inducción MEL (5h) | E5: Suministro conductor HTLS ACCC (RTHO) - En Bodega STN Buín | H5: % Avance Físico Global: | I5: =AVERAGE('Detalle Compromisos'!H2:H106) -> 0.047619048
B6: Traslado de conductor eléctrico desde zona sur
B7: Regularizar certificado Hombre Muerto PESCO para Camión Grúa | H7: Resumen por Responsable | I7: Tareas Asignadas
B8: Movilización especialista CTC Global | C8: Homologación Camión Pluma | D8: Ingeniería As Built de marcos (KPro) | E8: Aprobación de Contrato | H8: Jose Contuliano | I8: =COUNTIF('Detalle Compromisos'!$D$1:$D$119, "Jose Contuliano") -> 2
B9: Coaching psicológico 3D (10-12 personas) | C9: Obtener validación de MEL (Osman/Marco) para CV Supervisor | H9: Juan Carlos Santander | I9: =COUNTIF('Detalle Compromisos'!$D$1:$D$120, "Juan Carlos Santander") -> 4
B10: Tendido y templado 2 condxfase ACCC | C10: Carga de cursos LMS y OTEC | E10: Plan de Calidad y SSO | H10: Jesenia Ramirez | I10: =COUNTIF('Detalle Compromisos'!$D$1:$D$121, "Jesenia Ramirez") -> 3
B11: Retirar 3 camionetas estándar MEL desde Tatersal Antofagasta | H11: Andres Tebes | I11: =COUNTIF('Detalle Compromisos'!$D$7:$D$122, "Andres Tebes") -> 0
B12: Confirmar condición de entrega en sitio de Container arrendado | H12: Claudio Cajas | I12: =COUNTIF('Detalle Compromisos'!$D$8:$D$123, "Claudio Cajas") -> 1
B13: Comprar ropa de invierno requerida para test 3D | H13: Franklin Godoy | I13: =COUNTIF('Detalle Compromisos'!$D$9:$D$124, "Franklin Godoy") -> 3
B14: Emitir OC vía CAPEX para 4 radios APX 1.500 | I14: =SUM(I8:I13) -> 13

Sheet Curva_S_Avance
B2: CONTROL DE AVANCE FÍSICO Y CURVA S (METODOLOGÍA PMI) | I2: CONTROL DE AVANCE FINANCIERO Y CURVA S (METODOLOGÍA PMI)
B5: Indicador | C5: Mayo 2026 | D5: Junio 2026 | E5: Julio 2026 | F5: Agosto 2026 | G5: Septiembre 2026 | I5: Mes | J5: PV ($) | K5: EV ($) | L5: AC ($)
B6: Avance Planificado Mensual | C6: 0.12 | D6: 0.18 | E6: 0.6 | F6: 0.1 | G6: 0 | I6: May | J6: 30000000 | K6: 25000000 | L6: 26800000
B7: Avance Planificado Acumulado (PV %) | C7: =IFERROR(SUM(C6:C6), "Pendiente") -> 0.12 | D7: =IFERROR(SUM(C6:D6), "Pendiente") -> 0.3 | E7: =IFERROR(SUM(C6:E6), "Pendiente") -> 0.9 | F7: =IFERROR(SUM(C6:F6), "Pendiente") -> 1 | G7: =IFERROR(SUM(C6:G6), "Pendiente") -> 1 | I7: Jun | J7: 75000000 | K7: 0 | L7: 0
B8: Avance Físico Real Mensual | C8: 0.05 | D8: 0 | E8: 0 | F8: 0 | G8: 0 | I8: Jul | J8: 220000000 | K8: 0 | L8: 0
B9: Avance Físico Real Acumulado (EV %) | C9: =IFERROR(SUM(C8:C8), "Pendiente") -> 0.05 | D9: =IFERROR(SUM(C8:D8), "Pendiente") -> 0.05 | E9: =IFERROR(SUM(C8:E8), "Pendiente") -> 0.05 | F9: =IFERROR(SUM(C8:F8), "Pendiente") -> 0.05 | G9: =IFERROR(SUM(C8:G8), "Pendiente") -> 0.05 | I9: Ago | J9: 253028082 | K9: 0 | L9: 0
B10: Variación del Cronograma (SV % = EV - PV) | C10: =IFERROR(C9 - C7, "Pendiente") -> -0.07 | D10: =IFERROR(D9 - D7, "Pendiente") -> -0.25 | E10: =IFERROR(E9 - E7, "Pendiente") -> -0.85 | F10: =IFERROR(F9 - F7, "Pendiente") -> -0.95 | G10: =IFERROR(G9 - G7, "Pendiente") -> -0.95
B11: Índice Desempeño Cronograma (SPI = EV/PV) | C11: =IFERROR(C9 / C7, "Pendiente") -> 0.41666667 | D11: =IFERROR(D9 / D7, "Pendiente") -> 0.16666667 | E11: =IFERROR(E9 / E7, "Pendiente") -> 0.055555556 | F11: =IFERROR(F9 / F7, "Pendiente") -> 0.05 | G11: =IFERROR(G9 / G7, "Pendiente") -> 0.05
B12: * Ingrese el Avance Físico Real Mensual en las celdas celestes (Fila 8).
B14: CONTROL FINANCIERO (EVM $)
B15: Mes | C15: May 2026 | D15: Jun 2026 | E15: Jul 2026 | F15: Ago 2026 | G15: Sep 2026
B16: Valor Planeado Acumulado PV ($) | C16: =253028082.12 * C7 -> 30363370 | D16: =253028082.12 * D7 -> 75908425 | E16: =253028082.12 * E7 -> 2.2772527e+08 | F16: =253028082.12 * F7 -> 2.5302808e+08 | G16: =253028082.12 * G7 -> 2.5302808e+08
B17: Valor Ganado Acumulado EV ($) | C17: =253028082.12 * C9 -> 12651404 | D17: =253028082.12 * D9 -> 12651404 | E17: =253028082.12 * E9 -> 12651404 | F17: =253028082.12 * F9 -> 12651404 | G17: =253028082.12 * G9 -> 12651404
B18: Costo Real Acumulado AC ($) | C18: =SUM(Control_Presupuesto!D39) -> 200000 | D18: =SUM(Control_Presupuesto!E39) -> 0 | E18: =SUM(Control_Presupuesto!F39) -> 0 | F18: =SUM(Control_Presupuesto!G39) -> 0 | G18: =SUM(Control_Presupuesto!H39) -> 0
B20: CONTROL HORAS HOMBRE (HH)
B21: Mes | C21: May 2026 | D21: Jun 2026 | E21: Jul 2026 | F21: Ago 2026 | G21: Sep 2026 | H21: Total
B22: HH Real Incurridas Mensual | C22: 1250 | D22: 0 | E22: 0 | F22: 0 | G22: 0 | H22: =SUM(C22:G22) -> 1250
B23: Dotación Real Total | C23: 4 | D23: 0 | E23: 0 | F23: 0 | G23: 0
B24: HH Planificadas Mensual | C24: =+C25*(42*4) -> 672 | D24: =+D25*(42*4) -> 2856 | E24: =+E25*(42*4) -> 2856 | F24: =+F25*(42*4) -> 672 | G24: =+G25*(42*4) -> 168 | H24: =SUM(C24:G24) -> 7224
B25: Dotación Total Planificada | C25: 4 | D25: 17 | E25: 17 | F25: 4 | G25: 1

Sheet CartaGantt

Sheet Equipos_y_Flota
A1: ID | B1: Tipo Equipo | C1: Identificador / Patente | D1: Ubicación | E1: Responsable | F1: Doc. Base | G1: Seguro / Rev. Tec. | H1: Checklist Faena | I1: Op. Habilitado | J1: Inspección CEIM | K1: Tracktec / Sello | L1: Homologación | M1: Fecha Vencimiento | N1: % Avance Acreditación | O1: Estado | P1: Semáforo (Icono) | Q1: Observaciones
A2: V001 | B2: Camioneta | C2: Patente-1 | D2: Tattersal | E2: Franklin Godoy | F2: Pendiente doc. | G2: Pendiente doc. | H2: Pendiente doc. | I2: Pendiente doc. | J2: N/A | K2: Pendiente doc. | L2: N/A | M2: 46188 | O2: =IFERROR(IF(N2=1, "Acreditado", IF(N2>0, "En Proceso", "No Iniciado")), "Pendiente") -> No Iniciado | P2: =IFERROR(IF(O2="Acreditado", 3, IF(O2="En Proceso", 2, 1)), "Pendiente") -> 1
A3: V002 | B3: Camioneta | C3: Patente-2 | D3: Tattersal | E3: Franklin Godoy | F3: Pendiente doc. | G3: Pendiente doc. | H3: Pendiente doc. | I3: Pendiente doc. | J3: N/A | K3: Pendiente doc. | L3: N/A | M3: 46188 | O3: =IFERROR(IF(N3=1, "Acreditado", IF(N3>0, "En Proceso", "No Iniciado")), "Pendiente") -> No Iniciado | P3: =IFERROR(IF(O3="Acreditado", 3, IF(O3="En Proceso", 2, 1)), "Pendiente") -> 1
A4: V003 | B4: Camioneta | C4: Patente-3 | D4: Tattersal | E4: Franklin Godoy | F4: Pendiente doc. | G4: Pendiente doc. | H4: Pendiente doc. | I4: Pendiente doc. | J4: N/A | K4: Pendiente doc. | L4: N/A | M4: 46188 | O4: =IFERROR(IF(N4=1, "Acreditado", IF(N4>0, "En Proceso", "No Iniciado")), "Pendiente") -> No Iniciado | P4: =IFERROR(IF(O4="Acreditado", 3, IF(O4="En Proceso", 2, 1)), "Pendiente") -> 1
A5: V004 | B5: Camioneta | C5: Patente-4 | D5: Tattersal | E5: Franklin Godoy | F5: Pendiente doc. | G5: Pendiente doc. | H5: Pendiente doc. | I5: Pendiente doc. | J5: N/A | K5: Pendiente doc. | L5: N/A | M5: 46188 | O5: =IFERROR(IF(N5=1, "Acreditado", IF(N5>0, "En Proceso", "No Iniciado")), "Pendiente") -> No Iniciado | P5: =IFERROR(IF(O5="Acreditado", 3, IF(O5="En Proceso", 2, 1)), "Pendiente") -> 1
A6: CP01 | B6: Camión Pluma | C6: SHFS-99 | D6: STN Antofagasta | E6: Franklin Godoy | F6: OK | G6: Ok | H6: Pendiente doc. | I6: Pendiente doc. | J6: Pendiente doc. | K6: Pendiente doc. | L6: N/A | M6: 46188 | O6: =IFERROR(IF(N6=1, "Acreditado", IF(N6>0, "En Proceso", "No Iniciado")), "Pendiente") -> No Iniciado | P6: =IFERROR(IF(O6="Acreditado", 3, IF(O6="En Proceso", 2, 1)), "Pendiente") -> 1
A7: HR01 | B7: Herramienta Crítica | C7: Torque-01 | E7: Leonel Sanchez | F7: Pendiente doc. | G7: N/A | H7: N/A | I7: N/A | J7: Aprobado | K7: Aprobado | L7: Aprobado | O7: =IFERROR(IF(N7=1, "Acreditado", IF(N7>0, "En Proceso", "No Iniciado")), "Pendiente") -> No Iniciado | P7: =IFERROR(IF(O7="Acreditado", 3, IF(O7="En Proceso", 2, 1)), "Pendiente") -> 1
A8: HR02 | B8: Herramienta Crítica | C8: Izaje-01 | E8: Leonel Sanchez | F8: Pendiente doc. | G8: N/A | H8: N/A | I8: N/A | J8: No iniciado | K8: No iniciado | L8: No iniciado | O8: =IFERROR(IF(N8=1, "Acreditado", IF(N8>0, "En Proceso", "No Iniciado")), "Pendiente") -> No Iniciado | P8: =IFERROR(IF(O8="Acreditado", 3, IF(O8="En Proceso", 2, 1)), "Pendiente") -> 1
A9: EQ-01 | B9: Estación Total | C9: S/N: 12345 | E9: Leonel Sanchez | F9: Pendiente doc. | G9: N/A | H9: No iniciado | I9: N/A | J9: No iniciado | K9: N/A | L9: N/A | O9: =IFERROR(IF(N9=1, "Acreditado", IF(N9>0, "En Proceso", "No Iniciado")), "Pendiente") -> No Iniciado | P9: =IFERROR(IF(O9="Acreditado", 3, IF(O9="En Proceso", 2, 1)), "Pendiente") -> 1 | Q9: Certificado de calibración requerido

Sheet RACI
A1: Fase / Entregable Principal | B1: Controller / PM | C1: Administrador | D1: Jefe Terreno | E1: HSEC | F1: Oficina Técnica | G1: Especialista CTC
A2: Acreditación de Personal y Equipos | B2: A | C2: R | D2: I | E2: R | F2: C | G2: I
A3: Ingeniería As Built KPro | B3: A | C3: I | D3: I | E3: I | F3: R | G3: C
A4: Suministro Conductor ACCC RTHO | B4: R/A | C4: R | D4: C | E4: I | F4: I | G4: C
A5: Montaje y Tendido de Cable HTLS | B5: A | C5: A | D5: R | E5: C | F5: I | G5: C
A6: Pruebas y Comisionamiento (Pre COM/COM) | B6: A | C6: A | D6: R | E6: I | F6: C | G6: C
A7: Cierre de Proyecto y Dossier Calidad | B7: A | C7: R | D7: C | E7: C | F7: R | G7: I
A10: ¿QUÉ ES LA MATRIZ RACI?
A11: La Matriz RACI es una herramienta de gestión organizacional que define claramente los roles y responsabilidades para cada tarea crítica de un proyecto. Su sentido fundamental es evitar confusiones sobre quién debe ejecutar el trabajo (R), quién tiene la responsabilidad de aprobación final (A), a quién consultar como experto (C) y a quién se debe mantener informado (I). De este modo, se asegura que el proyecto avance sin superposición de roles ni cuellos de botella.
A15: LEYENDA RACI TÉCNICA
A16: R (Responsible / Responsable) | C16: Quien ejecuta la tarea y hace el trabajo real. Es el hacedor (doer).
A17: A (Accountable / Aprobador) | C17: Quien tiene la responsabilidad final y aprueba el trabajo (Solo debe haber 1 'A' por tarea).
A18: C (Consulted / Consultado) | C18: Quien aporta información clave, consejo o expertise antes o durante la tarea.
A19: I (Informed / Informado) | C19: Quien debe ser notificado del progreso o finalización. Comunicación unidireccional.

Sheet Matriz de Riesgos
A1: Faltan titulos
A2: R1 | B2: RRHH | C2: Vacante crítica operador/rigger | D2: Alta | E2: Alta | F2: 9 | G2: Reclutamiento acelerado + bolsa externa | H2: CTRL_01 | I2: 01-06-2026 | J2: Abierto | K2: Rojo
A3: R2 | B3: Flota | C3: Demora homologación camión pluma | D3: Alta | E3: Alta | F3: 9 | G3: Seguimiento diario y plan de contingencia | H3: ADM_01 | I3: 01-06-2026 | J3: Abierto | K3: Rojo
A4: R3 | B4: HSEC | C4: Vencimiento exámenes o cursos antes de movilización | D4: Media | E4: Alta | F4: 6 | G4: Acreditación por oleadas y control vencimientos | H4: HSEC_01 | I4: 15-06-2026 | J4: Abierto | K4: Rojo
A5: R4 | B5: RRHH | C5: Demora VB MEL a CVs lote 2 | D5: Media | E5: Alta | F5: 6 | G5: Apoyo vía contacto mantenimiento MEL | H5: CTRL_01 | I5: 15-06-2026 | J5: Abierto | K5: Rojo
A6: R5 | B6: Flota | C6: Camionetas fuera de estándar Tracktec | D6: Baja | E6: Alta | F6: 3 | G6: Upgrade técnico previo a sello | H6: ADM_01 | I6: 30-05-2026 | J6: Abierto | K6: Amarillo

Sheet 6. Contratos Servicios
AK2: =SUM(AK4:AK172) -> #REF! | AL2: =SUM(AL4:AL172) -> #REF! | AM2: =SUM(AM4:AM172) -> #REF! | AN2: =SUM(AN4:AN172) -> #REF! | AO2: =SUM(AO4:AO172) -> #REF! | AP2: =SUM(AP4:AP172) -> #REF! | AQ2: =SUM(AQ4:AQ172) -> #REF! | AR2: =SUM(AR4:AR172) -> #REF! | ... AT2: =SUM(AT4:AT172) -> #REF!
B3: Item | C3: Descripción del Servicio | D3: Proveedor 1 | E3: Proveedor 2 | F3: Proveedor 3 | G3: Responsable | H3: Fecha inicio | I3: Fecha límite | J3: Contrato Firma | K3: % Real | L3: % Esperado | M3: Estado | N3: Semáforo | O3: Observaciones Semana 11.06 | P3: Observaciones 27-08-2025 | Q3: Observaciones 24.10.2025 | R3: Comentarios 15.12.2025 | S3: Comentarios 07.12.2025 | T3: Observaciones 30.10.2025 | U3: Observaciones Semana 5 | V3: Observaciones Semana 6 | W3: Observaciones Semana 7 | X3: Observaciones Semana 8 | Y3: Observaciones Semana 9 | Z3: Observaciones Semana 10 | AA3: 43895 | AB3: 43901 | AC3: 43909 | AD3: 43916 | AE3: 43923 | AF3: 43930 | AG3: 43937 | AH3: 43944 | AI3: 43951 | AJ3: 43958 | AK3: Semana 1 | AL3: Semana 2 | AM3: Semana 3 | AN3: Semana 4 | AO3: Semana 5 | AP3: Semana 6 | AQ3: Semana 7 | AR3: Semana 8 | AS3: Semana 9 | AT3: Semana 10
B4: 1 | C4: Arriendo Camionetas (Leasing Operativo) | D4: Tattersall | G4: STN | H4: 45712 | I4: 45971 | J4: Firmado | K4: 1 | L4: =IF($H4>TODAY(),0,IF(OR($I4="Eliminada",$I4="En Revision"),$I4,IF($I4<>"Eliminada",IF($I4>TODAY(),(TODAY()-$H4)/($I4-$H4),1),0))) -> 1 | M4: =IF(K4=1,"Terminada",IF(K4<L4,"Atrasado", "A Tiempo")) -> Terminada | N4: =IF($M4="Eliminada",-2,IF($M4="Terminada",2,IF($M4="A Tiempo",1,IF($M4="En Revision",0,-1)))) -> 2 | O4: BHP debe indicar las especificaciones para área mina y ruta | Q4: Camionetas en Antofagasta y MEL, en coordinacion bajada para instalación de radios. | R4: Flota Completa. | S4: Flota Completa. | T4: Camionetas en Antofagasta y MEL, en coordinacion bajada para instalación de radios, estas ultimas en programación | AA4: =+IF(#REF!<$AA$3,1,0) -> #REF! | AB4: =+IF(AA4=0,IF($I4<$AB$3,1,0),0) -> #REF! | AC4: =+IF(SUM(AA4:AB4)=0,IF($I4<$AC$3,1,0),0) -> #REF! | AD4: =+IF(SUM(AA4:AC4)=0,IF($I4<$AD$3,1,0),0) -> #REF! | AE4: =+IF(SUM(AA4:AD4)=0,IF($I4<$AE$3,1,0),0) -> #REF! | AF4: =+IF(SUM(AA4:AE4)=0,IF($I4<$AF$3,1,0),0) -> #REF! | AG4: =+IF(SUM(AA4:AF4)=0,IF($I4<$AG$3,1,0),0) -> #REF! | AH4: =+IF(SUM(AA4:AG4)=0,IF($I4<$AH$3,1,0),0) -> #REF! | AI4: =+IF(SUM(AA4:AH4)=0,IF($I4<$AI$3,1,0),0) -> #REF! | AJ4: =+IF(SUM(AA4:AI4)=0,IF($I4<$AJ$3,1,0),0) -> #REF! | AK4: =AA4 -> #REF! | AL4: =AK4+AB4 -> #REF! | AM4: =AL4+AC4 -> #REF! | AN4: =AM4+AD4 -> #REF! | AO4: =AN4+AE4 -> #REF! | AP4: =AO4+AF4 -> #REF! | AQ4: =AP4+AG4 -> #REF! | AR4: =AQ4+AH4 -> #REF! | AS4: =AR4+AI4 -> #REF! | AT4: =AS4+AJ4 -> #REF!
B5: =+B4+1 -> 2 | C5: Alojamiento en Faena | D5: BHP | G5: BHP | H5: 45712 | I5: 45971 | J5: OK | K5: 1 | L5: =IF($H5>TODAY(),0,IF(OR($I5="Eliminada",$I5="En Revision"),$I5,IF($I5<>"Eliminada",IF($I5>TODAY(),(TODAY()-$H5)/($I5-$H5),1),0))) -> 1 | M5: =IF(K5=1,"Terminada",IF(K5<L5,"Atrasado", "A Tiempo")) -> Terminada | N5: =IF($M5="Eliminada",-2,IF($M5="Terminada",2,IF($M5="A Tiempo",1,IF($M5="En Revision",0,-1)))) -> 2 | O5: Especificaciones de distribucion de alojamientos del personal de STN en Escondida | Q5: Se debe emitir nomina 10 dias antes del inicio de servicio de STN | R5: OK, En programacion según curva de Alojamiento. | S5: OK, En programacion según curva de Alojamiento. | T5: Se debe emitir nomina 10 dias antes del inicio de servicio de STN | AA5: =+IF(#REF!<$AA$3,1,0) -> #REF! | AB5: =+IF(AA5=0,IF($I5<$AB$3,1,0),0) -> #REF! | AC5: =+IF(SUM(AA5:AB5)=0,IF($I5<$AC$3,1,0),0) -> #REF! | AD5: =+IF(SUM(AA5:AC5)=0,IF($I5<$AD$3,1,0),0) -> #REF! | AE5: =+IF(SUM(AA5:AD5)=0,IF($I5<$AE$3,1,0),0) -> #REF! | AF5: =+IF(SUM(AA5:AE5)=0,IF($I5<$AF$3,1,0),0) -> #REF! | AG5: =+IF(SUM(AA5:AF5)=0,IF($I5<$AG$3,1,0),0) -> #REF! | AH5: =+IF(SUM(AA5:AG5)=0,IF($I5<$AH$3,1,0),0) -> #REF! | AI5: =+IF(SUM(AA5:AH5)=0,IF($I5<$AI$3,1,0),0) -> #REF! | AJ5: =+IF(SUM(AA5:AI5)=0,IF($I5<$AJ$3,1,0),0) -> #REF! | AK5: =AA5 -> #REF! | AL5: =AK5+AB5 -> #REF! | AM5: =AL5+AC5 -> #REF! | AN5: =AM5+AD5 -> #REF! | AO5: =AN5+AE5 -> #REF! | AP5: =AO5+AF5 -> #REF! | AQ5: =AP5+AG5 -> #REF! | AR5: =AQ5+AH5 -> #REF! | AS5: =AR5+AI5 -> #REF! | AT5: =AS5+AJ5 -> #REF!
B6: =+B5+1 -> 3 | C6: Alimentación en faena | D6: BHP | G6: BHP | H6: 45712 | I6: 45971 | J6: OK | K6: 1 | L6: =IF($H6>TODAY(),0,IF(OR($I6="Eliminada",$I6="En Revision"),$I6,IF($I6<>"Eliminada",IF($I6>TODAY(),(TODAY()-$H6)/($I6-$H6),1),0))) -> 1 | M6: =IF(K6=1,"Terminada",IF(K6<L6,"Atrasado", "A Tiempo")) -> Terminada | N6: =IF($M6="Eliminada",-2,IF($M6="Terminada",2,IF($M6="A Tiempo",1,IF($M6="En Revision",0,-1)))) -> 2 | Q6: Se debe emitir nomina 10 dias antes del inicio de servicio de STN | R6: OK, En programacion según curva de Alojamiento. | S6: OK, En programacion según curva de Alojamiento. | T6: Se debe emitir nomina 10 dias antes del inicio de servicio de STN | AA6: =+IF(#REF!<$AA$3,1,0) -> #REF! | AB6: =+IF(AA6=0,IF($I6<$AB$3,1,0),0) -> #REF! | AC6: =+IF(SUM(AA6:AB6)=0,IF($I6<$AC$3,1,0),0) -> #REF! | AD6: =+IF(SUM(AA6:AC6)=0,IF($I6<$AD$3,1,0),0) -> #REF! | AE6: =+IF(SUM(AA6:AD6)=0,IF($I6<$AE$3,1,0),0) -> #REF! | AF6: =+IF(SUM(AA6:AE6)=0,IF($I6<$AF$3,1,0),0) -> #REF! | AG6: =+IF(SUM(AA6:AF6)=0,IF($I6<$AG$3,1,0),0) -> #REF! | AH6: =+IF(SUM(AA6:AG6)=0,IF($I6<$AH$3,1,0),0) -> #REF! | AI6: =+IF(SUM(AA6:AH6)=0,IF($I6<$AI$3,1,0),0) -> #REF! | AJ6: =+IF(SUM(AA6:AI6)=0,IF($I6<$AJ$3,1,0),0) -> #REF! | AK6: =AA6 -> #REF! | AL6: =AK6+AB6 -> #REF! | AM6: =AL6+AC6 -> #REF! | AN6: =AM6+AD6 -> #REF! | AO6: =AN6+AE6 -> #REF! | AP6: =AO6+AF6 -> #REF! | AQ6: =AP6+AG6 -> #REF! | AR6: =AQ6+AH6 -> #REF! | AS6: =AR6+AI6 -> #REF! | AT6: =AS6+AJ6 -> #REF!
B7: =+B6+1 -> 4 | C7: Lavandería | D7: Lavanor | E7: LeGrand Chic | F7: La Maestranza | G7: STN | H7: 45870 | I7: 45971 | J7: Firmado | K7: 1 | L7: =IF($H7>TODAY(),0,IF(OR($I7="Eliminada",$I7="En Revision"),$I7,IF($I7<>"Eliminada",IF($I7>TODAY(),(TODAY()-$H7)/($I7-$H7),1),0))) -> 1 | M7: =IF(K7=1,"Terminada",IF(K7<L7,"Atrasado", "A Tiempo")) -> Terminada | N7: =IF($M7="Eliminada",-2,IF($M7="Terminada",2,IF($M7="A Tiempo",1,IF($M7="En Revision",0,-1)))) -> 2 | O7: Indicar los requerimientos para ingresos de empresa externa, considerando que es un svs esporadico. | P7: En contacto con proveedor con oferta emitida. | Q7: Contrato en proceso de firmas, lidera Rodrigo Ackerman (STN) y Eduardo Varela (Lavanor), Plazo de Termino 30.10.2025 | R7: Contrato OK, Creado en PMF. Alejandro Morgado debe indicar estado de carpeta de arranque para ver el ingreso del personal en Deloitte. | S7: Contrato OK, Creado en PMF, falta la homologacion de Carpeta de Arranque y Validacion de Personal subcontrato HDR | T7: Contrato Firmado, en proceso de habilitación de Subcontrato Lavanor en MEL
B8: =+B7+1 -> 5 | C8: Combustible | D8: TCT Copec | E8: Chip Copec | G8: STN | H8: 45870 | I8: 45985 | J8: Pendiente adhesion chip faena. | K8: 1 | L8: =IF($H8>TODAY(),0,IF(OR($I8="Eliminada",$I8="En Revision"),$I8,IF($I8<>"Eliminada",IF($I8>TODAY(),(TODAY()-$H8)/($I8-$H8),1),0))) -> 1 | M8: =IF(K8=1,"Terminada",IF(K8<L8,"Atrasado", "A Tiempo")) -> Terminada | N8: =IF($M8="Eliminada",-2,IF($M8="Terminada",2,IF($M8="A Tiempo",1,IF($M8="En Revision",0,-1)))) -> 2 | O8: Contacto Proyectado 01-07-2025 | Q8: TCT para Ruta y Antofagasta, 100%. En gestion de proceso de combustible de faena. | R8: TCT OK, se agrega el Adblue en todas las tarjetas. Combustible de Faena, OK normalizad 11.12.2025. | S8: TCT OK, Se debe revisar con Copec el estado de adhesion de faena, ya que se cuentan con las tarjetas por vehiculo pero estan con Cargo a MEL. Reunion 09.12.2025 con Copec para ver los pasos a seguir. | T8: TCT para Ruta y Antofagasta, 100%. En gestion de proceso de combustible de faena.
B9: =+B8+1 -> 6 | C9: Alojamiento Adicional STN en Antofagasta | D9: Hotel Licantay | E9: Hotel Ancla Inn | F9: Hotel Madero | G9: STN | H9: 45870 | I9: 45971 | J9: Firmado | K9: 1 | L9: =IF($H9>TODAY(),0,IF(OR($I9="Eliminada",$I9="En Revision"),$I9,IF($I9<>"Eliminada",IF($I9>TODAY(),(TODAY()-$H9)/($I9-$H9),1),0))) -> 1 | M9: =IF(K9=1,"Terminada",IF(K9<L9,"Atrasado", "A Tiempo")) -> Terminada | N9: =IF($M9="Eliminada",-2,IF($M9="Terminada",2,IF($M9="A Tiempo",1,IF($M9="En Revision",0,-1)))) -> 2 | O9: Para personal en Antofagasta | Q9: Personal de Bajada: Licantay/Hotel /Madero Personal 5x2: Madero + Otros | R9: Alojamiento Sr. Hugo Gonzalez y Brayan Zepeda (Madero) | S9: OK, programados para los turnos de bajada y para el personal de 5x2 (H. Gonzalez, B. Zepeda) | T9: Personal de Bajada: Licantay/Hotel /Madero Personal 5x2: Madero + Otros
B10: =+B9+1 -> 7 | C10: Suministro Agua Desmineralizada | D10: Spot | G10: STN | H10: 45870 | I10: 45971 | J10: Firmado | K10: 1 | L10: =IF($H10>TODAY(),0,IF(OR($I10="Eliminada",$I10="En Revision"),$I10,IF($I10<>"Eliminada",IF($I10>TODAY(),(TODAY()-$H10)/($I10-$H10),1),0))) -> 1 | M10: =IF(K10=1,"Terminada",IF(K10<L10,"Atrasado", "A Tiempo")) -> Terminada | N10: =IF($M10="Eliminada",-2,IF($M10="Terminada",2,IF($M10="A Tiempo",1,IF($M10="En Revision",0,-1)))) -> 2 | O10: Proveedor Actual de STN Antofagasta, generar Adenda | Q10: Proveedor actual de Agua desmineralizada de Spot. | R10: OK a traves de proveedor de Spot. | S10: OK a traves de proveedor de Spot. | T10: Proveedor actual de Agua desmineralizada de Spot.
B11: =+B10+1 -> 8 | C11: Instalaciones de faena | D11: BHP | G11: BHP | H11: 45870 | I11: 45971 | J11: Pendiente | K11: 0.85 | L11: =IF($H11>TODAY(),0,IF(OR($I11="Eliminada",$I11="En Revision"),$I11,IF($I11<>"Eliminada",IF($I11>TODAY(),(TODAY()-$H11)/($I11-$H11),1),0))) -> 1 | M11: =IF(K11=1,"Terminada",IF(K11<L11,"Atrasado", "A Tiempo")) -> Atrasado | N11: =IF($M11="Eliminada",-2,IF($M11="Terminada",2,IF($M11="A Tiempo",1,IF($M11="En Revision",0,-1)))) -> -1 | O11: El mantenimiento de las instalaciones será aporte de BHP ( Baños, techumbres, otros) | Q11: Revisar los estados de instalaciones, Mobiliario, aire acondicionado,techumbre, entre otros. | R11: En estado de puesta en servicio, primera inspeccion 01.12.2025 | S11: En estado de puesta en servicio, primera inspeccion 01.12.2025 | T11: Revisar los estados de instalaciones, Mobiliario, aire acondicionado,techumbre, entre otros.
B12: 8.1 | C12: Ampliacion de capacidad Oficinas de Antofagasta | D12: Locales Afta | G12: STN | H12: 45870 | I12: 45991 | K12: 0.25 | L12: =IF($H12>TODAY(),0,IF(OR($I12="Eliminada",$I12="En Revision"),$I12,IF($I12<>"Eliminada",IF($I12>TODAY(),(TODAY()-$H12)/($I12-$H12),1),0))) -> 1 | Q12: Mobiliario: 1.Modificacion Sala de Capacitacion 2.Modificacion Comedor 3.Modificacion Sala de Enlace | T12: Mobiliario: 1.Modificacion Sala de Capacitacion 2.Modificacion Comedor 3.Modificacion Sala de Enlace
B13: 9 | C13: Traslado de Personal | D13: Viggo | G13: BHP | H13: 45712 | I13: 45971 | J13: Pendiente | K13: 1 | L13: =IF($H13>TODAY(),0,IF(OR($I13="Eliminada",$I13="En Revision"),$I13,IF($I13<>"Eliminada",IF($I13>TODAY(),(TODAY()-$H13)/($I13-$H13),1),0))) -> 1 | M13: =IF(K13=1,"Terminada",IF(K13<L13,"Atrasado", "A Tiempo")) -> Terminada | N13: =IF($M13="Eliminada",-2,IF($M13="Terminada",2,IF($M13="A Tiempo",1,IF($M13="En Revision",0,-1)))) -> 2 | O13: Identificar los requerimientos de agendamiento | Q13: Se debe informar a los trabajadores la forma de agendamiento en MEL | R13: Agendamiento de Buses de Personal de STN | S13: Agendamiento de Buses de Personal de STN | T13: Se debe informar a los trabajadores la forma de agendamiento en MEL
B14: 10 | C14: GPS y Somnolencia | D14: Samtech | G14: STN | H14: 45870 | I14: 45976 | J14: Firmado | K14: 1 | L14: =IF($H14>TODAY(),0,IF(OR($I14="Eliminada",$I14="En Revision"),$I14,IF($I14<>"Eliminada",IF($I14>TODAY(),(TODAY()-$H14)/($I14-$H14),1),0))) -> 1 | M14: =IF(K14=1,"Terminada",IF(K14<L14,"Atrasado", "A Tiempo")) -> Terminada | N14: =IF($M14="Eliminada",-2,IF($M14="Terminada",2,IF($M14="A Tiempo",1,IF($M14="En Revision",0,-1)))) -> 2 | Q14: En programacion de unidades 27.10 al 10.11.2025 | R14: En camionetas, administrado por Tattersall En camiones, administrado por STN | S14: En camionetas, administrado por Tattersall En camiones, administrado por STN | T14: En programacion de unidades 27.10 al 10.11.2025
B15: 11 | C15: Gestion de Comunicaciones Radios Portatiles - Interexport | D15: Interexport | G15: BHP | H15: 45870 | I15: 45981 | J15: Firmado | K15: 1 | L15: =IF($H15>TODAY(),0,IF(OR($I15="Eliminada",$I15="En Revision"),$I15,IF($I15<>"Eliminada",IF($I15>TODAY(),(TODAY()-$H15)/($I15-$H15),1),0))) -> 1 | M15: =IF(K15=1,"Terminada",IF(K15<L15,"Atrasado", "A Tiempo")) -> Terminada | N15: =IF($M15="Eliminada",-2,IF($M15="Terminada",2,IF($M15="A Tiempo",1,IF($M15="En Revision",0,-1)))) -> 2 | O15: Identificar los requerimientos de agendamiento | P15: Se debe gestionar contrato con Interexport por uso de frecuencia | Q15: Contrato Firmado 24.10.2025, en espera de agenda de programación. | R15: Radios OK. | S15: Radios Programadas con Interexport, en algunos vehiculos aun falta la instalacion (Plataforma y Camion de Lavado de MV). | T15: Contrato Firmado 24.10.2025, en programación desde el 28.10.2025
B16: 12 | C16: Inatrans (Empresa Preferente) | D16: Inatrans | G16: STN | H16: 45992 | I16: 45996 | J16: Pendiente | K16: 1 | L16: =IF($H16>TODAY(),0,IF(OR($I16="Eliminada",$I16="En Revision"),$I16,IF($I16<>"Eliminada",IF($I16>TODAY(),(TODAY()-$H16)/($I16-$H16),1),0))) -> 1 | M16: =IF(K16=1,"Terminada",IF(K16<L16,"Atrasado", "A Tiempo")) -> Terminada | N16: =IF($M16="Eliminada",-2,IF($M16="Terminada",2,IF($M16="A Tiempo",1,IF($M16="En Revision",0,-1)))) -> 2
B17: 13 | C17: Estudio de Somnolencia Conductores | D17: Northealth | G17: STN | H17: 45992 | I17: 46006 | J17: Pendiente | K17: 1 | L17: =IF($H17>TODAY(),0,IF(OR($I17="Eliminada",$I17="En Revision"),$I17,IF($I17<>"Eliminada",IF($I17>TODAY(),(TODAY()-$H17)/($I17-$H17),1),0))) -> 1 | M17: =IF(K17=1,"Terminada",IF(K17<L17,"Atrasado", "A Tiempo")) -> Terminada
C18: Total | K18: =AVERAGE(K4:K16) -> 0.93076923 | L18: =AVERAGE(L4:L16) -> 1 | M18: =IF(K18=1,"Terminada",IF(K18<L18,"Atrasado", "A Tiempo")) -> Atrasado | N18: =IF($M18="Eliminada",-2,IF($M18="Terminada",2,IF($M18="A Tiempo",1,IF($M18="En Revision",0,-1)))) -> -1

Sheet EPP-Ropa
A1: Ítem | B1: Meta Anual Contrato | C1: Meta Contrato (Mes) | D1: Stock Mínimo (Seguridad) | E1: Stock Bodega Faena | F1: Stock Of. Antofagasta | G1: STOCK TOTAL DISPONIBLE | H1: Entregado: Admininistración (7 Pers.) | I1: Entregado: Dx y Cables (24 Pers.) | J1: Entregado: EEPP (12 Pers.) | K1: Entregado: Salas y SSEE (15 Pers.) | L1: Entregado: Transmisión (10 Pers.) | M1: Total Entregado al 28-12-25 | N1: Stock Disponible al 28-12-25 | O1: ESTADO / ALERTA
A2: Bloqueador Solar | B2: 765 | C2: =+B2/12 -> 63.75 | D2: 16 | E2: 320 | F2: 100 | G2: =SUM(E2:F2) -> 420 | H2: 1 | I2: 24 | J2: 12 | K2: 15 | L2: 10 | M2: =SUM(H2:L2) -> 62 | N2: =+G2-M2 -> 358 | O2: =IF(N2<=D2, "🚨 STOCK CRÍTICO", IF(AND(C2>0, N2>C2), "⚠️ EXCESO DE INVENTARIO", IF(N2<=(D2*1.8), "📦 REPONER", "✅ OK"))) -> ⚠️ EXCESO DE INVENTARIO
A3: Barbiquejo | B3: 765 | C3: =+B3/12 -> 63.75 | D3: 16 | E3: 300 | F3: 100 | G3: =SUM(E3:F3) -> 400 | H3: 0 | I3: 24 | J3: 12 | K3: 15 | L3: 10 | M3: =SUM(H3:L3) -> 61 | N3: =+G3-M3 -> 339 | O3: =IF(N3<=D3, "🚨 STOCK CRÍTICO", IF(AND(C3>0, N3>C3), "⚠️ EXCESO DE INVENTARIO", IF(N3<=(D3*1.8), "📦 REPONER", "✅ OK"))) -> ⚠️ EXCESO DE INVENTARIO
A4: Respirador medio rostro | B4: 735 | C4: =+B4/12 -> 61.25 | D4: 15 | E4: 75 | F4: 0 | G4: =SUM(E4:F4) -> 75 | H4: 2 | I4: 24 | J4: 12 | K4: 15 | L4: 10 | M4: =SUM(H4:L4) -> 63 | N4: =+G4-M4 -> 12 | O4: =IF(N4<=D4, "🚨 STOCK CRÍTICO", IF(AND(C4>0, N4>C4), "⚠️ EXCESO DE INVENTARIO", IF(N4<=(D4*1.8), "📦 REPONER", "✅ OK"))) -> 🚨 STOCK CRÍTICO
A5: Guantes Cabritilla | B5: 576 | C5: =+B5/12 -> 48 | D5: 12 | E5: 200 | F5: 1350 | G5: =SUM(E5:F5) -> 1550 | H5: 2 | I5: 48 | J5: 24 | K5: 30 | L5: 20 | M5: =SUM(H5:L5) -> 124 | N5: =+G5-M5 -> 1426 | O5: =IF(N5<=D5, "🚨 STOCK CRÍTICO", IF(AND(C5>0, N5>C5), "⚠️ EXCESO DE INVENTARIO", IF(N5<=(D5*1.8), "📦 REPONER", "✅ OK"))) -> ⚠️ EXCESO DE INVENTARIO
A6: Camisa Ignífuga | B6: 153 | C6: =+B6/12 -> 12.75 | D6: 8 | E6: 200 | F6: 127 | G6: =SUM(E6:F6) -> 327 | H6: 6 | I6: 72 | J6: 36 | K6: 45 | L6: 30 | M6: =SUM(H6:L6) -> 189 | N6: =+G6-M6 -> 138 | O6: =IF(N6<=D6, "🚨 STOCK CRÍTICO", IF(AND(C6>0, N6>C6), "⚠️ EXCESO DE INVENTARIO", IF(N6<=(D6*1.8), "📦 REPONER", "✅ OK"))) -> ⚠️ EXCESO DE INVENTARIO
A7: Geólogo (Chaleco) | B7: 336 | C7: =+B7/12 -> 28 | D7: 7 | E7: 100 | F7: 48 | G7: =SUM(E7:F7) -> 148 | H7: 2 | I7: 24 | J7: 12 | K7: 15 | L7: 10 | M7: =SUM(H7:L7) -> 63 | N7: =+G7-M7 -> 85 | O7: =IF(N7<=D7, "🚨 STOCK CRÍTICO", IF(AND(C7>0, N7>C7), "⚠️ EXCESO DE INVENTARIO", IF(N7<=(D7*1.8), "📦 REPONER", "✅ OK"))) -> ⚠️ EXCESO DE INVENTARIO
A8: Audífonos | B8: 357 | C8: =+B8/12 -> 29.75 | D8: 8 | E8: 75 | F8: 0 | G8: =SUM(E8:F8) -> 75 | H8: 2 | I8: 24 | J8: 12 | K8: 15 | L8: 10 | M8: =SUM(H8:L8) -> 63 | N8: =+G8-M8 -> 12 | O8: =IF(N8<=D8, "🚨 STOCK CRÍTICO", IF(AND(C8>0, N8>C8), "⚠️ EXCESO DE INVENTARIO", IF(N8<=(D8*1.8), "📦 REPONER", "✅ OK"))) -> 📦 REPONER
A9: Zapatos Dieléctricos | B9: 306 | C9: =+B9/12 -> 25.5 | D9: 7 | E9: 78 | F9: 30 | G9: =SUM(E9:F9) -> 108 | H9: 2 | I9: 24 | J9: 12 | K9: 15 | L9: 10 | M9: =SUM(H9:L9) -> 63 | N9: =+G9-M9 -> 45 | O9: =IF(N9<=D9, "🚨 STOCK CRÍTICO", IF(AND(C9>0, N9>C9), "⚠️ EXCESO DE INVENTARIO", IF(N9<=(D9*1.8), "📦 REPONER", "✅ OK"))) -> ⚠️ EXCESO DE INVENTARIO
A10: Lentes | B10: 222 | C10: =+B10/12 -> 18.5 | D10: 5 | E10: 300 | F10: 1100 | G10: =SUM(E10:F10) -> 1400 | H10: 2 | I10: 48 | J10: 24 | K10: 30 | L10: 20 | M10: =SUM(H10:L10) -> 124 | N10: =+G10-M10 -> 1276 | O10: =IF(N10<=D10, "🚨 STOCK CRÍTICO", IF(AND(C10>0, N10>C10), "⚠️ EXCESO DE INVENTARIO", IF(N10<=(D10*1.8), "📦 REPONER", "✅ OK"))) -> ⚠️ EXCESO DE INVENTARIO
A11: Casco | B11: 153 | C11: =+B11/12 -> 12.75 | D11: 4 | E11: 65 | F11: 22 | G11: =SUM(E11:F11) -> 87 | H11: 2 | I11: 24 | J11: 12 | K11: 15 | L11: 10 | M11: =SUM(H11:L11) -> 63 | N11: =+G11-M11 -> 24 | O11: =IF(N11<=D11, "🚨 STOCK CRÍTICO", IF(AND(C11>0, N11>C11), "⚠️ EXCESO DE INVENTARIO", IF(N11<=(D11*1.8), "📦 REPONER", "✅ OK"))) -> ⚠️ EXCESO DE INVENTARIO
A12: Pantalón Ignífugo | B12: 153 | C12: =+B12/12 -> 12.75 | D12: 4 | E12: 152 | F12: 155 | G12: =SUM(E12:F12) -> 307 | H12: 6 | I12: 48 | J12: 24 | K12: 30 | L12: 20 | M12: =SUM(H12:L12) -> 128 | N12: =+G12-M12 -> 179 | O12: =IF(N12<=D12, "🚨 STOCK CRÍTICO", IF(AND(C12>0, N12>C12), "⚠️ EXCESO DE INVENTARIO", IF(N12<=(D12*1.8), "📦 REPONER", "✅ OK"))) -> ⚠️ EXCESO DE INVENTARIO
A13: Chaqueta Ignífuga | B13: 153 | C13: =+B13/12 -> 12.75 | D13: 4 | E13: 34 | F13: 49 | G13: =SUM(E13:F13) -> 83 | H13: 2 | I13: 24 | J13: 12 | K13: 15 | L13: 10 | M13: =SUM(H13:L13) -> 63 | N13: =+G13-M13 -> 20 | O13: =IF(N13<=D13, "🚨 STOCK CRÍTICO", IF(AND(C13>0, N13>C13), "⚠️ EXCESO DE INVENTARIO", IF(N13<=(D13*1.8), "📦 REPONER", "✅ OK"))) -> ⚠️ EXCESO DE INVENTARIO
... A18: Botas agua | B18: 0 | C18: =+B18/12 -> 0 | D18: 22 | E18: 0 | F18: 0 | G18: =SUM(E18:F18) -> 0 | H18: 0 | I18: 0 | J18: 0 | K18: 0 | L18: 0 | M18: =SUM(H18:L18) -> 0 | N18: =+G18-M18 -> 0 | O18: =IF(N18<=D18, "🚨 STOCK CRÍTICO", IF(AND(C18>0, N18>C18), "⚠️ EXCESO DE INVENTARIO", IF(N18<=(D18*1.8), "📦 REPONER", "✅ OK"))) -> 🚨 STOCK CRÍTICO
A19: Polerón Ignífugo | B19: 0 | C19: 0 | D19: 10 | E19: 102 | F19: 0 | G19: =SUM(E19:F19) -> 102 | H19: 3 | I19: 24 | J19: 12 | K19: 15 | L19: 10 | M19: =SUM(H19:L19) -> 64 | N19: =+G19-M19 -> 38 | O19: =IF(N19<=D19, "🚨 STOCK CRÍTICO", IF(AND(C19>0, N19>C19), "⚠️ EXCESO DE INVENTARIO", IF(N19<=(D19*1.8), "📦 REPONER", "✅ OK"))) -> ✅ OK
A20: Primera Capa | B20: 0 | C20: 0 | D20: 20 | E20: 200 | F20: 0 | G20: =SUM(E20:F20) -> 200 | H20: 0 | I20: 0 | J20: 0 | K20: 0 | L20: 0 | M20: =SUM(H20:L20) -> 0 | N20: =+G20-M20 -> 200 | O20: =IF(N20<=D20, "🚨 STOCK CRÍTICO", IF(AND(C20>0, N20>C20), "⚠️ EXCESO DE INVENTARIO", IF(N20<=(D20*1.8), "📦 REPONER", "✅ OK"))) -> ✅ OK
A21: Legionario Ignífugo | B21: 0 | C21: 0 | D21: 10 | E21: 70 | F21: 0 | G21: =SUM(E21:F21) -> 70 | H21: 0 | I21: 24 | J21: 12 | K21: 15 | L21: 10 | M21: =SUM(H21:L21) -> 61 | N21: =+G21-M21 -> 9 | O21: =IF(N21<=D21, "🚨 STOCK CRÍTICO", IF(AND(C21>0, N21>C21), "⚠️ EXCESO DE INVENTARIO", IF(N21<=(D21*1.8), "📦 REPONER", "✅ OK"))) -> 🚨 STOCK CRÍTICO
A22: Balaclava Ignífuga | B22: 0 | C22: 0 | D22: 10 | E22: 75 | F22: 0 | G22: =SUM(E22:F22) -> 75 | H22: 0 | I22: 24 | J22: 12 | K22: 15 | L22: 10 | M22: =SUM(H22:L22) -> 61 | N22: =+G22-M22 -> 14 | O22: =IF(N22<=D22, "🚨 STOCK CRÍTICO", IF(AND(C22>0, N22>C22), "⚠️ EXCESO DE INVENTARIO", IF(N22<=(D22*1.8), "📦 REPONER", "✅ OK"))) -> 📦 REPONER
A23: Overol Ignífugo | B23: 0 | C23: 0 | D23: 10 | E23: 66 | F23: 0 | G23: =SUM(E23:F23) -> 66 | H23: 0 | I23: 14 | J23: 0 | K23: 0 | L23: 6 | M23: =SUM(H23:L23) -> 20 | N23: =+G23-M23 -> 46 | O23: =IF(N23<=D23, "🚨 STOCK CRÍTICO", IF(AND(C23>0, N23>C23), "⚠️ EXCESO DE INVENTARIO", IF(N23<=(D23*1.8), "📦 REPONER", "✅ OK"))) -> ✅ OK
A24: Buzo Tivek (Desechable) | B24: 0 | C24: 0 | D24: 30 | E24: 300 | F24: 0 | G24: =SUM(E24:F24) -> 300 | H24: 0 | I24: 0 | J24: 0 | K24: 0 | L24: 0 | M24: =SUM(H24:L24) -> 0 | N24: =+G24-M24 -> 300 | O24: =IF(N24<=D24, "🚨 STOCK CRÍTICO", IF(AND(C24>0, N24>C24), "⚠️ EXCESO DE INVENTARIO", IF(N24<=(D24*1.8), "📦 REPONER", "✅ OK"))) -> ✅ OK
A25: Bolso EEPP y Ropa Sucia | B25: 0 | C25: 0 | D25: 15 | E25: 150 | F25: 0 | G25: =SUM(E25:F25) -> 150 | H25: 0 | I25: 48 | J25: 24 | K25: 30 | L25: 20 | M25: =SUM(H25:L25) -> 122 | N25: =+G25-M25 -> 28 | O25: =IF(N25<=D25, "🚨 STOCK CRÍTICO", IF(AND(C25>0, N25>C25), "⚠️ EXCESO DE INVENTARIO", IF(N25<=(D25*1.8), "📦 REPONER", "✅ OK"))) -> ✅ OK
A26: Protector Solar Labial | B26: 0 | C26: 0 | D26: 10 | E26: 100 | F26: 0 | G26: =SUM(E26:F26) -> 100 | H26: 0 | I26: 24 | J26: 12 | K26: 15 | L26: 10 | M26: =SUM(H26:L26) -> 61 | N26: =+G26-M26 -> 39 | O26: =IF(N26<=D26, "🚨 STOCK CRÍTICO", IF(AND(C26>0, N26>C26), "⚠️ EXCESO DE INVENTARIO", IF(N26<=(D26*1.8), "📦 REPONER", "✅ OK"))) -> ✅ OK
A27: Candado Rojo | B27: 0 | C27: 0 | D27: 5 | E27: 40 | F27: 0 | G27: =SUM(E27:F27) -> 40 | H27: 0 | I27: 2 | J27: 2 | K27: 2 | L27: 2 | M27: =SUM(H27:L27) -> 8 | N27: =+G27-M27 -> 32 | O27: =IF(N27<=D27, "🚨 STOCK CRÍTICO", IF(AND(C27>0, N27>C27), "⚠️ EXCESO DE INVENTARIO", IF(N27<=(D27*1.8), "📦 REPONER", "✅ OK"))) -> ✅ OK
A28: Candado Naranja | B28: 0 | C28: 0 | D28: 10 | E28: 80 | F28: 0 | G28: =SUM(E28:F28) -> 80 | H28: 0 | I28: 24 | J28: 12 | K28: 15 | L28: 10 | M28: =SUM(H28:L28) -> 61 | N28: =+G28-M28 -> 19 | O28: =IF(N28<=D28, "🚨 STOCK CRÍTICO", IF(AND(C28>0, N28>C28), "⚠️ EXCESO DE INVENTARIO", IF(N28<=(D28*1.8), "📦 REPONER", "✅ OK"))) -> ✅ OK
A29: Pinza Bloqueo | B29: 0 | C29: 0 | D29: 10 | E29: 80 | F29: 0 | G29: =SUM(E29:F29) -> 80 | H29: 0 | I29: 24 | J29: 12 | K29: 15 | L29: 10 | M29: =SUM(H29:L29) -> 61 | N29: =+G29-M29 -> 19 | O29: =IF(N29<=D29, "🚨 STOCK CRÍTICO", IF(AND(C29>0, N29>C29), "⚠️ EXCESO DE INVENTARIO", IF(N29<=(D29*1.8), "📦 REPONER", "✅ OK"))) -> ✅ OK
A30: Cono Naranja | B30: 0 | C30: 0 | D30: 30 | E30: 300 | F30: 0 | G30: =SUM(E30:F30) -> 300 | H30: 0 | I30: 0 | J30: 0 | K30: 0 | L30: 0 | M30: =SUM(H30:L30) -> 0 | N30: =+G30-M30 -> 300 | O30: =IF(N30<=D30, "🚨 STOCK CRÍTICO", IF(AND(C30>0, N30>C30), "⚠️ EXCESO DE INVENTARIO", IF(N30<=(D30*1.8), "📦 REPONER", "✅ OK"))) -> ✅ OK
... A48: Bolso porta SPDC | B48: 0 | C48: 0 | D48: 5 | E48: 50 | F48: 0 | G48: =SUM(E48:F48) -> 50 | H48: 0 | I48: 14 | J48: 0 | K48: 0 | L48: 6 | M48: =SUM(H48:L48) -> 20 | N48: =+G48-M48 -> 30 | O48: =IF(N48<=D48, "🚨 STOCK CRÍTICO", IF(AND(C48>0, N48>C48), "⚠️ EXCESO DE INVENTARIO", IF(N48<=(D48*1.8), "📦 REPONER", "✅ OK"))) -> ✅ OK

Sheet Proceso Vehículos
C1: Claudio Cajas
I2: 8 Mínimo | N2: 12 | AF2: Rev 22.08.25 | AG2: Rev. 08.09.25 | BE2: CEIM
B3: ID | C3: Descripción Vehículo | D3: Nombre Equipo | E3: Especificacion Equipamiento | F3: Patente | G3: Administración Equipo | H3: Especificación Unidad Movil | I3: ECAS | J3: Radio Base | K3: N° Radio | L3: Instalacion GPS+Somnolencia | M3: TPMS | N3: Supresor de Incendios | O3: Certificador / Verificador | P3: Fecha 1ra Presentación Certificación | Q3: Fecha 2da Presentación Certificación | R3: Ubicación Actual | S3: Solicitud de Sellos | T3: Status Sello | U3: Detalle / Última Novedad | V3: Sello | W3: PortaEscala | X3: Cupula | Y3: Fecha límite | Z3: Fecha Entrega PESCO | AA3: Check Documental Certificación (N°) | AB3: Check Documental Certificación (N°) | AC3: N° | AD3: Días Faltantes | AE3: Ingreso Proyectado al Contrato | AF3: Fecha Entrega | AG3: Fecha Entrega | AH3: % Real | AI3: % Esperado | AJ3: Estado | AK3: Semáforo | AL3: Estado Implementación | AM3: Observaciones 29.11.2025 | AN3: Observaciones 03.12.2025 | AO3: Fecha Compromiso Equipo Habilitado en Faena | AP3: Comentarios 15.12.2025 | AQ3: Comentarios 12.12.2025 | AR3: Comentarios 10.12.25 | AS3: 05.12.2025 | AT3: Fecha Subida MEL | AU3: Comentarios | AV3: Observaciones 27-08 | AW3: Observaciones 08.09.2025 | AX3: Observaciones 24.10.2025 | AY3: Observaciones 30.10.2025 | AZ3: Observaciones 03.11.2025 | BA3: Observaciones Semana 8 | BB3: Observaciones Semana 9 | BC3: Observaciones Semana 10 | BE3: Avance Unitario | BF3: % Avance | BG3: Empresa Certificadora | BH3: Fecha Certificación | BI3: Patente Original Programada
A4: P1 | B4: 1 | C4: Camión Enrolla Cable | D4: Camión Enrolla Cable | E4: Enrrollador CRH 450 | F4: VGDY 51 | G4: Distribución y Cables | H4: Scania P410 B6x4 | I4: Operativo | J4: Instalada | K4: 471CAV1112 | L4: Instalado | M4: Instalado | N4: Instalado | O4: VIAL | P4: 45986 | Q4: NA | R4: MEL | S4: Listo | T4: Aprobado | U4: Programada subida a faena el día de hoy 01.12.25 | V4: Amarillo/ Naranjo | Y4: 45971 | Z4: 45963 | AC4: 1 | AD4: =IF(AJ4="Terminada",0,+Y4-$AT$1) -> 45971 | AE4: 45992 | AF4: 45926 | AG4: 45926 | AH4: 0.98 | AI4: =IF($AT4>TODAY(),0,IF(OR($Y4="Eliminada",$Y4="En Revision"),$Y4,IF($Y4<>"Eliminada",IF($Y4>TODAY(),(TODAY()-$AT4)/($Y4-$AT4),1),0))) -> 1 | AJ4: =IF(AH4=1,"Terminada",IF(AH4<AI4,"Atrasado", "A Tiempo")) -> Atrasado | AK4: =IF($AJ4="Eliminada",-2,IF($AJ4="Terminada",2,IF($AJ4="A Tiempo",1,IF($AJ4="En Revision",0,-1)))) -> -1 | AL4: 0.8 | AM4: Inicio de Montaje, Linea de Producción 11.07.2025 | AN4: Camion Disponible para cambio de sello (Amarillo), lo puede operar Juan Tabilo, Sebastian Escalante y Nilson Rodriguez (Autorizados Ruta), se actualiza conduccion mina. Actualizacion ECAS 04-12-2025 Sello Amarillo 05-12-2025 | AO4: 46003 | AP4: Equipo Habilitado en MEL, con ingreso Mina desde el 12.12.2025, Operadores N. Rodriguez, V. Salas, J. Tabilo, D. Ortiz | AQ4: Equipo Habilitado en MEL, con ingreso Mina desde el 12.12.2025, Operadores N. Rodriguez, V. Salas, J. Tabilo, D. Ortiz | AR4: 11.12.25 tiene fecha para sello amarillo | AS4: Equipo requiere modificaciones de faena, instalacion de letrero mina. Bajada de Faena 08.12.2025 | AT4: 45993 | AU4: Camion en Planta de Pesco, este ultimo no ha informado el avance de FMA en la unidad CRH450. Verificar que el proveedor lo pueda reciibir sabado 06.12.25 para bajrlo y no perder el transporte de cable en faena (mediante escolta) | AV4: Se debe incluir Radio Base. | AW4: Se solicitaron 12 unidades de radio base para vehículos. Vehículo a la espera de revisión de CEIM en instalaciones de PESCO | AX4: Camion en estado de Inscripcion, Facturado 12.10, Traslado programado en periodo 27 al 30.10.2025 a Antofagasta. Se instalara Samtech en Stgo, Radio Base y CAS en Antofagasta. | AY4: Camion en estado de Inscripcion, Facturado 12.10, Traslado programado en periodo 27 al 30.10.2025 a Antofagasta. Se instalara Samtech en Stgo, Radio Base y CAS en Antofagasta. | AZ4: Instalación de GPS y sistema de somnolencia 07.11.25 Radio Base 07.11.25 ECAS 09.11.25
A5: P1 | B5: 2 | C5: Camión Pluma Articulada | D5: Camión Grúa (Pluma) | E5: HIAB 352 E8 | F5: VBHY 89 | G5: Distribución y Cables | H5: Scania P410 B6x4 | I5: Actualizar ECAS en MEL | J5: Instalada | K5: 471CAV1129 | L5: Instalado | M5: Instalado | N5: Instalado | O5: CEIM | P5: 45980 | Q5: NA | R5: MEL | S5: Listo | T5: Aprobado | U5: A planificar subida | V5: Amarillo/ Naranjo | Y5: 45971 | Z5: 45898 | AC5: 1 | AD5: =IF(AJ5="Terminada",0,+Y5-$AT$1) -> 45971 | AE5: 45992 | AF5: 45898 | AG5: 45898 | AH5: 0.97 | AI5: =IF($AT5>TODAY(),0,IF(OR($Y5="Eliminada",$Y5="En Revision"),$Y5,IF($Y5<>"Eliminada",IF($Y5>TODAY(),(TODAY()-$AT5)/($Y5-$AT5),1),0))) -> 1 | AJ5: =IF(AH5=1,"Terminada",IF(AH5<AI5,"Atrasado", "A Tiempo")) -> Atrasado | AK5: =IF($AJ5="Eliminada",-2,IF($AJ5="Terminada",2,IF($AJ5="A Tiempo",1,IF($AJ5="En Revision",0,-1)))) -> -1 | AM5: Inicio de Montaje, Linea de Producción 11.07.2025 | AN5: Camión Grua Disponible para subir, en actualización Licencia para operar Grua. Documentacion priorizada para Sesbatian Escalnte y Victor Salas, A confirmar subida por Ruta. | AO5: 46007 | AP5: 1.- Pendiente Actualizacion de ECAS 2.- Validar equipo para presentacion en MEL 3.- Trasladado a MEL 14.12.2025 | AQ5: 1. Actualizar ECAS 2. Actualizar Sello Amarillo 3. Licencia Juan Tabilo TB, Turno A Victor Salas Traslado V. Salas en Bus 13.12 | 21:00 HRS Citar 03 personas 14.12.2025 Carga de Camion | AR5: 10.12.25 se instala porta neumatico de repuesto. | AS5: Camión Grua Disponible para subir, en actualización Licencia para operar Grua En revisión de frecuencia. | AT5: 45995 | AU5: Camion en Planta, la Pluma ya se encuentra montada, se enviara a Carrozar (Instalacion de Kit Minero) | AW5: Vehículo a la espera de revisión de CEIM en instalaciones de PESCO | AX5: Trabajando sobre las brechas del informe de inspección, Programar Montaje de Radio Base y ECAS en la unidad Semana 27 al 30.10.2025 | AY5: Trabajando sobre las brechas del informe de inspección, Programar Montaje de Radio Base y ECAS en la unidad Semana 27 al 30.10.2025 | AZ5: Instalación de GPS y sistema de somnolencia 04.11.25 Radio Base 05.11.25 ECAS 06.11.25
B6: 3 | C6: Camión Alza-Hombre | D6: Hidroelevador (Alza Hombre) | E6: ALTEC A77T | F6: Sin patente, camión en construcción | G6: Distribución y Cables | H6: Scania P410 B6x4 | I6: NA | J6: 45987 | K6: Por confirmar | L6: Instalado | M6: Instalado | N6: Programado | O6: CEIM | P6: 46020 | R6: PESCO Santiago | S6: 46028 | T6: 46028 | U6: Camión en construcción | V6: Naranjo | Y6: 46027 | Z6: 46013 | AC6: 1 | AD6: =IF(AJ6="Terminada",0,+Y6-$AT$1) -> 46027 | AE6: 46031 | AF6: 45982 | AG6: 45982 | AH6: 0.8 | AI6: =IF($AT6>TODAY(),0,IF(OR($Y6="Eliminada",$Y6="En Revision"),$Y6,IF($Y6<>"Eliminada",IF($Y6>TODAY(),(TODAY()-$AT6)/($Y6-$AT6),1),0))) -> 1 | AJ6: =IF(AH6=1,"Terminada",IF(AH6<AI6,"Atrasado", "A Tiempo")) -> Atrasado | AK6: =IF($AJ6="Eliminada",-2,IF($AJ6="Terminada",2,IF($AJ6="A Tiempo",1,IF($AJ6="En Revision",0,-1)))) -> -1 | AM6: Inicio de Montaje, Linea de Producción 11.07.2025 | AN6: En montaje, revision el 08.12.2025 en Santiago | AO6: 46031 | AP6: Camion en Montaje, ya tiene TPMS, GPS, Somnolencia, falta inscripcion y pruebas de operatividad del equipo. Programar Visita CEIM 19.12.2025 (Certificacion) | AQ6: Camion en Montaje, ya tiene TPMS, GPS, Somnolencia, falta inscripcion y pruebas de operatividad del equipo. Programar Visita CEIM 19.12.2025 (Certificacion) | AR6: En montaje, revision el 10.12.2025 en Santiago | AS6: En montaje, revision el 09.12.2025 en Santiago | AT6: 45719 | AU6: En revision por visita a EEUU, validar el nivel de avance del equipo y la linea de tiempo definitiva. | AX6: En revision unidades STGG50 y VBHY 58 para la acreditacion en MEL | AY6: En revision unidades STGG50 (Excepción) y VBHY 58 (En coordinacion visita inspectiva) para la acreditacion en MEL | AZ6: En revision unidades STGG50 (Excepción) y VBHY 58 (En coordinacion visita inspectiva) para la acreditacion en MEL
A7: P1 | B7: 4 | C7: Camion Lavador Pitón Manual | D7: Lavador (Pitón Manual) | E7: ALTEC HLIW 1600 SKID | F7: VGDY 49 | G7: Distribución y Cables | H7: Scania P410 B6x4 | I7: NA | J7: 45986 | K7: 471CAV1126 | L7: Instalado | M7: Instalado | N7: 45984 | O7: VIAL | P7: 45987 | Q7: 45982 | R7: MEL | S7: Listo | T7: Aprobado | U7: Programada subida a faena el día de hoy 01.12.25 | V7: Naranjo | Y7: 45971 | Z7: 45959 | AC7: 1 | AD7: =IF(AJ7="Terminada",0,+Y7-$AT$1) -> 45971 | AE7: 45992 | AF7: 45926 | AG7: 45926 | AH7: 0.98 | AI7: =IF($AT7>TODAY(),0,IF(OR($Y7="Eliminada",$Y7="En Revision"),$Y7,IF($Y7<>"Eliminada",IF($Y7>TODAY(),(TODAY()-$AT7)/($Y7-$AT7),1),0))) -> 1 | AJ7: =IF(AH7=1,"Terminada",IF(AH7<AI7,"Atrasado", "A Tiempo")) -> Atrasado | AK7: =IF($AJ7="Eliminada",-2,IF($AJ7="Terminada",2,IF($AJ7="A Tiempo",1,IF($AJ7="En Revision",0,-1)))) -> -1 | AM7: Inicio de Montaje, Linea de Producción 11.07.2025 | AN7: Camion Disponible, lo puede operar Juan Tabilo, Sebastian Escalante y Nilson Rodriguez (Autorizados Ruta), se actualiza conduccion mina. | AO7: 45993 | AP7: Camion Operativo, utilizado de Apoyo en Lavado de SSEE Coloso (15.12.2025) Camión fallo el 15.12.25 Actualmente en PESCO y se proyecta salida 16.12.25 | AQ7: Camion Operativo | AR7: Camion Operativo en MEL | AS7: Camion Operativo en MEL | AT7: 45992 | AU7: Equipo HIW1600 en Taller de PESCO. Camion de Lavado | AX7: Equipo en revision por inscricpion, sin emision de patente aun (se debe instalar sistema GPS y somnolencia Samtech) | AY7: En Stgo, instalacion de GPS y Sistema de Somnolencia 30.10 | AZ7: Sistema de somnolencia 06.11.25
B8: 5 | C8: Camión Aljibe 15 m3 - Scania P410B 6x4 | D8: Camión Aljibe 15 m3 | E8: ALJIBE 15 M3 | F8: VBHY 90 | G8: Transmisión | H8: Scania P410 B6x4 | I8: NA | J8: 45988 | K8: 471CAV1111 | L8: Instalado | M8: Instalado | N8: 45985 | O8: VIAL | P8: 45973 | Q8: 45987 | R8: STN | S8: Listo | T8: Aprobado | U8: Falta Radio Base (se instala martes 15 hrs) y aprobación en plataforma (C.O). | V8: Naranjo | Y8: 45971 | Z8: 45898 | AC8: 1 | AD8: =IF(AJ8="Terminada",0,+Y8-$AT$1) -> 0 | AE8: 45992 | AF8: 45898 | AG8: 45898 | AH8: 1 | AI8: =IF($AT8>TODAY(),0,IF(OR($Y8="Eliminada",$Y8="En Revision"),$Y8,IF($Y8<>"Eliminada",IF($Y8>TODAY(),(TODAY()-$AT8)/($Y8-$AT8),1),0))) -> 1 | AJ8: =IF(AH8=1,"Terminada",IF(AH8<AI8,"Atrasado", "A Tiempo")) -> Terminada | AK8: =IF($AJ8="Eliminada",-2,IF($AJ8="Terminada",2,IF($AJ8="A Tiempo",1,IF($AJ8="En Revision",0,-1)))) -> 2 | AM8: Inicio de Montaje, Linea de Producción 11.07.2025 | AN8: Se levantaron las brechas deberia ser aprobado. | AO8: 46001 | AP8: Camion Operativo, está en Antofagasta a espera de coordinación de traslado a MEL | AQ8: Camion Operativo | AR8: Aprobado 09.12.25 Subida por programar | AS8: Camion Rechazado en Inspeccion de Sellos. Se debe cambiar el informe de mantenimiento del equipo. | Progaramado 09.12.2025, 15:00 hrs (Resp. 07.12.2025) | AT8: 46001 | AU8: Equipo llegado a planta, con estanque montado, se debe validar su recepcion y proceso de emision de informacion. | AW8: Vehículo a la espera de revisión de CEIM en instalaciones de PESCO | AX8: Trabajando sobre las brechas del informe de inspección, Instalación de GPS y sist. Somnolencia 29.10 Semana 27 al 30.10.2025 | AY8: Trabajando sobre las brechas del informe de inspección, Instalación de GPS y sist. Somnolencia 29.10 Semana 27 al 30.10.2025 | AZ8: Pendiente Radio Base. GPS y Sistema de Somnolencia OK | BE8: 13 de 15 | BF8: 0.86666667
B9: 6 | C9: Camión con plataforma | D9: Camión Plataforma | E9: ZEPRO Z20-150 | F9: VGDY 50 | G9: Equipos Primarios | H9: Scania P410 B6x4 | I9: NA | J9: 45989 | K9: 471CBH0749 | L9: Instalado | M9: Instalado | N9: Instalado | O9: VIAL | P9: 45973 | Q9: 45987 | R9: STN | S9: 46007 | T9: Pendiente | U9: Brechas: Certificado de Fatiga y Somnolencia (Crítico, revisar punto 3). Certificado GPS. Certificado de Cabina. Certificado de Mantenimiento de Torque (No encontrado en revisión ayer). Radio Base (Falta instalación física). | V9: Naranjo | Y9: 45971 | Z9: 45959 | AC9: 1 | AD9: =IF(AJ9="Terminada",0,+Y9-$AT$1) -> 45971 | AE9: 45992 | AF9: 45926 | AG9: 45926 | AH9: 0.96 | AI9: =IF($AT9>TODAY(),0,IF(OR($Y9="Eliminada",$Y9="En Revision"),$Y9,IF($Y9<>"Eliminada",IF($Y9>TODAY(),(TODAY()-$AT9)/($Y9-$AT9),1),0))) -> 1 | AJ9: =IF(AH9=1,"Terminada",IF(AH9<AI9,"Atrasado", "A Tiempo")) -> Atrasado | AK9: =IF($AJ9="Eliminada",-2,IF($AJ9="Terminada",2,IF($AJ9="A Tiempo",1,IF($AJ9="En Revision",0,-1)))) -> -1 | AM9: Inicio de Montaje, Linea de Producción 11.07.2025 | AN9: Se levantaron las brechas, pero la radio no esta transmistiendo se genero Ticket a Interexport | AO9: 46008 | AP9: Revision estado de Radio Base y Sincronizacion GPS Hora solicitada para revisión sello 17.12.2025 | AQ9: Revision estado de Radio Base y Sincronizacion GPS | AR9: Se levantaron las brechas, pero la radio no esta transmistiendo se genero Ticket a Interexport | AS9: Se levantaron las brechas, pero la radio no esta transmistiendo se genero Ticket a Interexport | AT9: 45993 | AX9: Equipo en revision por inscricpion, sin emision de patente aun (se debe instalar sistema GPS y somnolencia Samtech) | AY9: En Stgo, instalacion de GPS y Sistema de Somnolencia 30.10 | AZ9: Pendiente Radio Base. GPS y Sistema de Somnolencia OK
B10: 7 | C10: Man Lift | D10: TEUPEN TC89AJ | E10: TEUPEN TC89AJ | F10: NA | G10: Distribución y Cables | H10: NA | I10: NA | J10: NA | K10: NA | L10: NA | M10: NA | N10: NA | O10: CEIM | P10: 45980 | Q10: 45980 | R10: STN | S10: NA | T10: NA | U10: OK y se trasladara en el camión pluma | V10: No aplica | Y10: 45971 | Z10: 45898 | AC10: 1 | AD10: =IF(AJ10="Terminada",0,+Y10-$AT$1) -> 0 | AE10: 45992 | AF10: 45887 | AG10: 45887 | AH10: 1 | AI10: =IF($AT10>TODAY(),0,IF(OR($Y10="Eliminada",$Y10="En Revision"),$Y10,IF($Y10<>"Eliminada",IF($Y10>TODAY(),(TODAY()-$AT10)/($Y10-$AT10),1),0))) -> 0 | AJ10: =IF(AH10=1,"Terminada",IF(AH10<AI10,"Atrasado", "A Tiempo")) -> Terminada | AK10: =IF($AJ10="Eliminada",-2,IF($AJ10="Terminada",2,IF($AJ10="A Tiempo",1,IF($AJ10="En Revision",0,-1)))) -> 2 | AM10: Inicio de Montaje, Linea de Producción 11.07.2025 | AN10: Para programar subida. | AO10: 46007 | AP10: Equipo Operativo, en validacion de traslado con camion VBHY 89 ó VGDY 50 | AQ10: Equipo Operativo | AR10: Operativo, programar subida. | AS10: Operativo, programar subida. | AT10: A coordinar por tema logístico | AU10: Equipo en Planta PESCO Santiago, personal de | AW10: Equipo a la espera de revisión de CEIM en instalaciones de PESCO | AX10: Trabajando en las brechas del informe de inspección, Semana del 27 al 30.10.2025 | AY10: Trabajando en las brechas del informe de inspección, Semana del 27 al 30.10.2025 | AZ10: En levantamiento de brechas
B11: 8 | C11: Camion Lavador Pitón Remoto 2 | D11: Lavador (Pitón Remoto) 2 | E11: ALTEC HW145 (reacondicionado) | F11: KZGR 16 | G11: Transmisión | H11: Freightliner SD 108 | I11: NA | J11: Instalada | K11: 471CAV1134 | L11: Instalado | M11: Excepción | N11: NA | O11: VIAL | P11: 45989 | R11: KAUFMANN | S11: Listo | T11: Aprobado | U11: Brechas detectadas: TPMS, barandas de escalera, stickers y pernos. Lunes: Cerrar brechas mecánicas/TPMS. Martes: Ingreso a revisión. | V11: Naranjo | Y11: 45981 | Z11: 45976 | AC11: 1 | AD11: =IF(AJ11="Terminada",0,+Y11-$AT$1) -> 45981 | AE11: 45992 | AF11: 45929 | AG11: 45976 | AH11: 0.78 | AI11: =IF($AT11>TODAY(),0,IF(OR($Y11="Eliminada",$Y11="En Revision"),$Y11,IF($Y11<>"Eliminada",IF($Y11>TODAY(),(TODAY()-$AT11)/($Y11-$AT11),1),0))) -> 1 | AJ11: =IF(AH11=1,"Terminada",IF(AH11<AI11,"Atrasado", "A Tiempo")) -> Atrasado | AK11: =IF($AJ11="Eliminada",-2,IF($AJ11="Terminada",2,IF($AJ11="A Tiempo",1,IF($AJ11="En Revision",0,-1)))) -> -1 | AM11: Arriendo, equipo con solicitud de excepción | AN11: Camión en Levantamiento de Brechas en Taller de Kaufmann | AO11: 46013 | AP11: 16.12.25 a las 16:00 Hrs PESCO informará fecha de salida. Se estima viernes 19.12.25 | AQ11: Validar las funcionalidades del equipo, en revision de equipo para operar. | AR11: En Kaufmann por encedido de check engine | AS11: Equipo con Sello04.12.2025, para programacion de lavado la semana proxima. | AT11: 45992 | AU11: Inicio de Overhaul equipo KZGR 16, equipo en programacion con Spot. Emision de OC por parte de STN | AX11: Revisado este equipo, entrega por PESCO 15.11.2025 | AY11: Revisado este equipo, entrega por PESCO 15.11.2025 | AZ11: Equipo en mantenimiento
B12: 9 | D12: Lavador Manual (Plan de Accion) | E12: ALTEC HLIW 1600 SKID + Alzahombre Axion | F12: VBHY 58 | G12: Transmisión | H12: MAN TGS 18.330 | I12: NA | J12: 16-12-2025, 14:00 hrs | K12: 471CAV1130 | L12: Instalado | M12: 16-12-2025, 08:30 hrs | N12: NA | O12: CEIM | P12: 16-12-2025, horario PM (Sugerido 17:30 hrs) | R12: STN | S12: 46008 | T12: Pendiente | V12: Naranjo | AO12: 46014 | AP12: Habilitacion de Equipo sin Alzahombre, con esto se puede utilizar el equipo de manera anticipada. 17.12.2025. Asignación de sellos planificada para el 16.12.25 a las 17:00 Hrs | AQ12: Habilitacion de Equipo sin Alzahombre, con esto se puede utilizar el equipo de manera anticipada. | AR12: Stickes 15.12.2025 Armado de Carpeta Presentacion: 15.12.2025 | AS12: Camion en Traslado desde Chañaral a Antofagasta (05.12.20025), en programación instalacion de Aftermrket (TPMS) + GPS + Sistema de Fatiga y Somnolencia | Revisar Programacion de Radio Base | AU12: Se debe generar Gantt solicitada por Marco Rodriguez el 05.12.25 Se requiere certificacion de los operadores de la marca MAN. Se esta gestionando con PESCO.
B13: 10 | C13: Camion Lavador Pitón Remoto 1 (Reacondicionado) | D13: Piton Remoto | E13: ALTEC HW145 (reacondicionado) | F13: Sin patente, camión en construcción | G13: Transmisión | H13: Freightliner M2 106 Plus 6x6 | I13: NA | J13: Por confirmar | L13: 46014 | M13: 46020 | N13: NA | O13: VIAL | P13: No se ha solicitado | Q13: Pendiente | R13: Pendiente | T13: Pendiente | V13: Naranjo | Y13: 46017 | Z13: 46017 | AC13: 1 | AE13: 46055 | AG13: 46017 | AH13: 0.85 | AI13: =IF($AT13>TODAY(),0,IF(OR($Y13="Eliminada",$Y13="En Revision"),$Y13,IF($Y13<>"Eliminada",IF($Y13>TODAY(),(TODAY()-$AT13)/($Y13-$AT13),1),0))) -> 1 | AJ13: =IF(AH13=1,"Terminada",IF(AH13<AI13,"Atrasado", "A Tiempo")) -> Atrasado | AK13: =IF($AJ13="Eliminada",-2,IF($AJ13="Terminada",2,IF($AJ13="A Tiempo",1,IF($AJ13="En Revision",0,-1)))) -> -1 | AN13: Camión en Levantamiento de Brechas en Taller de Kaufmann | AO13: 46037 | AP13: Camion en Montaje, se instalara el equipamiento en Planta de PESCO en Stgo (GPS+Somnolencia + Ibutton+ TPMS) | AQ13: Camion en Montaje, se instalara el equipamiento en Planta de PESCO en Stgo (GPS+Somnolencia + Ibutton+ TPMS) | AR13: Proxima revision de montaje de equipo 10.12.2025 para plan de aceleración | AS13: Proxima revision de montaje de equipo 08.12.2025 para plan de aceleración | AT13: 46054 | AX13: En plazo de llegada desde EEUU , inicio de trabajos de planta en Santiago 03.11.2025 | AY13: En plazo de llegada desde EEUU , inicio de trabajos de planta en Santiago 03.11.2025, Llegada el 28.10.2025
B14: 11 | C14: Camion Lavador Pitón Remoto 2 (Reacondicionado) | D14: Arriendo PESCO RENTAL | E14: ALTEC HW145 (reacondicionado) | F14: Sin patente, camión en construcción | G14: Transmisión | H14: Freightliner M2 106 Plus 6x6 | I14: NA | J14: Por confirmar | L14: Por confirmar | M14: Pendiente | N14: Lo Requiere | O14: VIAL | P14: No se ha solicitado | Q14: Pendiente | R14: Pendiente | T14: Pendiente | V14: Naranjo | Y14: 46017 | Z14: 46017 | AC14: 1 | AE14: 46055 | AG14: 46017 | AH14: 0.85 | AI14: =IF($AT14>TODAY(),0,IF(OR($Y14="Eliminada",$Y14="En Revision"),$Y14,IF($Y14<>"Eliminada",IF($Y14>TODAY(),(TODAY()-$AT14)/($Y14-$AT14),1),0))) -> 1 | AJ14: =IF(AH14=1,"Terminada",IF(AH14<AI14,"Atrasado", "A Tiempo")) -> Atrasado | AK14: =IF($AJ14="Eliminada",-2,IF($AJ14="Terminada",2,IF($AJ14="A Tiempo",1,IF($AJ14="En Revision",0,-1)))) -> -1 | AO14: 46068 | AT14: 46054 | AX14: En plazo de llegada desde EEUU , inicio de trabajos de planta en Santiago 03.11.2025 | AY14: En plazo de llegada desde EEUU , inicio de trabajos de planta en Santiago 03.11.2025, Llegada el 28.10.2025
B15: 12 | C15: Camion Lavador Pitón Remoto 0 (Nuevo) | D15: Piton Remoto 2 | E15: ALTEC HW145 (new) | F15: Sin patente, camión en construcción | G15: Transmisión | H15: Freightliner M2 106 Plus 6x6 | I15: NA | J15: Por confirmar | L15: Por confirmar | M15: Pendiente | N15: Lo Requiere | O15: VIAL | P15: No se ha solicitado | Q15: Pendiente | R15: Pendiente | T15: Pendiente | V15: Naranjo | Y15: 46446 | Z15: 45992 | AC15: 1 | AD15: =IF(AJ15="Terminada",0,+Y15-$AT$1) -> 46446 | AE15: 46476 | AF15: 46724 | AG15: 46458 | AH15: 0.58 | AI15: =IF($AT15>TODAY(),0,IF(OR($Y15="Eliminada",$Y15="En Revision"),$Y15,IF($Y15<>"Eliminada",IF($Y15>TODAY(),(TODAY()-$AT15)/($Y15-$AT15),1),0))) -> 0.30662983 | AJ15: =IF(AH15=1,"Terminada",IF(AH15<AI15,"Atrasado", "A Tiempo")) -> A Tiempo | AK15: =IF($AJ15="Eliminada",-2,IF($AJ15="Terminada",2,IF($AJ15="A Tiempo",1,IF($AJ15="En Revision",0,-1)))) -> 1 | AM15: Arriendo, equipo con solicitud de excepción | AO15: 46476 | AT15: 46084 | AU15: Inicio de Overhaul equipo HYCZ 45, iniciado 18.08, se cerro acuerdo comercial por 175 MM | AX15: Llegada en Febrero-Marzo 2027 | AY15: Llegada en Febrero-Marzo 2027
B16: 8 | C16: Camion Lavador Pitón Remoto 1 | D16: Lavador (Pitón Remoto) | E16: ALTEC HW145 (reacondicionado) | F16: HYCZ 45 | G16: Transmisión | H16: Freightliner SD 108 | I16: NA | J16: Instalada | K16: 471CAV1130 | L16: Instalado | M16: Excepción | N16: NA | O16: VIAL | P16: 45988 | R16: Programada | S16: Agendado 04.22.2025 | T16: Levantamiento Brechas | U16: Brechas detectadas: TPMS, barandas de escalera, stickers y pernos. Lunes: Cerrar brechas mecánicas/TPMS. Martes: Ingreso a revisión. | V16: Naranjo | Y16: 45971 | Z16: 45960 | AC16: 1 | AD16: =IF(AJ16="Terminada",0,+Y16-$AT$1) -> 45971 | AE16: 45992 | AF16: 45929 | AG16: 45991 | AH16: 0.92 | AI16: =IF($AT16>TODAY(),0,IF(OR($Y16="Eliminada",$Y16="En Revision"),$Y16,IF($Y16<>"Eliminada",IF($Y16>TODAY(),(TODAY()-$AT16)/($Y16-$AT16),1),0))) -> 1 | AJ16: =IF(AH16=1,"Terminada",IF(AH16<AI16,"Atrasado", "A Tiempo")) -> Atrasado | AK16: =IF($AJ16="Eliminada",-2,IF($AJ16="Terminada",2,IF($AJ16="A Tiempo",1,IF($AJ16="En Revision",0,-1)))) -> -1 | AM16: Arriendo, equipo con solicitud de excepción | AN16: Camión en Levantamiento de Brechas en Taller de Kaufmann | AR16: Fuera de estandar | AS16: Proceso se finaliza el 04.12.2025, MEL indica que no habra excepcion por la antigüedad del equipo. | AT16: 45992 | AU16: Inicio de Overhaul equipo HYCZ 45, iniciado 18.08, se cerro acuerdo comercial por 175 MM | AX16: Revisado este equipo, entrega por PESCO 30.10.2025, en la semana del 03 al 10 se instalara sistema de GPS y Somnolencia | AY16: Revisado este equipo, entrega por PESCO 30.10.2025. | AZ16: Equipo recepcionado En pruebas Instalación de GPS y Sistema de Somnolencia 03.11.25
B17: 1 | C17: Camioneta 1 | D17: Camioneta | E17: Estandar Tattersall Mina | F17: VGLL 80 | G17: Distribución y Cables | H17: Toyota Hilux 2.4 MT TSS 4x4 | I17: Pendiente. En uso Bbosch | J17: Instalada | K17: 471CAV1135 | L17: Instalada | M17: Instalado | N17: NA | O17: NA | P17: 45986 | Q17: NA | R17: MEL | S17: 45974 | T17: Listo | U17: Pendiente ECAS y Sellos Amarillo / Rojo | V17: Amarillo/Rojo | W17: Si | Y17: 45945 | AC17: 1 | AE17: 45992 | AG17: 45945 | AH17: 1 | AI17: =IF($AT17>TODAY(),0,IF(OR($Y17="Eliminada",$Y17="En Revision"),$Y17,IF($Y17<>"Eliminada",IF($Y17>TODAY(),(TODAY()-$AT17)/($Y17-$AT17),1),0))) -> 1 | AJ17: =IF(AH17=1,"Terminada",IF(AH17<AI17,"Atrasado", "A Tiempo")) -> Terminada | AK17: =IF($AJ17="Eliminada",-2,IF($AJ17="Terminada",2,IF($AJ17="A Tiempo",1,IF($AJ17="En Revision",0,-1)))) -> 2 | AM17: Camioneta debe ser trasladada para validacion de sellos. Se presentara como Sello Rojo en MEL 02.12.2025 | AN17: Camioneta Operativa | AT17: 45989 | AY17: Proyectada Bajada de MEL 03.11.2025
B18: 2 | C18: Camioneta 2 | D18: Camioneta | E18: Estandar Tattersall Mina | F18: VGLL 83 | G18: Distribución y Cables | H18: Toyota Hilux 2.4 MT TSS 4x4 | I18: Operativo | J18: Instalada | K18: 471CAV1137 | L18: Instalada | M18: Instalado | N18: NA | O18: NA | P18: 45986 | Q18: NA | R18: MEL | S18: 45974 | T18: Listo | U18: Sello Rojo OK Pend. Amarillo | V18: Amarillo/Rojo | W18: Si | Y18: 45945 | AC18: 1 | AE18: 45992 | AG18: 45945 | AH18: 1 | AI18: =IF($AT18>TODAY(),0,IF(OR($Y18="Eliminada",$Y18="En Revision"),$Y18,IF($Y18<>"Eliminada",IF($Y18>TODAY(),(TODAY()-$AT18)/($Y18-$AT18),1),0))) -> 1 | AJ18: =IF(AH18=1,"Terminada",IF(AH18<AI18,"Atrasado", "A Tiempo")) -> Terminada | AK18: =IF($AJ18="Eliminada",-2,IF($AJ18="Terminada",2,IF($AJ18="A Tiempo",1,IF($AJ18="En Revision",0,-1)))) -> 2 | AM18: Camioneta puede ser manejada por Jeffrey Troncoso, el estara en turno de contingencia el 01.12.2025 | AN18: Camioneta Operativa | AT18: 45989 | AX18: Unidad en MEL, en coordinación traslado a Antofagasta para montaje Radio base y ECAS. (27 al 30.10) ECAS 03 al 10.11.2025 | AY18: Proyectada Bajada de MEL 03.11.2025
B19: 3 | C19: Camioneta 3 | D19: Camioneta | E19: Estandar Tattersall Mina | F19: VGLL 68 | G19: Salas y Subestaciones | H19: Toyota Hilux 2.4 MT TSS 4x4 | I19: Operativo | J19: Instalada | K19: 471CAV1142 | L19: Instalada | M19: Instalado | N19: NA | O19: NA | P19: 45986 | Q19: NA | R19: MEL | S19: 45974 | T19: Listo | U19: Sello Rojo OK Pend. Amarillo | V19: Amarillo/Rojo | W19: Si | Y19: 45945 | AC19: 1 | AE19: 45992 | AG19: 45945 | AH19: 1 | AI19: =IF($AT19>TODAY(),0,IF(OR($Y19="Eliminada",$Y19="En Revision"),$Y19,IF($Y19<>"Eliminada",IF($Y19>TODAY(),(TODAY()-$AT19)/($Y19-$AT19),1),0))) -> 1 | AJ19: =IF(AH19=1,"Terminada",IF(AH19<AI19,"Atrasado", "A Tiempo")) -> Terminada | AK19: =IF($AJ19="Eliminada",-2,IF($AJ19="Terminada",2,IF($AJ19="A Tiempo",1,IF($AJ19="En Revision",0,-1)))) -> 2 | AM19: Camioneta puede ser manejada por Jeffrey Troncoso, el estara en turno de contingencia el 01.12.2025 | AN19: Camioneta Operativa | AP19: 06.01.26 a las 13:00Hrs: Camioneta será trasladada a Tattersall para Correctivo a las 14:30. La moverán al taller de cables mientras (No marcará Ibutton, el correctivo es para eso) | AT19: 45989 | AX19: Unidad en MEL, en coordinación traslado a Antofagasta para montaje Radio base y ECAS. (27 al 30.10) ECAS 03 al 10.11.2025 | AY19: Proyectada Bajada de MEL 03.11.2025
B20: 4 | C20: Camioneta 4 | D20: Camioneta | E20: Estandar Tattersall Mina | F20: VGLL 99 | G20: Salas y Subestaciones | H20: Toyota Hilux 2.4 MT TSS 4x4 | I20: Pendiente. En uso Bbosch | J20: Instalada | K20: 471CAV2163 | L20: Instalada | M20: Instalado | N20: NA | O20: NA | P20: 45986 | Q20: NA | R20: MEL | S20: 45978 | T20: Listo | U20: Pendiente ECAS y Sellos Amarillo / Rojo | V20: Amarillo/Rojo | W20: Si | Y20: 45945 | AC20: 1 | AE20: 45992 | AG20: 45945 | AH20: 1 | AI20: =IF($AT20>TODAY(),0,IF(OR($Y20="Eliminada",$Y20="En Revision"),$Y20,IF($Y20<>"Eliminada",IF($Y20>TODAY(),(TODAY()-$AT20)/($Y20-$AT20),1),0))) -> 1 | AJ20: =IF(AH20=1,"Terminada",IF(AH20<AI20,"Atrasado", "A Tiempo")) -> Terminada | AK20: =IF($AJ20="Eliminada",-2,IF($AJ20="Terminada",2,IF($AJ20="A Tiempo",1,IF($AJ20="En Revision",0,-1)))) -> 2 | AM20: Camioneta debe ser trasladada para validacion de sellos. Se presentara como Sello Rojo en MEL 02.12.2025 | AN20: Camioneta Operativa | AT20: 45989 | AY20: Proyectada Bajada de MEL 03.11.2025
B21: 5 | C21: Camioneta 5 | D21: Camioneta | E21: Estandar Tattersall Mina | F21: VGLL 43 | G21: Distribución y Cables | H21: Toyota Hilux 2.4 MT TSS 4x4 | I21: Pendiente. En uso Bbosch | J21: 45985 | K21: 471CBH0765 | L21: Instalada | M21: Instalado | N21: NA | O21: NA | P21: 45986 | Q21: NA | R21: MEL | S21: 45978 | T21: Listo | U21: Sello Rojo OK Pend. Amarillo Pendiente ECAS | V21: Amarillo/Rojo | Y21: 45945 | AC21: 1 | AE21: 45992 | AG21: 45945 | AH21: 1 | AI21: =IF($AT21>TODAY(),0,IF(OR($Y21="Eliminada",$Y21="En Revision"),$Y21,IF($Y21<>"Eliminada",IF($Y21>TODAY(),(TODAY()-$AT21)/($Y21-$AT21),1),0))) -> 1 | AJ21: =IF(AH21=1,"Terminada",IF(AH21<AI21,"Atrasado", "A Tiempo")) -> Terminada | AK21: =IF($AJ21="Eliminada",-2,IF($AJ21="Terminada",2,IF($AJ21="A Tiempo",1,IF($AJ21="En Revision",0,-1)))) -> 2 | AM21: Se van a ingresar a Tatersall Antofagasta para Traslado a MEL 01.12.2025 | Gestionar Priorizarizacion | AN21: Camioneta Operativa | AT21: 45989 | AX21: Unidad en MEL, en coordinación traslado a Antofagasta para montaje Radio base y ECAS. (27 al 30.10) ECAS 03 al 10.11.2025 | AY21: Proyectada Bajada de MEL 03.11.2025 | BI21: VGLL 99 | BJ21: En STN | BK21: Franklin Godoy | BL21: 0.6875
B22: 6 | C22: Camioneta 6 | D22: Camioneta | E22: Estandar Tattersall Mina | F22: VGLL 77 | G22: Distribución y Cables | H22: Toyota Hilux 2.4 MT TSS 4x4 | I22: Pendiente. En uso Bbosch | J22: 45985 | K22: 471CBH0767 | L22: Instalada | M22: Instalado | N22: NA | O22: NA | P22: 45986 | Q22: NA | R22: MEL | S22: 45978 | T22: Listo | U22: Sello Rojo OK Pend. Amarillo | V22: Amarillo/Rojo | Y22: 45945 | AC22: 1 | AE22: 45992 | AG22: 45945 | AH22: 1 | AI22: =IF($AT22>TODAY(),0,IF(OR($Y22="Eliminada",$Y22="En Revision"),$Y22,IF($Y22<>"Eliminada",IF($Y22>TODAY(),(TODAY()-$AT22)/($Y22-$AT22),1),0))) -> 1 | AJ22: =IF(AH22=1,"Terminada",IF(AH22<AI22,"Atrasado", "A Tiempo")) -> Terminada | AK22: =IF($AJ22="Eliminada",-2,IF($AJ22="Terminada",2,IF($AJ22="A Tiempo",1,IF($AJ22="En Revision",0,-1)))) -> 2 | AM22: Se van a ingresar a Tatersall Antofagasta para Traslado a MEL 01.12.2025 | Gestionar Priorizarizacion | AN22: Camioneta Operativa | AT22: 45989 | AU22: 1843081 | AX22: Unidad en MEL, en coordinación traslado a Antofagasta para montaje Radio base y ECAS. (27 al 30.10) ECAS 03 al 10.11.2025 | AY22: Proyectada Bajada de MEL 03.11.2025 | BI22: VGLL 80 | BJ22: En STN | BK22: C. Carmona | BL22: 0.6875
B23: 7 | C23: Camioneta 7 | D23: Camioneta | E23: Estandar Tattersall Sitios Remotos | F23: VGLP 45 | G23: Transmisión | H23: Toyota Hilux 2.4 MT TSS 4x4 | I23: NA | J23: Instalada | K23: 471CAV1139 | L23: Instalada | M23: Instalado | N23: NA | O23: NA | P23: 45986 | Q23: NA | R23: STN | S23: 45978 | T23: Listo | U23: Sello Naranjo OK Pend. Azul | V23: Naranjo/Azul | Y23: 45945 | AC23: 1 | AE23: 45992 | AG23: 45945 | AH23: 1 | AI23: =IF($AT23>TODAY(),0,IF(OR($Y23="Eliminada",$Y23="En Revision"),$Y23,IF($Y23<>"Eliminada",IF($Y23>TODAY(),(TODAY()-$AT23)/($Y23-$AT23),1),0))) -> 1 | AJ23: =IF(AH23=1,"Terminada",IF(AH23<AI23,"Atrasado", "A Tiempo")) -> Terminada | AK23: =IF($AJ23="Eliminada",-2,IF($AJ23="Terminada",2,IF($AJ23="A Tiempo",1,IF($AJ23="En Revision",0,-1)))) -> 2 | AM23: Subida de Camioneta desde Afta a MEL, Personal Turno B (Ropa de Trabajo TB) | Instrumentos. Victor Aguayo - Jorge Guerrero | AN23: Camioneta Operativa | AT23: 45993 | AY23: Unidad en Dependencias de STN, Rev. Estandar MEL | BI23: OK | BJ23: En STN | BK23: Wilmar Forero | BL23: 0.66666667
B24: 8 | C24: Camioneta 8 | D24: Camioneta | E24: Estandar Tattersall Sitios Remotos | F24: VGLS 40 | G24: Salas y Subestaciones | H24: Toyota Hilux 2.4 MT TSS 4x4 | I24: NA | J24: Instalada | K24: 471CAV1140 | L24: Instalada | M24: Instalado | N24: NA | O24: NA | P24: 45986 | Q24: NA | R24: MEL | S24: 45978 | T24: Listo | U24: Sello Naranjo OK Pend. Azul | V24: Naranjo/Azul | X24: Si | Y24: 45945 | AC24: 1 | AE24: 45992 | AG24: 45945 | AH24: 1 | AI24: =IF($AT24>TODAY(),0,IF(OR($Y24="Eliminada",$Y24="En Revision"),$Y24,IF($Y24<>"Eliminada",IF($Y24>TODAY(),(TODAY()-$AT24)/($Y24-$AT24),1),0))) -> 1 | AJ24: =IF(AH24=1,"Terminada",IF(AH24<AI24,"Atrasado", "A Tiempo")) -> Terminada | AK24: =IF($AJ24="Eliminada",-2,IF($AJ24="Terminada",2,IF($AJ24="A Tiempo",1,IF($AJ24="En Revision",0,-1)))) -> 2 | AM24: Subida de Camioneta desde Afta a MEL, Personal Turno B (Ropa de Trabajo TB) | Instrumentos. Victor Aguayo - Jorge Guerrero | AN24: Camioneta Operativa | AT24: 45989 | AY24: Unidad en Dependencias de STN, Rev. Estandar MEL
